Workbook

Sheet README
A1: United Airlines Holdings (UAL) — модель оценки
A3: Дата анализа: 14.10.2026. Цена акции: $103,23 — закрытие NASDAQ 13.10.2026 (Yahoo Finance chart API; совпадает с отчётом Zacks/Yahoo от 13.10.2026).
A4: Последняя опубликованная отчётность: 10-Q за 2 кв. 2026 (подан в SEC 16.07.2026) и 8-K с пресс-релизом от 15.07.2026.
A5: Отчёт за 3 кв. 2026 на дату анализа НЕ вышел: компания назначила публикацию на 20.10.2026 после закрытия рынка (звонок 21.10.2026). Данные 3 кв. в модели не используются.
A6: Пиры: TTM на 30.06.2026 (последний общий период для всех). Delta уже отчиталась за 3 кв. (09.10.2026), но для сопоставимости берём её данные на 30.06.2026.
A8: Цвета: синий шрифт — вводные значения (факты из отчётности и допущения); чёрный — формулы. Жёлтая заливка — ключевые результаты.
A9: Типы данных в колонке источника: [Ф] факт из отчётности; [Д] допущение аналитика; [О] оценка аналитика (расчёт на основе фактов).
A10: Все финансовые показатели — млн долл. США, если не указано иное. Удельные показатели (TRASM, CASM) — центы на ASM.
A12: Листы:
A13: Hist — исходные данные 2019–2025, 1П25, 1П26, TTM 2К26 и квартальные данные (факты с указанием документа SEC).
A14: Metrics — производные метрики (формулы): загрузка, доходность, маржи, качество прибыли, долговая нагрузка.
A15: Assumptions — ВСЕ допущения прогноза в одном месте: рынок, WACC, драйверы по трём сценариям, терминальные параметры, вероятности.
... A23: Debt — график погашения, ликвидность, рейтинги, сравнение долговой нагрузки через EBITDAR и через операционный денежный поток, поставки самолётов.

Sheet Hist
A1: Исходные данные UAL (факты из отчётности SEC)
A3: Показатель | B3: Ед. | C3: 2019 | D3: 2020 | E3: 2021 | F3: 2022 | G3: 2023 | H3: 2024 | I3: 2025 | J3: 1П25 | K3: 1П26 | L3: TTM 2К26 | M3: Источник / тип
A4: Операционные показатели
A5: Пассажиро-кресло-мили (ASM) | B5: млн | C5: 284999 | D5: 122804 | E5: 178684 | F5: 247858 | G5: 291333 | H5: 311185 | I5: 330284 | J5: 159503 | K5: 164977 | L5: =I5+K5-J5 -> 335758 | M5: [Ф] Пресс-релизы 8-K по итогам 4 кв.: FY2019–2021 (8-K 19.01.2022), FY2022 (17.01.2023), FY2023 (22.01.2024), FY2024 (21.01.2025), FY2025 (20.01.2026); 1П — 8-K 15.07.2026
A6: Пассажиро-мили (RPM) | B6: млн | C6: 239360 | D6: 73883 | E6: 128979 | F6: 206791 | G6: 244435 | H6: 258503 | I6: 271619 | J6: 129604 | K6: 136150 | L6: =I6+K6-J6 -> 278165 | M6: [Ф] Пресс-релизы 8-K по итогам 4 кв.: FY2019–2021 (8-K 19.01.2022), FY2022 (17.01.2023), FY2023 (22.01.2024), FY2024 (21.01.2025), FY2025 (20.01.2026); 1П — 8-K 15.07.2026
A7: Пассажиры | B7: тыс. | C7: 162443 | D7: 57761 | E7: 104082 | F7: 144300 | G7: 164927 | H7: 173603 | I7: 181053 | J7: 86992 | K7: 91178 | L7: =I7+K7-J7 -> 185239 | M7: [Ф] Пресс-релизы 8-K по итогам 4 кв.: FY2019–2021 (8-K 19.01.2022), FY2022 (17.01.2023), FY2023 (22.01.2024), FY2024 (21.01.2025), FY2025 (20.01.2026); 1П — 8-K 15.07.2026
A8: CASM-ex (отчётный, non-GAAP) | B8: центы | C8: 10.21 | D8: 17.13 | E8: 12.96 | F8: 11.73 | G8: 12.03 | H8: 12.58 | I8: 12.64 | J8: 12.74 | K8: 13.51 | M8: [Ф] Пресс-релизы 8-K по итогам 4 кв.: FY2019–2021 (8-K 19.01.2022), FY2022 (17.01.2023), FY2023 (22.01.2024), FY2024 (21.01.2025), FY2025 (20.01.2026); 1П — 8-K 15.07.2026; без топлива, участия в прибыли, спецстатей и сторонних услуг
A9: Средняя цена топлива | B9: $/галлон | C9: 2.09 | D9: 1.57 | E9: 2.11 | F9: 3.63 | G9: 3.01 | H9: 2.65 | I9: 2.44 | J9: 2.43 | K9: 3.53 | M9: [Ф] Пресс-релизы 8-K по итогам 4 кв.: FY2019–2021 (8-K 19.01.2022), FY2022 (17.01.2023), FY2023 (22.01.2024), FY2024 (21.01.2025), FY2025 (20.01.2026); 1П — 8-K 15.07.2026
A10: Потреблено топлива | B10: млн галл. | C10: 4292 | D10: 2004 | E10: 2729 | F10: 3608 | G10: 4205 | H10: 4444 | I10: 4663 | J10: 2254 | K10: 2312 | L10: =I10+K10-J10 -> 4721 | M10: [Ф] Пресс-релизы 8-K по итогам 4 кв.: FY2019–2021 (8-K 19.01.2022), FY2022 (17.01.2023), FY2023 (22.01.2024), FY2024 (21.01.2025), FY2025 (20.01.2026); 1П — 8-K 15.07.2026
A11: Самолётов в парке на конец периода | B11: шт. | C11: 1372 | D11: 1287 | E11: 1344 | F11: 1338 | G11: 1358 | H11: 1406 | I11: 1490 | J11: 1473 | K11: 1552 | L11: =K11 -> 1552 | M11: [Ф] Пресс-релизы 8-K по итогам 4 кв.: FY2019–2021 (8-K 19.01.2022), FY2022 (17.01.2023), FY2023 (22.01.2024), FY2024 (21.01.2025), FY2025 (20.01.2026); 1П — 8-K 15.07.2026
A12: Численность персонала на конец периода | B12: тыс. | C12: 95.9 | D12: 74.4 | E12: 84.1 | F12: 92.8 | G12: 103.3 | H12: 107.3 | I12: 113.2 | J12: 111.3 | K12: 117.5 | L12: =K12 -> 117.5 | M12: [Ф] Пресс-релизы 8-K по итогам 4 кв.: FY2019–2021 (8-K 19.01.2022), FY2022 (17.01.2023), FY2023 (22.01.2024), FY2024 (21.01.2025), FY2025 (20.01.2026); 1П — 8-K 15.07.2026
A13: Средняя длина рейса | B13: миль | C13: 1460 | D13: 1307 | E13: 1315 | F13: 1437 | G13: 1479 | H13: 1490 | I13: 1488 | J13: 1482 | K13: 1462 | M13: [Ф] Пресс-релизы 8-K по итогам 4 кв.: FY2019–2021 (8-K 19.01.2022), FY2022 (17.01.2023), FY2023 (22.01.2024), FY2024 (21.01.2025), FY2025 (20.01.2026); 1П — 8-K 15.07.2026
A14: Грузовые тонно-мили (RTM) | B14: млн | C14: 3329 | D14: 2711 | E14: 3285 | F14: 3041 | G14: 3159 | H14: 3604 | I14: 3626 | J14: 1774 | K14: 1810 | L14: =I14+K14-J14 -> 3662 | M14: [Ф] Пресс-релизы 8-K по итогам 4 кв.: FY2019–2021 (8-K 19.01.2022), FY2022 (17.01.2023), FY2023 (22.01.2024), FY2024 (21.01.2025), FY2025 (20.01.2026); 1П — 8-K 15.07.2026
A15: Отчёт о прибылях и убытках
A16: Пассажирская выручка | B16: $ млн | C16: 39625 | D16: 11805 | E16: 20197 | F16: 40032 | G16: 49046 | H16: 51829 | I16: 53438 | J16: 25696 | K16: 29267 | L16: =I16+K16-J16 -> 57009 | M16: [Ф] Пресс-релизы 8-K по итогам 4 кв.: FY2019–2021 (8-K 19.01.2022), FY2022 (17.01.2023), FY2023 (22.01.2024), FY2024 (21.01.2025), FY2025 (20.01.2026); 1П — 8-K 15.07.2026
A17: Грузовая выручка | B17: $ млн | C17: 1179 | D17: 1648 | E17: 2349 | F17: 2171 | G17: 1495 | H17: 1743 | I17: 1779 | J17: 859 | K17: 949 | L17: =I17+K17-J17 -> 1869 | M17: [Ф] Пресс-релизы 8-K по итогам 4 кв.: FY2019–2021 (8-K 19.01.2022), FY2022 (17.01.2023), FY2023 (22.01.2024), FY2024 (21.01.2025), FY2025 (20.01.2026); 1П — 8-K 15.07.2026; 10-K 2025 (Cargo 1,779/1,743)
A18: Прочая операционная выручка | B18: $ млн | C18: 2455 | D18: 1902 | E18: 2088 | F18: 2752 | G18: 3176 | H18: 3491 | I18: 3853 | J18: 1893 | K18: 2064 | L18: =I18+K18-J18 -> 4024 | M18: [Ф] Пресс-релизы 8-K по итогам 4 кв.: FY2019–2021 (8-K 19.01.2022), FY2022 (17.01.2023), FY2023 (22.01.2024), FY2024 (21.01.2025), FY2025 (20.01.2026); 1П — 8-K 15.07.2026
A19: Итого операционная выручка | B19: $ млн | C19: =SUM(C16:C18) -> 43259 | D19: =SUM(D16:D18) -> 15355 | E19: =SUM(E16:E18) -> 24634 | F19: =SUM(F16:F18) -> 44955 | G19: =SUM(G16:G18) -> 53717 | H19: =SUM(H16:H18) -> 57063 | I19: =SUM(I16:I18) -> 59070 | J19: =SUM(J16:J18) -> 28448 | ... L19: =SUM(L16:L18) -> 62902 | M19: формула; сверка с отчётной выручкой ниже
A20: Справочно: выручка по отчётности | B20: $ млн | C20: 43259 | D20: 15355 | E20: 24634 | F20: 44955 | G20: 53717 | H20: 57063 | I20: 59070 | J20: 28448 | K20: 32280 | L20: =I20+K20-J20 -> 62902 | M20: [Ф] XBRL RevenueFromContractWithCustomer (10-K/10-Q)
A21: в т.ч. выручка от партнёров MileagePlus в прочей выручке | B21: $ млн | G21: 2700 | H21: 2900 | I21: 3200 | J21: 1600 | K21: 1800 | L21: =I21+K21-J21 -> 3400 | M21: [Ф] 10-K 2025 прим. 2 ($3.2/2.9/2.7 млрд); 10-Q 2К26 ($1.8/1.6 млрд за 6 мес.). 2019–2022: не найдено в использованных документах
A22: Мили начислены (отложенная выручка, прирост) | B22: $ млн | H22: 3563 | I22: 3883 | M22: [Ф] 10-K 2025, roll-forward Frequent flyer deferred revenue
A23: Мили погашены на перелёты (признано в пасс. выручке) | B23: $ млн | H23: 3150 | I23: 3414 | M23: [Ф] 10-K 2025, roll-forward Frequent flyer deferred revenue
A24: Расходы на топливо | B24: $ млн | C24: 8953 | D24: 3153 | E24: 5755 | F24: 13113 | G24: 12651 | H24: 11756 | I24: 11396 | J24: 5476 | K24: 8150 | L24: =I24+K24-J24 -> 14070 | M24: [Ф] Пресс-релизы 8-K по итогам 4 кв.: FY2019–2021 (8-K 19.01.2022), FY2022 (17.01.2023), FY2023 (22.01.2024), FY2024 (21.01.2025), FY2025 (20.01.2026); 1П — 8-K 15.07.2026
A25: Зарплата и связанные расходы | B25: $ млн | C25: 12071 | D25: 9522 | E25: 9566 | F25: 11466 | G25: 14787 | H25: 16678 | I25: 17647 | J25: 8568 | K25: 9248 | L25: =I25+K25-J25 -> 18327 | M25: [Ф] Пресс-релизы 8-K по итогам 4 кв.: FY2019–2021 (8-K 19.01.2022), FY2022 (17.01.2023), FY2023 (22.01.2024), FY2024 (21.01.2025), FY2025 (20.01.2026); 1П — 8-K 15.07.2026
A26: Амортизация (D&A) | B26: $ млн | C26: 2288 | D26: 2488 | E26: 2485 | F26: 2456 | G26: 2671 | H26: 2928 | I26: 2939 | J26: 1461 | K26: 1518 | L26: =I26+K26-J26 -> 2996 | M26: [Ф] XBRL DepreciationDepletionAndAmortization (10-K/10-Q)
A27: Аренда самолётов (aircraft rent) | B27: $ млн | C27: 288 | D27: 198 | E27: 228 | F27: 252 | G27: 197 | H27: 193 | I27: 252 | J27: 118 | K27: 195 | L27: =I27+K27-J27 -> 329 | M27: [Ф] XBRL AircraftRental (10-K/10-Q)
A28: Специальные статьи (доход) в опер. расходах | B28: $ млн | C28: 246 | D28: -2616 | E28: -3367 | F28: 140 | G28: 949 | H28: 112 | I28: 259 | J28: 340 | K28: -534 | L28: =I28+K28-J28 -> -615 | M28: [Ф] Пресс-релизы 8-K по итогам 4 кв.: FY2019–2021 (8-K 19.01.2022), FY2022 (17.01.2023), FY2023 (22.01.2024), FY2024 (21.01.2025), FY2025 (20.01.2026); 1П — 8-K 15.07.2026; 2020–21 — гос. поддержка PSP (кредит)
A29: Участие сотрудников в прибыли (profit sharing) | B29: $ млн | C29: 485 | D29: 0 | E29: 0 | F29: 133 | G29: 681 | H29: 713 | I29: 704 | J29: 231 | K29: 150 | L29: =I29+K29-J29 -> 623 | M29: [Ф] Пресс-релизы 8-K по итогам 4 кв.: FY2019–2021 (8-K 19.01.2022), FY2022 (17.01.2023), FY2023 (22.01.2024), FY2024 (21.01.2025), FY2025 (20.01.2026); 1П — 8-K 15.07.2026; 2019 — [О] 0,17 цента × ASM из таблицы CASM-ex
A30: Операционная прибыль (GAAP) | B30: $ млн | C30: 4301 | D30: -6359 | E30: -1022 | F30: 2337 | G30: 4211 | H30: 5096 | I30: 4713 | J30: 1932 | K30: 2093 | L30: =I30+K30-J30 -> 4874 | M30: [Ф] XBRL OperatingIncomeLoss
A31: Скорр. операционная прибыль (non-GAAP) | B31: $ млн | C31: 4547 | D31: -8975 | E31: -4389 | F31: 2477 | G31: 5160 | H31: 5208 | I31: 4972 | J31: 2272 | K31: 1559 | L31: =I31+K31-J31 -> 4259 | M31: [Ф] Пресс-релизы 8-K по итогам 4 кв.: FY2019–2021 (8-K 19.01.2022), FY2022 (17.01.2023), FY2023 (22.01.2024), FY2024 (21.01.2025), FY2025 (20.01.2026); 1П — 8-K 15.07.2026
A32: Процентные расходы (валовые) | B32: $ млн | C32: 731 | D32: 1063 | E32: 1657 | F32: 1778 | G32: 1956 | H32: 1629 | I32: 1373 | J32: 717 | K32: 670 | L32: =I32+K32-J32 -> 1326 | M32: [Ф] Пресс-релизы 8-K по итогам 4 кв.: FY2019–2021 (8-K 19.01.2022), FY2022 (17.01.2023), FY2023 (22.01.2024), FY2024 (21.01.2025), FY2025 (20.01.2026); 1П — 8-K 15.07.2026
A33: Чистые процентные расходы (за вычетом капитализ. % и % доходов) | B33: $ млн | C33: 513 | D33: 942 | E33: 1541 | F33: 1375 | G33: 947 | H33: 676 | I33: 556 | J33: 288 | K33: 273 | L33: =I33+K33-J33 -> 541 | M33: [Ф] Пресс-релизы 8-K по итогам 4 кв.: FY2019–2021 (8-K 19.01.2022), FY2022 (17.01.2023), FY2023 (22.01.2024), FY2024 (21.01.2025), FY2025 (20.01.2026); 1П — 8-K 15.07.2026 (сверка Adj. EBITDA)
A34: Налог на прибыль | B34: $ млн | C34: 905 | D34: -1753 | E34: -593 | F34: 253 | G34: 769 | H34: 1019 | I34: 953 | J34: 366 | K34: 393 | L34: =I34+K34-J34 -> 980 | M34: [Ф] XBRL IncomeTaxExpenseBenefit
A35: Чистая прибыль (GAAP) | B35: $ млн | C35: 3009 | D35: -7069 | E35: -1964 | F35: 737 | G35: 2618 | H35: 3149 | I35: 3353 | J35: 1361 | K35: 1504 | L35: =I35+K35-J35 -> 3496 | M35: [Ф] XBRL NetIncomeLoss
... A37: Скорр. разводнённая прибыль на акцию | B37: $ | C37: 12.05 | D37: -27.57 | E37: -13.94 | F37: 2.52 | G37: 10.05 | H37: 10.61 | I37: 10.62 | J37: 4.75 | K37: 3.18 | L37: =I37+K37-J37 -> 9.05 | M37: [Ф] Пресс-релизы 8-K по итогам 4 кв.: FY2019–2021 (8-K 19.01.2022), FY2022 (17.01.2023), FY2023 (22.01.2024), FY2024 (21.01.2025), FY2025 (20.01.2026); 1П — 8-K 15.07.2026
A38: Разводнённое средневзв. число акций | B38: млн | C38: 259.9 | D38: 279.4 | E38: 321.9 | F38: 330.1 | G38: 331.9 | H38: 333.2 | I38: 328.5 | J38: 330.1 | K38: 326.7 | M38: [Ф] Пресс-релизы 8-K по итогам 4 кв.: FY2019–2021 (8-K 19.01.2022), FY2022 (17.01.2023), FY2023 (22.01.2024), FY2024 (21.01.2025), FY2025 (20.01.2026); 1П — 8-K 15.07.2026
A39: Скорр. EBITDA (non-GAAP, определение UAL) | B39: $ млн | C39: 6808 | D39: -6430 | E39: -1783 | F39: 4948 | G39: 7938 | H39: 8211 | I39: 8076 | J39: 3809 | K39: 3133 | L39: =I39+K39-J39 -> 7400 | M39: [Ф] Пресс-релизы 8-K по итогам 4 кв.: FY2019–2021 (8-K 19.01.2022), FY2022 (17.01.2023), FY2023 (22.01.2024), FY2024 (21.01.2025), FY2025 (20.01.2026); 1П — 8-K 15.07.2026
A40: Фиксированная часть операционной аренды (новое определение EBITDAR UAL) | B40: $ млн | H40: 855 | I40: 894 | J40: 433 | K40: 514 | L40: =I40+K40-J40 -> 975 | M40: [Ф] 8-K 20.01.2026 и 15.07.2026; ранее не раскрывалось
A41: Денежные потоки
A42: Операционный денежный поток (CFO) | B42: $ млн | C42: 6909 | D42: -4133 | E42: 2067 | F42: 6066 | G42: 6911 | H42: 9445 | I42: 8431 | J42: 5927 | K42: 6409 | L42: =I42+K42-J42 -> 8913 | M42: [Ф] XBRL NetCashProvidedByOperatingActivities
A43: Капзатраты (GAAP, за вычетом возврата депозитов) | B43: $ млн | C43: 4528 | D43: 1727 | E43: 2107 | F43: 4819 | G43: 7171 | H43: 5615 | I43: 5874 | J43: 2520 | K43: 3015 | L43: =I43+K43-J43 -> 6369 | M43: [Ф] XBRL PaymentsToAcquireProductiveAssets
A44: Скорр. капзатраты (вкл. приобретённое в долг/лизинг) | B44: $ млн | D44: 3449 | E44: 2907 | F44: 4838 | G44: 7948 | H44: 6263 | I44: 6266 | J44: 2468 | K44: 3167 | L44: =I44+K44-J44 -> 6965 | M44: [Ф] Пресс-релизы 8-K по итогам 4 кв.: FY2019–2021 (8-K 19.01.2022), FY2022 (17.01.2023), FY2023 (22.01.2024), FY2024 (21.01.2025), FY2025 (20.01.2026); 1П — 8-K 15.07.2026; 2024 — пересчитано в релизе 20.01.2026; 2019 — не найдено
A45: FCF по определению UAL (non-GAAP) | B45: $ млн | D45: -7753 | E45: -1508 | F45: 1224 | G45: -1037 | H45: 4270 | I45: 2710 | J45: 3442 | K45: 3225 | L45: =I45+K45-J45 -> 2493 | M45: [Ф] Пресс-релизы 8-K по итогам 4 кв.: FY2019–2021 (8-K 19.01.2022), FY2022 (17.01.2023), FY2023 (22.01.2024), FY2024 (21.01.2025), FY2025 (20.01.2026); 1П — 8-K 15.07.2026; методика изменена в 2025 (2024 пересчитан 3,424→4,270)
A46: Выкуп акций | B46: $ млн | C46: 1645 | D46: 353 | E46: 0 | F46: 0 | G46: 0 | H46: 162 | I46: 637 | J46: 589 | K46: 27 | L46: =I46+K46-J46 -> 75 | M46: [Ф] XBRL PaymentsForRepurchaseOfCommonStock; 10-Q 2К26
A47: Баланс (на конец периода)
A48: Денежные средства и эквиваленты | B48: $ млн | C48: 2762 | D48: 11269 | E48: 18283 | F48: 7166 | G48: 6058 | H48: 8769 | I48: 5942 | J48: 9354 | K48: 10166 | L48: =K48 -> 10166 | M48: [Ф] XBRL CashAndCashEquivalents; 8-K 15.07.2026
A49: Краткосрочные инвестиции | B49: $ млн | C49: 2182 | D49: 414 | E49: 123 | F49: 9248 | G49: 8330 | H49: 5706 | I49: 6298 | J49: 6262 | K49: 6471 | L49: =K49 -> 6471 | M49: [Ф] XBRL ShortTermInvestments
A50: Долг, финансовая аренда и прочие фин. обязательства | B50: $ млн | C50: 14818 | D50: 27153 | E50: 33658 | F50: 32280 | G50: 31660 | H50: 28656 | I50: 24988 | J50: 27079 | K50: 26464 | L50: =K50 -> 26464 | M50: [Ф] 2022–1П26: 8-K (таблица Adjusted total debt); 2019–2021: [О] XBRL LongTermDebt тек.+долгоср. + FinanceLeaseLiability
A51: Обязательства по операционной аренде | B51: $ млн | C51: 5632 | D51: 5598 | E51: 5708 | F51: 5020 | G51: 5079 | H51: 4977 | I51: 6048 | J51: 5707 | K51: 7204 | L51: =K51 -> 7204 | M51: [Ф] XBRL OperatingLeaseLiability; 8-K
A52: Пенсионные и пострабочие обязательства (долгоср.) | B52: $ млн | C52: 1446 | D52: 2460 | E52: 1920 | F52: 1418 | G52: 1605 | H52: 1233 | I52: 1058 | J52: 1199 | K52: 1074 | L52: =K52 -> 1074 | M52: [Ф] 2022+: 8-K; 2019–2021: XBRL DefinedBenefitPensionPlanLiabilitiesNoncurrent (только пенсии — определение уже)
A53: Авансы за билеты (air traffic liability) | B53: $ млн | D53: 4833 | E53: 6354 | F53: 7555 | G53: 6704 | H53: 7561 | I53: 8131 | K53: 10752 | L53: =K53 -> 10752 | M53: [Ф] Балансы в 8-K по итогам 4 кв. и 15.07.2026; 2019 — не найдено
A54: Отложенная выручка MileagePlus (тек.+долгоср.) | B54: $ млн | D54: 5975 | E54: 6282 | F54: 6675 | G54: 7143 | H54: 7441 | I54: 7777 | K54: 7971 | L54: =K54 -> 7971 | M54: [Ф] Балансы в 8-K; 10-K 2025 roll-forward
A55: Итого активы | B55: $ млн | C55: 52611 | D55: 59548 | E55: 68175 | F55: 67358 | G55: 71104 | H55: 74083 | I55: 76448 | K55: 84569 | L55: =K55 -> 84569 | M55: [Ф] XBRL Assets; 8-K 15.07.2026
A56: Итого краткосрочные обязательства | B56: $ млн | I56: 26133 | K56: 27764 | L56: =K56 -> 27764 | M56: [Ф] 8-K 15.07.2026 (баланс)
A57: Итого долгосрочные обязательства | B57: $ млн | I57: 35033 | K57: 40108 | L57: =K57 -> 40108 | M57: [Ф] 8-K 15.07.2026 (баланс)
A58: Собственный капитал | B58: $ млн | C58: 11531 | D58: 5960 | E58: 5029 | F58: 6896 | G58: 9324 | H58: 12675 | I58: 15282 | K58: 16697 | L58: =K58 -> 16697 | M58: [Ф] XBRL StockholdersEquity
A59: Проверка баланса: активы − обязательства − капитал (должно быть 0) | B59: $ млн | I59: =I55-I56-I57-I58 -> 0 | K59: =K55-K56-K57-K58 -> 0 | M59: формула
A60: Акций в обращении на конец периода | B60: млн | C60: 251.2 | D60: 311.8 | E60: 323.8 | F60: 326.9 | G60: 328 | H60: 327.9 | I60: 323.5 | K60: 324.6 | L60: =K60 -> 324.6 | M60: [Ф] XBRL CommonStockSharesOutstanding; 1П26 — обложка 10-Q (324 583 772 на 09.07.2026)
A61: Цена акции на конец периода | B61: $ | C61: 88.09 | D61: 43.25 | E61: 43.78 | F61: 37.7 | G61: 41.26 | H61: 97.1 | I61: 111.82 | J61: 79.63 | K61: 135.99 | M61: [Ф] Yahoo Finance, месячные цены закрытия (декабрь / июнь)
A63: TTM 2К26 = 2025 + 1П26 − 1П25 для потоков; для остатков — значение на 30.06.2026. Пустая ячейка = данные не найдены в использованных первичных источниках.
A65: Квартальные данные | B65: Ед. | C65: 2К25 | D65: 3К25 | E65: 4К25 | F65: 1К26 | G65: 2К26 | M65: Источник / тип
A66: ASM | B66: млн | C66: 84347 | D66: 87417 | E66: 83365 | F66: 77698 | G66: 87279 | M66: [Ф] 8-K: 16.07.2025, 15.10.2025, 20.01.2026, 21.04.2026, 15.07.2026
A67: Выручка | B67: $ млн | C67: 15236 | D67: 15225 | E67: 15397 | F67: 14608 | G67: 17672 | M67: [Ф] 8-K: 16.07.2025, 15.10.2025, 20.01.2026, 21.04.2026, 15.07.2026
A68: TRASM | B68: центы | C68: 18.06 | D68: 17.42 | E68: 18.47 | F68: 18.8 | G68: 20.25 | M68: [Ф] 8-K: 16.07.2025, 15.10.2025, 20.01.2026, 21.04.2026, 15.07.2026
A69: CASM-ex | B69: центы | C69: 12.36 | D69: 12.15 | E69: 12.94 | F69: 13.95 | G69: 13.12 | M69: [Ф] 8-K: 16.07.2025, 15.10.2025, 20.01.2026, 21.04.2026, 15.07.2026
A70: Цена топлива | B70: $/галл. | C70: 2.34 | D70: 2.43 | E70: 2.49 | F70: 2.78 | G70: 4.19 | M70: [Ф] 8-K: 16.07.2025, 15.10.2025, 20.01.2026, 21.04.2026, 15.07.2026
A71: Скорр. операционная маржа | B71: % | C71: 0.116 | D71: 0.087 | E71: 0.09 | F71: 0.042 | G71: 0.054 | M71: [Ф] 8-K: 16.07.2025, 15.10.2025, 20.01.2026, 21.04.2026, 15.07.2026
A72: Скорр. маржа до налога | B72: % | C72: 0.11 | D72: 0.08 | E72: 0.085 | F72: 0.034 | G72: 0.048 | M72: [Ф] 8-K: 16.07.2025, 15.10.2025, 20.01.2026, 21.04.2026, 15.07.2026
A73: Скорр. EPS | B73: $ | C73: 3.87 | D73: 2.78 | E73: 3.1 | F73: 1.19 | G73: 1.99 | M73: [Ф] 8-K: 16.07.2025, 15.10.2025, 20.01.2026, 21.04.2026, 15.07.2026
A74: Справочно: спот Gulf Coast jet (среднее за квартал) | B74: $/галл. | C74: 2 | D74: 2.12 | E74: 2.13 | F74: 2.66 | G74: 3.64 | M74: [Ф] FRED MJFUELUSGULF (EIA), среднее месячных значений

Sheet Metrics
A1: Производные метрики UAL (формулы на основе листа Hist)
A3: Метрика | B3: Ед. | C3: 2019 | D3: 2020 | E3: 2021 | F3: 2022 | G3: 2023 | H3: 2024 | I3: 2025 | J3: 1П25 | K3: 1П26 | L3: TTM 2К26 | M3: Источник / тип
A4: Операционные
A5: Загрузка (load factor) = RPM / ASM | B5: % | C5: =Hist!$C$6/Hist!$C$5 -> 0.8398626 | D5: =Hist!$D$6/Hist!$D$5 -> 0.6016335 | E5: =Hist!$E$6/Hist!$E$5 -> 0.72182736 | F5: =Hist!$F$6/Hist!$F$5 -> 0.83431239 | G5: =Hist!$G$6/Hist!$G$5 -> 0.8390227 | H5: =Hist!$H$6/Hist!$H$5 -> 0.83070521 | I5: =Hist!$I$6/Hist!$I$5 -> 0.82238013 | J5: =Hist!$J$6/Hist!$J$5 -> 0.81254898 | K5: =Hist!$K$6/Hist!$K$5 -> 0.82526655 | L5: =Hist!$L$6/Hist!$L$5 -> 0.82846872 | M5: формула
A6: Доходность (yield) = пасс. выручка / RPM | B6: центы | C6: =Hist!$C$16/Hist!$C$6*100 -> 16.554562 | D6: =Hist!$D$16/Hist!$D$6*100 -> 15.977965 | E6: =Hist!$E$16/Hist!$E$6*100 -> 15.659138 | F6: =Hist!$F$16/Hist!$F$6*100 -> 19.358676 | G6: =Hist!$G$16/Hist!$G$6*100 -> 20.065048 | H6: =Hist!$H$16/Hist!$H$6*100 -> 20.049671 | I6: =Hist!$I$16/Hist!$I$6*100 -> 19.673881 | J6: =Hist!$J$16/Hist!$J$6*100 -> 19.826549 | K6: =Hist!$K$16/Hist!$K$6*100 -> 21.496144 | L6: =Hist!$L$16/Hist!$L$6*100 -> 20.49467 | M6: формула
A7: PRASM = пасс. выручка / ASM | B7: центы | C7: =Hist!$C$16/Hist!$C$5*100 -> 13.903558 | D7: =Hist!$D$16/Hist!$D$5*100 -> 9.6128791 | E7: =Hist!$E$16/Hist!$E$5*100 -> 11.303194 | F7: =Hist!$F$16/Hist!$F$5*100 -> 16.151183 | G7: =Hist!$G$16/Hist!$G$5*100 -> 16.835031 | H7: =Hist!$H$16/Hist!$H$5*100 -> 16.655366 | I7: =Hist!$I$16/Hist!$I$5*100 -> 16.179409 | J7: =Hist!$J$16/Hist!$J$5*100 -> 16.110042 | K7: =Hist!$K$16/Hist!$K$5*100 -> 17.740049 | L7: =Hist!$L$16/Hist!$L$5*100 -> 16.979193 | M7: формула
A8: TRASM (RASM) = выручка / ASM | B8: центы | C8: =Hist!$C$19/Hist!$C$5*100 -> 15.17865 | D8: =Hist!$D$19/Hist!$D$5*100 -> 12.503664 | E8: =Hist!$E$19/Hist!$E$5*100 -> 13.786349 | F8: =Hist!$F$19/Hist!$F$5*100 -> 18.137401 | G8: =Hist!$G$19/Hist!$G$5*100 -> 18.438351 | H8: =Hist!$H$19/Hist!$H$5*100 -> 18.337323 | I8: =Hist!$I$19/Hist!$I$5*100 -> 17.884608 | J8: =Hist!$J$19/Hist!$J$5*100 -> 17.835401 | K8: =Hist!$K$19/Hist!$K$5*100 -> 19.566364 | L8: =Hist!$L$19/Hist!$L$5*100 -> 18.734327 | M8: формула
A9: CASM = опер. расходы / ASM | B9: центы | C9: =(Hist!$C$19-Hist!$C$30)/Hist!$C$5*100 -> 13.669522 | D9: =(Hist!$D$19-Hist!$D$30)/Hist!$D$5*100 -> 17.681834 | E9: =(Hist!$E$19-Hist!$E$30)/Hist!$E$5*100 -> 14.358309 | F9: =(Hist!$F$19-Hist!$F$30)/Hist!$F$5*100 -> 17.194523 | G9: =(Hist!$G$19-Hist!$G$30)/Hist!$G$5*100 -> 16.992926 | H9: =(Hist!$H$19-Hist!$H$30)/Hist!$H$5*100 -> 16.699712 | I9: =(Hist!$I$19-Hist!$I$30)/Hist!$I$5*100 -> 16.457655 | J9: =(Hist!$J$19-Hist!$J$30)/Hist!$J$5*100 -> 16.624139 | K9: =(Hist!$K$19-Hist!$K$30)/Hist!$K$5*100 -> 18.297702 | L9: =(Hist!$L$19-Hist!$L$30)/Hist!$L$5*100 -> 17.282686 | M9: формула
A10: CASM-ex (отчётный) | B10: центы | C10: =Hist!$C$8 -> 10.21 | D10: =Hist!$D$8 -> 17.13 | E10: =Hist!$E$8 -> 12.96 | F10: =Hist!$F$8 -> 11.73 | G10: =Hist!$G$8 -> 12.03 | H10: =Hist!$H$8 -> 12.58 | I10: =Hist!$I$8 -> 12.64 | J10: =Hist!$J$8 -> 12.74 | K10: =Hist!$K$8 -> 13.51 | M10: формула
A11: Топливо на ASM | B11: центы | C11: =Hist!$C$24/Hist!$C$5*100 -> 3.1414145 | D11: =Hist!$D$24/Hist!$D$5*100 -> 2.5675059 | E11: =Hist!$E$24/Hist!$E$5*100 -> 3.2207696 | F11: =Hist!$F$24/Hist!$F$5*100 -> 5.2905293 | G11: =Hist!$G$24/Hist!$G$5*100 -> 4.3424535 | H11: =Hist!$H$24/Hist!$H$5*100 -> 3.7778171 | I11: =Hist!$I$24/Hist!$I$5*100 -> 3.4503639 | J11: =Hist!$J$24/Hist!$J$5*100 -> 3.4331643 | K11: =Hist!$K$24/Hist!$K$5*100 -> 4.9400826 | L11: =Hist!$L$24/Hist!$L$5*100 -> 4.1905182 | M11: формула
A12: Спред TRASM − CASM | B12: центы | C12: =Metrics!$C$8-Metrics!$C$9 -> 1.5091281 | D12: =Metrics!$D$8-Metrics!$D$9 -> -5.1781701 | E12: =Metrics!$E$8-Metrics!$E$9 -> -0.57195944 | F12: =Metrics!$F$8-Metrics!$F$9 -> 0.94287858 | G12: =Metrics!$G$8-Metrics!$G$9 -> 1.445425 | H12: =Metrics!$H$8-Metrics!$H$9 -> 1.6376111 | I12: =Metrics!$I$8-Metrics!$I$9 -> 1.4269538 | J12: =Metrics!$J$8-Metrics!$J$9 -> 1.2112625 | K12: =Metrics!$K$8-Metrics!$K$9 -> 1.2686617 | L12: =Metrics!$L$8-Metrics!$L$9 -> 1.4516408 | M12: формула
A13: Топливная эффективность: галлонов на 1000 ASM | B13: галл. | C13: =Hist!$C$10/Hist!$C$5*1000 -> 15.059702 | D13: =Hist!$D$10/Hist!$D$5*1000 -> 16.318687 | E13: =Hist!$E$10/Hist!$E$5*1000 -> 15.272772 | F13: =Hist!$F$10/Hist!$F$5*1000 -> 14.556722 | G13: =Hist!$G$10/Hist!$G$5*1000 -> 14.433655 | H13: =Hist!$H$10/Hist!$H$5*1000 -> 14.280894 | I13: =Hist!$I$10/Hist!$I$5*1000 -> 14.118153 | J13: =Hist!$J$10/Hist!$J$5*1000 -> 14.131396 | K13: =Hist!$K$10/Hist!$K$5*1000 -> 14.014075 | L13: =Hist!$L$10/Hist!$L$5*1000 -> 14.060722 | M13: формула
A14: Производительность: ASM на сотрудника | B14: млн | C14: =Hist!$C$5/Hist!$C$12/1000 -> 2.9718352 | D14: =Hist!$D$5/Hist!$D$12/1000 -> 1.6505914 | E14: =Hist!$E$5/Hist!$E$12/1000 -> 2.1246611 | F14: =Hist!$F$5/Hist!$F$12/1000 -> 2.6708836 | G14: =Hist!$G$5/Hist!$G$12/1000 -> 2.8202614 | H14: =Hist!$H$5/Hist!$H$12/1000 -> 2.9001398 | I14: =Hist!$I$5/Hist!$I$12/1000 -> 2.9177032 | M14: формула
A15: Рост ASM г/г | B15: % | D15: =Hist!$D$5/Hist!$C$5-1 -> -0.56910726 | E15: =Hist!$E$5/Hist!$D$5-1 -> 0.45503404 | F15: =Hist!$F$5/Hist!$E$5-1 -> 0.38713035 | G15: =Hist!$G$5/Hist!$F$5-1 -> 0.17540285 | H15: =Hist!$H$5/Hist!$G$5-1 -> 0.068141954 | I15: =Hist!$I$5/Hist!$H$5-1 -> 0.061375066 | M15: формула
A16: Рост TRASM г/г | B16: % | D16: =Metrics!$D$8/Metrics!$C$8-1 -> -0.17623342 | E16: =Metrics!$E$8/Metrics!$D$8-1 -> 0.1025847 | F16: =Metrics!$F$8/Metrics!$E$8-1 -> 0.31560583 | G16: =Metrics!$G$8/Metrics!$F$8-1 -> 0.01659275 | H16: =Metrics!$H$8/Metrics!$G$8-1 -> -0.0054791863 | I16: =Metrics!$I$8/Metrics!$H$8-1 -> -0.024688175 | M16: формула
A17: Рост CASM-ex г/г | B17: % | D17: =Metrics!$D$10/Metrics!$C$10-1 -> 0.6777669 | E17: =Metrics!$E$10/Metrics!$D$10-1 -> -0.24343257 | F17: =Metrics!$F$10/Metrics!$E$10-1 -> -0.094907407 | G17: =Metrics!$G$10/Metrics!$F$10-1 -> 0.025575448 | H17: =Metrics!$H$10/Metrics!$G$10-1 -> 0.045719036 | I17: =Metrics!$I$10/Metrics!$H$10-1 -> 0.0047694754 | M17: формула
A18: Структура выручки
A19: Доля пассажирской выручки | B19: % | C19: =Hist!$C$16/Hist!$C$19 -> 0.91599436 | D19: =Hist!$D$16/Hist!$D$19 -> 0.76880495 | E19: =Hist!$E$16/Hist!$E$19 -> 0.81988309 | F19: =Hist!$F$16/Hist!$F$19 -> 0.89049049 | G19: =Hist!$G$16/Hist!$G$19 -> 0.91304429 | H19: =Hist!$H$16/Hist!$H$19 -> 0.90827682 | I19: =Hist!$I$16/Hist!$I$19 -> 0.90465549 | J19: =Hist!$J$16/Hist!$J$19 -> 0.90326209 | K19: =Hist!$K$16/Hist!$K$19 -> 0.90666047 | L19: =Hist!$L$16/Hist!$L$19 -> 0.90631458 | M19: формула
A20: Доля грузовой выручки | B20: % | C20: =Hist!$C$17/Hist!$C$19 -> 0.027254444 | D20: =Hist!$D$17/Hist!$D$19 -> 0.1073266 | E20: =Hist!$E$17/Hist!$E$19 -> 0.095356012 | F20: =Hist!$F$17/Hist!$F$19 -> 0.048292737 | G20: =Hist!$G$17/Hist!$G$19 -> 0.02783104 | H20: =Hist!$H$17/Hist!$H$19 -> 0.030545187 | I20: =Hist!$I$17/Hist!$I$19 -> 0.030116811 | J20: =Hist!$J$17/Hist!$J$19 -> 0.030195444 | K20: =Hist!$K$17/Hist!$K$19 -> 0.029399009 | L20: =Hist!$L$17/Hist!$L$19 -> 0.029712887 | M20: формула
A21: Доля прочей выручки | B21: % | C21: =Hist!$C$18/Hist!$C$19 -> 0.056751196 | D21: =Hist!$D$18/Hist!$D$19 -> 0.12386845 | E21: =Hist!$E$18/Hist!$E$19 -> 0.0847609 | F21: =Hist!$F$18/Hist!$F$19 -> 0.061216772 | G21: =Hist!$G$18/Hist!$G$19 -> 0.059124672 | H21: =Hist!$H$18/Hist!$H$19 -> 0.061177996 | I21: =Hist!$I$18/Hist!$I$19 -> 0.065227696 | J21: =Hist!$J$18/Hist!$J$19 -> 0.066542463 | K21: =Hist!$K$18/Hist!$K$19 -> 0.06394052 | L21: =Hist!$L$18/Hist!$L$19 -> 0.063972529 | M21: формула
A22: Партнёрская выручка MileagePlus / выручка | B22: % | G22: =Hist!$G$21/Hist!$G$19 -> 0.050263418 | H22: =Hist!$H$21/Hist!$H$19 -> 0.050821022 | I22: =Hist!$I$21/Hist!$I$19 -> 0.054173015 | J22: =Hist!$J$21/Hist!$J$19 -> 0.05624297 | K22: =Hist!$K$21/Hist!$K$19 -> 0.055762082 | L22: =Hist!$L$21/Hist!$L$19 -> 0.054052335 | M22: формула
A23: [О] MileagePlus всего ≈ партнёрская + погашения на перелёты | B23: $ млн | H23: =Hist!$H$21+Hist!$H$23 -> 6050 | I23: =Hist!$I$21+Hist!$I$23 -> 6614 | M23: [О] нижняя оценка: не включает продажу миль, учтённую при начислении
A24: [О] MileagePlus всего / выручка | B24: % | H24: =Metrics!$H$23/Hist!$H$19 -> 0.10602317 | I24: =Metrics!$I$23/Hist!$I$19 -> 0.11196885 | M24: формула
A25: Прибыльность
A26: Операционная маржа (GAAP) | B26: % | C26: =Hist!$C$30/Hist!$C$19 -> 0.099424397 | D26: =Hist!$D$30/Hist!$D$19 -> -0.4141322 | E26: =Hist!$E$30/Hist!$E$19 -> -0.041487375 | F26: =Hist!$F$30/Hist!$F$19 -> 0.051985319 | G26: =Hist!$G$30/Hist!$G$19 -> 0.078392315 | H26: =Hist!$H$30/Hist!$H$19 -> 0.089304803 | I26: =Hist!$I$30/Hist!$I$19 -> 0.079786694 | J26: =Hist!$J$30/Hist!$J$19 -> 0.067913386 | K26: =Hist!$K$30/Hist!$K$19 -> 0.06483891 | L26: =Hist!$L$30/Hist!$L$19 -> 0.077485613 | M26: формула
A27: Скорр. операционная маржа | B27: % | C27: =Hist!$C$31/Hist!$C$19 -> 0.10511108 | D27: =Hist!$D$31/Hist!$D$19 -> -0.58450016 | E27: =Hist!$E$31/Hist!$E$19 -> -0.17816839 | F27: =Hist!$F$31/Hist!$F$19 -> 0.055099544 | G27: =Hist!$G$31/Hist!$G$19 -> 0.096058976 | H27: =Hist!$H$31/Hist!$H$19 -> 0.091267546 | I27: =Hist!$I$31/Hist!$I$19 -> 0.084171322 | J27: =Hist!$J$31/Hist!$J$19 -> 0.079865017 | K27: =Hist!$K$31/Hist!$K$19 -> 0.048296159 | L27: =Hist!$L$31/Hist!$L$19 -> 0.067708499 | M27: формула
A28: Скорр. маржа до налога | B28: % | C28: =Hist!$C$36/Hist!$C$19 -> 0.094107585 | D28: =Hist!$D$36/Hist!$D$19 -> -0.64213611 | E28: =Hist!$E$36/Hist!$E$19 -> -0.23581229 | F28: =Hist!$F$36/Hist!$F$19 -> 0.024847069 | G28: =Hist!$G$36/Hist!$G$19 -> 0.080421468 | H28: =Hist!$H$36/Hist!$H$19 -> 0.080735328 | I28: =Hist!$I$36/Hist!$I$19 -> 0.077535128 | J28: =Hist!$J$36/Hist!$J$19 -> 0.072447975 | K28: =Hist!$K$36/Hist!$K$19 -> 0.04157373 | L28: =Hist!$L$36/Hist!$L$19 -> 0.061381196 | M28: формула
A29: Чистая маржа | B29: % | C29: =Hist!$C$35/Hist!$C$19 -> 0.06955778 | D29: =Hist!$D$35/Hist!$D$19 -> -0.46037121 | E29: =Hist!$E$35/Hist!$E$19 -> -0.079727206 | F29: =Hist!$F$35/Hist!$F$19 -> 0.016394172 | G29: =Hist!$G$35/Hist!$G$19 -> 0.048736899 | H29: =Hist!$H$35/Hist!$H$19 -> 0.055184621 | I29: =Hist!$I$35/Hist!$I$19 -> 0.056763162 | J29: =Hist!$J$35/Hist!$J$19 -> 0.047841676 | K29: =Hist!$K$35/Hist!$K$19 -> 0.046592317 | L29: =Hist!$L$35/Hist!$L$19 -> 0.055578519 | M29: формула
A30: EBITDAR = скорр. EBITDA + аренда самолётов (постоянное определение) | B30: $ млн | C30: =Hist!$C$39+Hist!$C$27 -> 7096 | D30: =Hist!$D$39+Hist!$D$27 -> -6232 | E30: =Hist!$E$39+Hist!$E$27 -> -1555 | F30: =Hist!$F$39+Hist!$F$27 -> 5200 | G30: =Hist!$G$39+Hist!$G$27 -> 8135 | H30: =Hist!$H$39+Hist!$H$27 -> 8404 | I30: =Hist!$I$39+Hist!$I$27 -> 8328 | J30: =Hist!$J$39+Hist!$J$27 -> 3927 | K30: =Hist!$K$39+Hist!$K$27 -> 3328 | L30: =Hist!$L$39+Hist!$L$27 -> 7729 | M30: формула; совпадает с отчётным EBITDAR UAL 2022–2024 (5,200 / 8,135 / 8,404)
A31: Справочно: EBITDAR по новому определению UAL (+ фикс. часть опер. аренды) | B31: $ млн | H31: =Hist!$H$39+Hist!$H$40 -> 9066 | I31: =Hist!$I$39+Hist!$I$40 -> 8970 | J31: =Hist!$J$39+Hist!$J$40 -> 4242 | K31: =Hist!$K$39+Hist!$K$40 -> 3647 | L31: =Hist!$L$39+Hist!$L$40 -> 8375 | M31: формула; TTM = 8,373 как в 8-K 15.07.2026
A32: Маржа EBITDAR | B32: % | C32: =Metrics!$C$30/Hist!$C$19 -> 0.16403523 | D32: =Metrics!$D$30/Hist!$D$19 -> -0.40586128 | E32: =Metrics!$E$30/Hist!$E$19 -> -0.063124137 | F32: =Metrics!$F$30/Hist!$F$19 -> 0.11567123 | G32: =Metrics!$G$30/Hist!$G$19 -> 0.15144182 | H32: =Metrics!$H$30/Hist!$H$19 -> 0.14727582 | I32: =Metrics!$I$30/Hist!$I$19 -> 0.14098527 | J32: =Metrics!$J$30/Hist!$J$19 -> 0.13804134 | K32: =Metrics!$K$30/Hist!$K$19 -> 0.10309789 | L32: =Metrics!$L$30/Hist!$L$19 -> 0.12287368 | M32: формула
A33: Денежный поток и качество прибыли
A34: FCF простой = CFO − капзатраты (GAAP) | B34: $ млн | C34: =Hist!$C$42-Hist!$C$43 -> 2381 | D34: =Hist!$D$42-Hist!$D$43 -> -5860 | E34: =Hist!$E$42-Hist!$E$43 -> -40 | F34: =Hist!$F$42-Hist!$F$43 -> 1247 | G34: =Hist!$G$42-Hist!$G$43 -> -260 | H34: =Hist!$H$42-Hist!$H$43 -> 3830 | I34: =Hist!$I$42-Hist!$I$43 -> 2557 | J34: =Hist!$J$42-Hist!$J$43 -> 3407 | K34: =Hist!$K$42-Hist!$K$43 -> 3394 | L34: =Hist!$L$42-Hist!$L$43 -> 2544 | M34: формула
A35: Маржа FCF | B35: % | C35: =Metrics!$C$34/Hist!$C$19 -> 0.05504057 | D35: =Metrics!$D$34/Hist!$D$19 -> -0.38163465 | E35: =Metrics!$E$34/Hist!$E$19 -> -0.001623772 | F35: =Metrics!$F$34/Hist!$F$19 -> 0.02773885 | G35: =Metrics!$G$34/Hist!$G$19 -> -0.0048401809 | H35: =Metrics!$H$34/Hist!$H$19 -> 0.067118799 | I35: =Metrics!$I$34/Hist!$I$19 -> 0.043287625 | J35: =Metrics!$J$34/Hist!$J$19 -> 0.11976237 | K35: =Metrics!$K$34/Hist!$K$19 -> 0.1051425 | L35: =Metrics!$L$34/Hist!$L$19 -> 0.040443865 | M35: формула
A36: CFO / чистая прибыль | B36: x | C36: =IF(Hist!$C$35>0,Hist!$C$42/Hist!$C$35,"н/п") -> 2.2961117 | D36: =IF(Hist!$D$35>0,Hist!$D$42/Hist!$D$35,"н/п") -> н/п | E36: =IF(Hist!$E$35>0,Hist!$E$42/Hist!$E$35,"н/п") -> н/п | F36: =IF(Hist!$F$35>0,Hist!$F$42/Hist!$F$35,"н/п") -> 8.2306649 | G36: =IF(Hist!$G$35>0,Hist!$G$42/Hist!$G$35,"н/п") -> 2.6398014 | H36: =IF(Hist!$H$35>0,Hist!$H$42/Hist!$H$35,"н/п") -> 2.9993649 | I36: =IF(Hist!$I$35>0,Hist!$I$42/Hist!$I$35,"н/п") -> 2.5144647 | J36: =IF(Hist!$J$35>0,Hist!$J$42/Hist!$J$35,"н/п") -> 4.3548861 | K36: =IF(Hist!$K$35>0,Hist!$K$42/Hist!$K$35,"н/п") -> 4.2613032 | L36: =IF(Hist!$L$35>0,Hist!$L$42/Hist!$L$35,"н/п") -> 2.5494851 | M36: формула
A37: Скорр. капзатраты / выручка | B37: % | D37: =Hist!$D$44/Hist!$D$19 -> 0.22461739 | E37: =Hist!$E$44/Hist!$E$19 -> 0.11800763 | F37: =Hist!$F$44/Hist!$F$19 -> 0.10761873 | G37: =Hist!$G$44/Hist!$G$19 -> 0.14796061 | H37: =Hist!$H$44/Hist!$H$19 -> 0.10975588 | I37: =Hist!$I$44/Hist!$I$19 -> 0.10607754 | J37: =Hist!$J$44/Hist!$J$19 -> 0.086754781 | K37: =Hist!$K$44/Hist!$K$19 -> 0.098110285 | L37: =Hist!$L$44/Hist!$L$19 -> 0.1107278 | M37: формула
A38: Изменение ATL + отложенной выручки MileagePlus (приток в CFO) | B38: $ млн | E38: =(Hist!$E$53+Hist!$E$54)-(Hist!$D$53+Hist!$D$54) -> 1828 | F38: =(Hist!$F$53+Hist!$F$54)-(Hist!$E$53+Hist!$E$54) -> 1594 | G38: =(Hist!$G$53+Hist!$G$54)-(Hist!$F$53+Hist!$F$54) -> -383 | H38: =(Hist!$H$53+Hist!$H$54)-(Hist!$G$53+Hist!$G$54) -> 1155 | I38: =(Hist!$I$53+Hist!$I$54)-(Hist!$H$53+Hist!$H$54) -> 906 | M38: формула
A39: CFO без прироста ATL и отложенной выручки | B39: $ млн | E39: =Hist!$E$42-Metrics!$E$38 -> 239 | F39: =Hist!$F$42-Metrics!$F$38 -> 4472 | G39: =Hist!$G$42-Metrics!$G$38 -> 7294 | H39: =Hist!$H$42-Metrics!$H$38 -> 8290 | I39: =Hist!$I$42-Metrics!$I$38 -> 7525 | M39: формула
A40: CFO без ATL / чистая прибыль | B40: x | F40: =IF(Hist!$F$35>0,Metrics!$F$39/Hist!$F$35,"н/п") -> 6.0678426 | G40: =IF(Hist!$G$35>0,Metrics!$G$39/Hist!$G$35,"н/п") -> 2.7860963 | H40: =IF(Hist!$H$35>0,Metrics!$H$39/Hist!$H$35,"н/п") -> 2.6325818 | I40: =IF(Hist!$I$35>0,Metrics!$I$39/Hist!$I$35,"н/п") -> 2.2442589 | M40: формула
A41: (ATL + отложенная выручка) / выручка | B41: % | D41: =(Hist!$D$53+Hist!$D$54)/Hist!$D$19 -> 0.70387496 | E41: =(Hist!$E$53+Hist!$E$54)/Hist!$E$19 -> 0.51294958 | F41: =(Hist!$F$53+Hist!$F$54)/Hist!$F$19 -> 0.31653876 | G41: =(Hist!$G$53+Hist!$G$54)/Hist!$G$19 -> 0.25777687 | H41: =(Hist!$H$53+Hist!$H$54)/Hist!$H$19 -> 0.26290241 | I41: =(Hist!$I$53+Hist!$I$54)/Hist!$I$19 -> 0.2693076 | M41: формула
A42: Долговая нагрузка
A43: Скорр. долг = долг + опер. аренда + пенсии | B43: $ млн | C43: =Hist!$C$50+Hist!$C$51+Hist!$C$52 -> 21896 | D43: =Hist!$D$50+Hist!$D$51+Hist!$D$52 -> 35211 | E43: =Hist!$E$50+Hist!$E$51+Hist!$E$52 -> 41286 | F43: =Hist!$F$50+Hist!$F$51+Hist!$F$52 -> 38718 | G43: =Hist!$G$50+Hist!$G$51+Hist!$G$52 -> 38344 | H43: =Hist!$H$50+Hist!$H$51+Hist!$H$52 -> 34866 | I43: =Hist!$I$50+Hist!$I$51+Hist!$I$52 -> 32094 | J43: =Hist!$J$50+Hist!$J$51+Hist!$J$52 -> 33985 | K43: =Hist!$K$50+Hist!$K$51+Hist!$K$52 -> 34742 | L43: =Hist!$L$50+Hist!$L$51+Hist!$L$52 -> 34742 | M43: формула
A44: Денежные средства + краткосрочные инвестиции | B44: $ млн | C44: =Hist!$C$48+Hist!$C$49 -> 4944 | D44: =Hist!$D$48+Hist!$D$49 -> 11683 | E44: =Hist!$E$48+Hist!$E$49 -> 18406 | F44: =Hist!$F$48+Hist!$F$49 -> 16414 | G44: =Hist!$G$48+Hist!$G$49 -> 14388 | H44: =Hist!$H$48+Hist!$H$49 -> 14475 | I44: =Hist!$I$48+Hist!$I$49 -> 12240 | J44: =Hist!$J$48+Hist!$J$49 -> 15616 | K44: =Hist!$K$48+Hist!$K$49 -> 16637 | L44: =Hist!$L$48+Hist!$L$49 -> 16637 | M44: формула
A45: Чистый скорр. долг | B45: $ млн | C45: =Metrics!$C$43-Metrics!$C$44 -> 16952 | D45: =Metrics!$D$43-Metrics!$D$44 -> 23528 | E45: =Metrics!$E$43-Metrics!$E$44 -> 22880 | F45: =Metrics!$F$43-Metrics!$F$44 -> 22304 | G45: =Metrics!$G$43-Metrics!$G$44 -> 23956 | H45: =Metrics!$H$43-Metrics!$H$44 -> 20391 | I45: =Metrics!$I$43-Metrics!$I$44 -> 19854 | J45: =Metrics!$J$43-Metrics!$J$44 -> 18369 | K45: =Metrics!$K$43-Metrics!$K$44 -> 18105 | L45: =Metrics!$L$43-Metrics!$L$44 -> 18105 | M45: формула; 1П26 = 18,105 как в 8-K 15.07.2026
A46: Чистый скорр. долг / EBITDAR | B46: x | C46: =IF(Metrics!$C$30>0,Metrics!$C$45/Metrics!$C$30,"н/п") -> 2.3889515 | D46: =IF(Metrics!$D$30>0,Metrics!$D$45/Metrics!$D$30,"н/п") -> н/п | E46: =IF(Metrics!$E$30>0,Metrics!$E$45/Metrics!$E$30,"н/п") -> н/п | F46: =IF(Metrics!$F$30>0,Metrics!$F$45/Metrics!$F$30,"н/п") -> 4.2892308 | G46: =IF(Metrics!$G$30>0,Metrics!$G$45/Metrics!$G$30,"н/п") -> 2.9448064 | H46: =IF(Metrics!$H$30>0,Metrics!$H$45/Metrics!$H$30,"н/п") -> 2.4263446 | I46: =IF(Metrics!$I$30>0,Metrics!$I$45/Metrics!$I$30,"н/п") -> 2.3840058 | L46: =IF(Metrics!$L$30>0,Metrics!$L$45/Metrics!$L$30,"н/п") -> 2.3424764 | M46: формула
A47: Справочно: чистый долг / EBITDAR (новое опр. UAL) | B47: x | I47: =Metrics!$I$45/Metrics!$I$31 -> 2.2133779 | L47: =Metrics!$L$45/Metrics!$L$31 -> 2.161791 | M47: формула
A48: Чистый скорр. долг / CFO | B48: x | C48: =IF(Hist!$C$42>0,Metrics!$C$45/Hist!$C$42,"н/п") -> 2.4536112 | D48: =IF(Hist!$D$42>0,Metrics!$D$45/Hist!$D$42,"н/п") -> н/п | E48: =IF(Hist!$E$42>0,Metrics!$E$45/Hist!$E$42,"н/п") -> 11.069182 | F48: =IF(Hist!$F$42>0,Metrics!$F$45/Hist!$F$42,"н/п") -> 3.6768876 | G48: =IF(Hist!$G$42>0,Metrics!$G$45/Hist!$G$42,"н/п") -> 3.466358 | H48: =IF(Hist!$H$42>0,Metrics!$H$45/Hist!$H$42,"н/п") -> 2.1589201 | I48: =IF(Hist!$I$42>0,Metrics!$I$45/Hist!$I$42,"н/п") -> 2.3548808 | L48: =IF(Hist!$L$42>0,Metrics!$L$45/Hist!$L$42,"н/п") -> 2.0313026 | M48: формула
A49: Чистый скорр. долг / CFO без прироста ATL | B49: x | F49: =Metrics!$F$45/Metrics!$F$39 -> 4.9874776 | G49: =Metrics!$G$45/Metrics!$G$39 -> 3.2843433 | H49: =Metrics!$H$45/Metrics!$H$39 -> 2.4597105 | I49: =Metrics!$I$45/Metrics!$I$39 -> 2.6384053 | M49: формула
A50: Покрытие процентов = скорр. опер. прибыль / валовые % | B50: x | C50: =Hist!$C$31/Hist!$C$32 -> 6.2202462 | D50: =Hist!$D$31/Hist!$D$32 -> -8.4430856 | E50: =Hist!$E$31/Hist!$E$32 -> -2.6487628 | F50: =Hist!$F$31/Hist!$F$32 -> 1.3931384 | G50: =Hist!$G$31/Hist!$G$32 -> 2.6380368 | H50: =Hist!$H$31/Hist!$H$32 -> 3.1970534 | I50: =Hist!$I$31/Hist!$I$32 -> 3.6212673 | L50: =Hist!$L$31/Hist!$L$32 -> 3.2119155 | M50: формула
A51: Покрытие фикс. платежей = EBITDAR / (валовые % + аренда самолётов) | B51: x | C51: =Metrics!$C$30/(Hist!$C$32+Hist!$C$27) -> 6.9636899 | D51: =Metrics!$D$30/(Hist!$D$32+Hist!$D$27) -> -4.9421094 | E51: =Metrics!$E$30/(Hist!$E$32+Hist!$E$27) -> -0.82493369 | F51: =Metrics!$F$30/(Hist!$F$32+Hist!$F$27) -> 2.5615764 | G51: =Metrics!$G$30/(Hist!$G$32+Hist!$G$27) -> 3.7784487 | H51: =Metrics!$H$30/(Hist!$H$32+Hist!$H$27) -> 4.6125137 | I51: =Metrics!$I$30/(Hist!$I$32+Hist!$I$27) -> 5.1249231 | L51: =Metrics!$L$30/(Hist!$L$32+Hist!$L$27) -> 4.6700906 | M51: формула
A52: Собственный капитал / активы | B52: % | C52: =Hist!$C$58/Hist!$C$55 -> 0.2191747 | D52: =Hist!$D$58/Hist!$D$55 -> 0.10008732 | E52: =Hist!$E$58/Hist!$E$55 -> 0.073766043 | F52: =Hist!$F$58/Hist!$F$55 -> 0.10237834 | G52: =Hist!$G$58/Hist!$G$55 -> 0.13113186 | H52: =Hist!$H$58/Hist!$H$55 -> 0.17109188 | I52: =Hist!$I$58/Hist!$I$55 -> 0.19990059 | K52: =Hist!$K$58/Hist!$K$55 -> 0.19743641 | M52: формула
A53: Нормализация через цикл
A54: [О] Средняя скорр. опер. маржа: 2019, 2022–2025 (без пандемии 2020–21) | B54: % | I54: =AVERAGE(Metrics!$C$27,Metrics!$F$27,Metrics!$G$27,Metrics!$H$27,Metrics!$I$27) -> 0.086341693 | M54: [О] mid-cycle маржа; 2022 — год восстановления, включён как слабая точка цикла
A55: [О] То же без 2022 | B55: % | I55: =AVERAGE(Metrics!$C$27,Metrics!$G$27,Metrics!$H$27,Metrics!$I$27) -> 0.09415223 | M55: [О] верхняя граница нормальной маржи

Sheet Assumptions
A1: Допущения модели (все вводные прогноза — здесь)
A3: Параметр | B3: Ед. | C3: 2026E | D3: 2027E | E3: 2028E | F3: 2029E | G3: 2030E | H3: 2031E | I3: 2032E | J3: Обоснование / тип
A4: Рынок и оценка
A5: Цена акции UAL | B5: $ | C5: 103.23 | J5: [Ф] закрытие 13.10.2026, Yahoo Finance chart API (NASDAQ)
A6: Разводнённое число акций | B6: млн | C6: 326.6 | J6: [Ф] средневзвешенное разводнённое 2К26 (8-K 15.07.2026); базовое 324,6 млн на 09.07.2026
A7: Безрисковая ставка (UST 10 лет) | B7: % | C7: 0.0524 | J7: [Ф] FRED DGS10, 09.10.2026 = 5,24%
A8: Премия за риск рынка акций | B8: % | C8: 0.05 | J8: [Д] 5,0%: середина типичного диапазона 4,5–5,5% (Damodaran, implied ERP для США); не проверено на дату
A9: Стоимость долга до налога (вкл. аренду) | B9: % | C9: 0.065 | J9: [Д] UST10 5,24% + ~1,25 п.п. спред BB+/Ba1; проверка: ноты 2031 (5,375%) размещены 02.2026 при UST10 4,29% → спред ~1,1 п.п.
A10: Налоговая ставка | B10: % | C10: 0.22 | J10: [Д] эффективная ставка 2025 = 953/(3,353+953) = 22,1%; 1П26 = 20,7%
A11: PV налогового щита от убытков прошлых лет (NOL) | B11: $ млн | C11: 2000 | J11: [О] 10-K 2025: NOL $10,6 млрд (федеральные) → налоговый эффект $2,3 млрд вкл. штаты; использование за ~3–4 года, дисконт ~8,5% → ~$2,0 млрд
A12: FCFF 1П26 фактический (FCF UAL + чистые % после налога) | B12: $ млн | C12: =Hist!$K$45+Hist!$K$33*(1-Assumptions!$C$10) -> 3437.94 | J12: [О] 3,225 + 273×(1−t); вычитается из FCFF 2026E, т.к. дисконтируем с 30.06.2026
A13: Вес метода Гордона в итоговой DCF-оценке | B13: % | C13: 0.5 | J13: [Д] 50/50 Гордон и выходной мультипликатор
A14: Общие операционные параметры (все сценарии)
A15: Изменение расхода топлива на ASM (обновление парка) | B15: % | C15: -0.01 | D15: -0.01 | E15: -0.01 | F15: -0.01 | G15: -0.01 | H15: -0.01 | I15: -0.01 | J15: [Д] 2019→2025: 15,06→14,12 галл./1000 ASM = −1,1% в год (Metrics)
A16: Расходы на сторонние услуги (не в CASM-ex) | B16: % выручки | C16: 0.0045 | D16: 0.0045 | E16: 0.0045 | F16: 0.0045 | G16: 0.0045 | H16: 0.0045 | I16: 0.0045 | J16: [Д] 1П26: 132/32,280 = 0,41%
A17: Участие в прибыли | B17: % от EBIT до него | C17: 0.12 | D17: 0.12 | E17: 0.12 | F17: 0.12 | G17: 0.12 | H17: 0.12 | I17: 0.12 | J17: [Д] калибровка: 2025 704/(4,972+704) = 12,4%; 2024 12,0%
A18: D&A | B18: % выручки | C18: 0.048 | D18: 0.048 | E18: 0.048 | F18: 0.048 | G18: 0.048 | H18: 0.048 | I18: 0.048 | J18: [Д] TTM 2К26: 2,996/62,902 = 4,8%
A19: Фиксированная часть опер. аренды (для EBITDAR) | B19: % выручки | C19: 0.0155 | D19: 0.0155 | E19: 0.0155 | F19: 0.0155 | G19: 0.0155 | H19: 0.0155 | I19: 0.0155 | J19: [Д] TTM 2К26: 975/62,902 = 1,55%
A20: Ставка процента, заложенная в аренду | B20: % | C20: 0.065 | J20: [Д] = стоимость долга; часть арендного платежа, переносимая в финансирование
A21: Приток оборотного капитала (ATL, мили) | B21: % от прироста выручки | C21: 0.1 | D21: 0.1 | E21: 0.1 | F21: 0.1 | G21: 0.1 | H21: 0.1 | I21: 0.1 | J21: [Д] (ATL+отлож. выручка)/выручка = 27% (2025); с учётом оттоков по прочим статьям берём 10%
A22: Чистые процентные расходы (для EPS) | B22: $ млн | C22: 550 | D22: 550 | E22: 550 | F22: 550 | G22: 550 | H22: 550 | I22: 550 | J22: [Д] TTM 2К26 = 541 (8-K 15.07.2026)
A23: Скорр. капзатраты 2026E | B23: $ млн | C23: 7500 | J23: [Ф] прогноз UAL ~$7,5 млрд (Investor Update 15.07.2026)
A24: Терминальный рост (Гордон) | B24: % | C24: 0.025 | J24: [Д] ≈ номинальный рост ВВП США в долгосроке ниже текущей инфляции
A25: Доходность новых инвестиций в терминале (RONIC) | B25: % | C25: 0.1 | J25: [Д] чуть выше WACC: реинвестиции = g/RONIC = 25% NOPAT
A27: Сценарий: Пессимистичный (рецессия + дорогое топливо)
A28: Рост ASM | B28: % | C28: 0.025 | D28: -0.02 | E28: 0.02 | F28: 0.04 | G28: 0.04 | H28: 0.035 | I28: 0.03 | J28: [Д] см. логику базового сценария
A29: Базовый рост TRASM (без топлива) | B29: % | C29: 0.025 | D29: -0.05 | E29: 0.05 | F29: 0.045 | G29: 0.035 | H29: 0.027 | I29: 0.027 | J29: [Д] см. логику базового сценария
A30: Перенос топлива в тариф | B30: доля | C30: 0.8 | D30: 0.6 | E30: 1 | F30: 1 | G30: 1 | H30: 1 | I30: 1 | J30: [Д] см. логику базового сценария
A31: Рост CASM-ex | B31: % | C31: 0.055 | D31: 0.035 | E31: 0.01 | F31: 0.015 | G31: 0.02 | H31: 0.027 | I31: 0.027 | J31: [Д] см. логику базового сценария
A32: Цена топлива (all-in) | B32: $/галл. | C32: 3.97 | D32: 4.1 | E32: 3.4 | F32: 3.1 | G32: 3.1 | H32: 3.1 | I32: 3.1 | J32: [Д] см. логику базового сценария
A33: Скорр. капзатраты | B33: % выручки | D33: 0.08 | E33: 0.08 | F33: 0.09 | G33: 0.1 | H33: 0.1 | I33: 0.1 | J33: [Д] см. логику базового сценария
A34: Сценарий: Базовый
A35: Рост ASM | B35: % | C35: 0.025 | D35: 0.04 | E35: 0.05 | F35: 0.05 | G35: 0.045 | H35: 0.04 | I35: 0.035 | J35: [Д] 2026: 1П +3,4%, 2П ~+1,6% (прогноз UAL 0…+2%) (прогноз UAL 21.04.2026, сокращение из-за топлива); далее — поставки 787/MAX/A321 (10-Q: ожидаемые поставки)
A36: Базовый рост TRASM (без топлива) | B36: % | C36: 0.025 | D36: 0.02 | E36: 0.025 | F36: 0.025 | G36: 0.025 | H36: 0.025 | I36: 0.025 | J36: [Д] рост TRASM без переноса топлива; история 2019–2025: ~2,5% в год (TRASM 15,18→17,88, из них ~0,3 цента — топливо)
A37: Перенос топлива в тариф | B37: доля | C37: 0.8 | D37: 0.75 | E37: 1 | F37: 1 | G37: 1 | H37: 1 | I37: 1 | J37: [Д] доля изменения топливных затрат на ASM, переносимая в тариф; UAL: 1П ~50%, 3 кв. 80–90%, 4 кв. 100% (Investor Update 15.07.2026)
A38: Рост CASM-ex | B38: % | C38: 0.055 | D38: 0.025 | E38: 0.02 | F38: 0.023 | G38: 0.027 | H38: 0.027 | I38: 0.027 | J38: [Д] 2026: 1П +6,0% (сокращение мощностей, новые договоры AFA/IAM); 2027+ — инфляция зарплат против эффекта масштаба
A39: Цена топлива (all-in) | B39: $/галл. | C39: 3.97 | D39: 3.3 | E39: 3 | F39: 2.9 | G39: 2.9 | H39: 2.95 | I39: 3 | J39: [Д] 2026: 1П $3,53 факт, 2П ~$4,40 (спот Gulf Coast сент.–окт. $4,34–4,39 + ~$0,35 логистика/налоги); 2027 — EIA STEO окт. 2026 (Brent $84)
A40: Скорр. капзатраты | B40: % выручки | D40: 0.115 | E40: 0.12 | F40: 0.12 | G40: 0.11 | H40: 0.105 | I40: 0.1 | J40: [Д] 2026 — прогноз UAL $7,5 млрд; далее % выручки по контрактным обязательствам 10-K (2027–2030: $5,6–9,0 млрд в год только по заказам)
A41: Сценарий: Оптимистичный (премиальный спрос и маржа)
A42: Рост ASM | B42: % | C42: 0.025 | D42: 0.05 | E42: 0.06 | F42: 0.06 | G42: 0.05 | H42: 0.045 | I42: 0.04 | J42: [Д] см. логику базового сценария
A43: Базовый рост TRASM (без топлива) | B43: % | C43: 0.025 | D43: 0.035 | E43: 0.03 | F43: 0.025 | G43: 0.025 | H43: 0.025 | I43: 0.025 | J43: [Д] см. логику базового сценария
A44: Перенос топлива в тариф | B44: доля | C44: 0.8 | D44: 0.6 | E44: 1 | F44: 1 | G44: 1 | H44: 1 | I44: 1 | J44: [Д] см. логику базового сценария
A45: Рост CASM-ex | B45: % | C45: 0.055 | D45: 0.02 | E45: 0.02 | F45: 0.025 | G45: 0.027 | H45: 0.027 | I45: 0.027 | J45: [Д] см. логику базового сценария
A46: Цена топлива (all-in) | B46: $/галл. | C46: 3.97 | D46: 2.9 | E46: 2.75 | F46: 2.7 | G46: 2.75 | H46: 2.8 | I46: 2.85 | J46: [Д] см. логику базового сценария
A47: Скорр. капзатраты | B47: % выручки | D47: 0.115 | E47: 0.12 | F47: 0.12 | G47: 0.11 | H47: 0.105 | I47: 0.1 | J47: [Д] см. логику базового сценария
A48: Вероятности сценариев и выходные мультипликаторы
A49: Вероятность: пессимистичный | B49: % | C49: 0.25 | J49: [Д] Brent >$100, UST10 >5%, ослабление спроса — реальный риск 2027
A50: Вероятность: базовый | B50: % | C50: 0.5 | J50: [Д]
A51: Вероятность: оптимистичный | B51: % | C51: 0.25 | J51: [Д]
A52: Проверка: сумма вероятностей | B52: % | C52: =Assumptions!$C$49+Assumptions!$C$50+Assumptions!$C$51 -> 1 | J52: формула (должно быть 100%)
A53: Порог рекомендации Buy: потенциал выше | B53: % | C53: 0.15 | J53: [Д] правило рейтинга
A54: Порог рекомендации Sell: потенциал ниже | B54: % | C54: -0.1 | J54: [Д] правило рейтинга

Sheet Beta
A1: Бета UAL: месячные доходности против S&P 500, 60 месяцев (10.2021–10.2026)
A3: Месяц | B3: UAL (скорр. цена) | C3: S&P 500 | D3: Доходн. UAL | E3: Доходн. S&P | G3: Бета (SLOPE) | H3: =SLOPE(D5:D64,E5:E64) -> 1.3605204
A4: 2021-10 | B4: 46.14 | C4: 4605.38 | G4: Скорр. бета (Блюм) | H4: =0.67*H3+0.33 -> 1.2415487
A5: 2021-11 | B5: 42.26 | C5: 4567 | D5: =B5/B4-1 -> -0.084091894 | E5: =C5/C4-1 -> -0.0083337314
A6: 2021-12 | B6: 43.78 | C6: 4766.18 | D6: =B6/B5-1 -> 0.035967818 | E6: =C6/C5-1 -> 0.043612875 | G6: Источник: Yahoo Finance chart API, месячные цены закрытия (adjclose); последняя точка — 13.10.2026 (неполный месяц).
A7: 2022-01 | B7: 42.88 | C7: 4515.55 | D7: =B7/B6-1 -> -0.020557332 | E7: =C7/C6-1 -> -0.052585089 | G7: Для справки (тот же расчёт): DAL 1,42; AAL 1,44; LUV 1,23; ALK 1,42; JBLU 1,84 — медиана пиров 1,42.
A8: 2022-02 | B8: 44.4 | C8: 4373.94 | D8: =B8/B7-1 -> 0.035447761 | E8: =C8/C7-1 -> -0.031360521
A9: 2022-03 | B9: 46.36 | C9: 4530.41 | D9: =B9/B8-1 -> 0.044144144 | E9: =C9/C8-1 -> 0.035773239
A10: 2022-04 | B10: 50.5 | C10: 4131.93 | D10: =B10/B9-1 -> 0.089301122 | E10: =C10/C9-1 -> -0.087956719
A11: 2022-05 | B11: 47.63 | C11: 4132.15 | D11: =B11/B10-1 -> -0.056831683 | E11: =C11/C10-1 -> 5.3243884e-05
A12: 2022-06 | B12: 35.42 | C12: 3785.38 | D12: =B12/B11-1 -> -0.25635104 | E12: =C12/C11-1 -> -0.083919993
A13: 2022-07 | B13: 36.75 | C13: 4130.29 | D13: =B13/B12-1 -> 0.037549407 | E13: =C13/C12-1 -> 0.091116348
A14: 2022-08 | B14: 35.01 | C14: 3955 | D14: =B14/B13-1 -> -0.047346939 | E14: =C14/C13-1 -> -0.042440119
A15: 2022-09 | B15: 32.53 | C15: 3585.62 | D15: =B15/B14-1 -> -0.070836904 | E15: =C15/C14-1 -> -0.093395702
A16: 2022-10 | B16: 43.08 | C16: 3871.98 | D16: =B16/B15-1 -> 0.32431602 | E16: =C16/C15-1 -> 0.079863455
A17: 2022-11 | B17: 44.17 | C17: 4080.11 | D17: =B17/B16-1 -> 0.025301764 | E17: =C17/C16-1 -> 0.05375286
A18: 2022-12 | B18: 37.7 | C18: 3839.5 | D18: =B18/B17-1 -> -0.14647951 | E18: =C18/C17-1 -> -0.058971449
A19: 2023-01 | B19: 48.96 | C19: 4076.6 | D19: =B19/B18-1 -> 0.29867374 | E19: =C19/C18-1 -> 0.061752832
... A64: 2026-10 | B64: 103.23 | C64: 7805.45 | D64: =B64/B63-1 -> -0.069580892 | E64: =C64/C63-1 -> 0.020114905

Sheet WACC
A1: Ставка дисконтирования (WACC) с учётом аренды
A3: Компонент | B3: Ед. | C3: Значение | D3: Источник / тип
A4: Безрисковая ставка | B4: % | C4: =Assumptions!$C$7 -> 0.0524
A5: Бета (5 лет, месячная, сырая) | B5: x | C5: =Beta!$H$3 -> 1.3605204 | D5: лист Beta; скорр. по Блюму ~1,24 — ниже, даёт WACC ~8,2%
A6: Премия за риск | B6: % | C6: =Assumptions!$C$8 -> 0.05
A7: Стоимость собственного капитала = Rf + β × ERP | B7: % | C7: =WACC!$C$4+WACC!$C$5*WACC!$C$6 -> 0.12042602
A8: Стоимость долга до налога | B8: % | C8: =Assumptions!$C$9 -> 0.065
A9: Стоимость долга после налога | B9: % | C9: =WACC!$C$8*(1-Assumptions!$C$10) -> 0.0507
A10: Рыночная капитализация (цена × разводн. акции) | B10: $ млн | C10: =Assumptions!$C$5*Assumptions!$C$6 -> 33714.918
A11: Скорр. долг 30.06.2026 (долг + опер. аренда + пенсии) | B11: $ млн | C11: =Metrics!$K$43 -> 34742 | D11: Metrics; аренда включена в долг
A12: Доля собственного капитала | B12: % | C12: =WACC!$C$10/(WACC!$C$10+WACC!$C$11) -> 0.49249833
A13: Доля долга | B13: % | C13: =1-WACC!$C$12 -> 0.50750167
A14: WACC | B14: % | C14: =WACC!$C$12*WACC!$C$7+WACC!$C$13*WACC!$C$9 -> 0.085039949
A15: Чистый скорр. долг 30.06.2026 (вычитается из EV) | B15: $ млн | C15: =Metrics!$K$45 -> 18105

Sheet DCF
A1: DCF (FCFF) — три сценария, 2026E–2032E; дата оценки 30.06.2026 (баланс), середина периода
A3: Пессимистичный (рецессия + дорогое топливо) | B3: Ед. | C3: 2025A | D3: 2026E | E3: 2027E | F3: 2028E | G3: 2029E | H3: 2030E | I3: 2031E | J3: 2032E | K3: Источник / тип
A4: ASM | B4: млн | C4: =Hist!$I$5 -> 330284 | D4: =DCF!$C$4*(1+Assumptions!$C$28) -> 338541.1 | E4: =DCF!$D$4*(1+Assumptions!$D$28) -> 331770.28 | F4: =DCF!$E$4*(1+Assumptions!$E$28) -> 338405.68 | G4: =DCF!$F$4*(1+Assumptions!$F$28) -> 351941.91 | H4: =DCF!$G$4*(1+Assumptions!$G$28) -> 366019.59 | I4: =DCF!$H$4*(1+Assumptions!$H$28) -> 378830.27 | J4: =DCF!$I$4*(1+Assumptions!$I$28) -> 390195.18
A5: Галлонов на 1000 ASM | B5: галл. | C5: =Metrics!$I$13 -> 14.118153 | D5: =DCF!$C$5*(1+Assumptions!$C$15) -> 13.976971 | E5: =DCF!$D$5*(1+Assumptions!$D$15) -> 13.837202 | F5: =DCF!$E$5*(1+Assumptions!$E$15) -> 13.69883 | G5: =DCF!$F$5*(1+Assumptions!$F$15) -> 13.561841 | H5: =DCF!$G$5*(1+Assumptions!$G$15) -> 13.426223 | I5: =DCF!$H$5*(1+Assumptions!$H$15) -> 13.291961 | J5: =DCF!$I$5*(1+Assumptions!$I$15) -> 13.159041
A6: Цена топлива | B6: $/галл. | C6: =Hist!$I$9 -> 2.44 | D6: =Assumptions!$C$32 -> 3.97 | E6: =Assumptions!$D$32 -> 4.1 | F6: =Assumptions!$E$32 -> 3.4 | G6: =Assumptions!$F$32 -> 3.1 | H6: =Assumptions!$G$32 -> 3.1 | I6: =Assumptions!$H$32 -> 3.1 | J6: =Assumptions!$I$32 -> 3.1
A7: Топливо на ASM | B7: центы | C7: =DCF!$C$5*DCF!$C$6/10 -> 3.4448293 | D7: =DCF!$D$5*DCF!$D$6/10 -> 5.5488576 | E7: =DCF!$E$5*DCF!$E$6/10 -> 5.6732527 | F7: =DCF!$F$5*DCF!$F$6/10 -> 4.6576021 | G7: =DCF!$G$5*DCF!$G$6/10 -> 4.2041708 | H7: =DCF!$H$5*DCF!$H$6/10 -> 4.1621291 | I7: =DCF!$I$5*DCF!$I$6/10 -> 4.1205078 | J7: =DCF!$J$5*DCF!$J$6/10 -> 4.0793027
A8: TRASM = TRASM(t−1)×(1+базовый рост) + перенос×Δтопливо/ASM | B8: центы | C8: =Metrics!$I$8 -> 17.884608 | D8: =DCF!$C$8*(1+Assumptions!$C$29)+Assumptions!$C$30*(DCF!$D$7-DCF!$C$7) -> 20.014946 | E8: =DCF!$D$8*(1+Assumptions!$D$29)+Assumptions!$D$30*(DCF!$E$7-DCF!$D$7) -> 19.088836 | F8: =DCF!$E$8*(1+Assumptions!$E$29)+Assumptions!$E$30*(DCF!$F$7-DCF!$E$7) -> 19.027627 | G8: =DCF!$F$8*(1+Assumptions!$F$29)+Assumptions!$F$30*(DCF!$G$7-DCF!$F$7) -> 19.430439 | H8: =DCF!$G$8*(1+Assumptions!$G$29)+Assumptions!$G$30*(DCF!$H$7-DCF!$G$7) -> 20.068463 | I8: =DCF!$H$8*(1+Assumptions!$H$29)+Assumptions!$H$30*(DCF!$I$7-DCF!$H$7) -> 20.56869 | J8: =DCF!$I$8*(1+Assumptions!$I$29)+Assumptions!$I$30*(DCF!$J$7-DCF!$I$7) -> 21.08284
A9: Выручка | B9: $ млн | C9: =Hist!$I$19 -> 59070 | D9: =DCF!$D$4*DCF!$D$8/100 -> 67758.819 | E9: =DCF!$E$4*DCF!$E$8/100 -> 63331.084 | F9: =DCF!$F$4*DCF!$F$8/100 -> 64390.572 | G9: =DCF!$G$4*DCF!$G$8/100 -> 68383.859 | H9: =DCF!$H$4*DCF!$H$8/100 -> 73454.505 | I9: =DCF!$I$4*DCF!$I$8/100 -> 77920.424 | J9: =DCF!$J$4*DCF!$J$8/100 -> 82264.224
A10: CASM-ex | B10: центы | C10: =Metrics!$I$10 -> 12.64 | D10: =DCF!$C$10*(1+Assumptions!$C$31) -> 13.3352 | E10: =DCF!$D$10*(1+Assumptions!$D$31) -> 13.801932 | F10: =DCF!$E$10*(1+Assumptions!$E$31) -> 13.939951 | G10: =DCF!$F$10*(1+Assumptions!$F$31) -> 14.149051 | H10: =DCF!$G$10*(1+Assumptions!$G$31) -> 14.432032 | I10: =DCF!$H$10*(1+Assumptions!$H$31) -> 14.821696 | J10: =DCF!$I$10*(1+Assumptions!$I$31) -> 15.221882
A11: Нетопливные расходы (CASM-ex × ASM) | B11: $ млн | D11: =DCF!$D$4*DCF!$D$10/100 -> 45145.133 | E11: =DCF!$E$4*DCF!$E$10/100 -> 45790.708 | F11: =DCF!$F$4*DCF!$F$10/100 -> 47173.588 | G11: =DCF!$G$4*DCF!$G$10/100 -> 49796.439 | H11: =DCF!$H$4*DCF!$H$10/100 -> 52824.063 | I11: =DCF!$I$4*DCF!$I$10/100 -> 56149.073 | J11: =DCF!$J$4*DCF!$J$10/100 -> 59395.051
A12: Топливо | B12: $ млн | D12: =DCF!$D$4*DCF!$D$7/100 -> 18785.164 | E12: =DCF!$E$4*DCF!$E$7/100 -> 18822.166 | F12: =DCF!$F$4*DCF!$F$7/100 -> 15761.59 | G12: =DCF!$G$4*DCF!$G$7/100 -> 14796.239 | H12: =DCF!$H$4*DCF!$H$7/100 -> 15234.208 | I12: =DCF!$I$4*DCF!$I$7/100 -> 15609.731 | J12: =DCF!$J$4*DCF!$J$7/100 -> 15917.243
A13: Сторонние услуги | B13: $ млн | D13: =DCF!$D$9*Assumptions!$C$16 -> 304.91469 | E13: =DCF!$E$9*Assumptions!$D$16 -> 284.98988 | F13: =DCF!$F$9*Assumptions!$E$16 -> 289.75757 | G13: =DCF!$G$9*Assumptions!$F$16 -> 307.72736 | H13: =DCF!$H$9*Assumptions!$G$16 -> 330.54527 | I13: =DCF!$I$9*Assumptions!$H$16 -> 350.64191 | J13: =DCF!$J$9*Assumptions!$I$16 -> 370.18901
A14: EBIT до участия в прибыли | B14: $ млн | D14: =DCF!$D$9-DCF!$D$11-DCF!$D$12-DCF!$D$13 -> 3523.6082 | E14: =DCF!$E$9-DCF!$E$11-DCF!$E$12-DCF!$E$13 -> -1566.78 | F14: =DCF!$F$9-DCF!$F$11-DCF!$F$12-DCF!$F$13 -> 1165.6366 | G14: =DCF!$G$9-DCF!$G$11-DCF!$G$12-DCF!$G$13 -> 3483.4534 | H14: =DCF!$H$9-DCF!$H$11-DCF!$H$12-DCF!$H$13 -> 5065.6892 | I14: =DCF!$I$9-DCF!$I$11-DCF!$I$12-DCF!$I$13 -> 5810.9785 | J14: =DCF!$J$9-DCF!$J$11-DCF!$J$12-DCF!$J$13 -> 6581.7413
A15: Участие в прибыли | B15: $ млн | D15: =MAX(0,DCF!$D$14)*Assumptions!$C$17 -> 422.83298 | E15: =MAX(0,DCF!$E$14)*Assumptions!$D$17 -> 0 | F15: =MAX(0,DCF!$F$14)*Assumptions!$E$17 -> 139.87639 | G15: =MAX(0,DCF!$G$14)*Assumptions!$F$17 -> 418.0144 | H15: =MAX(0,DCF!$H$14)*Assumptions!$G$17 -> 607.8827 | I15: =MAX(0,DCF!$I$14)*Assumptions!$H$17 -> 697.31742 | J15: =MAX(0,DCF!$J$14)*Assumptions!$I$17 -> 789.80895
A16: Скорр. EBIT | B16: $ млн | C16: =Hist!$I$31 -> 4972 | D16: =DCF!$D$14-DCF!$D$15 -> 3100.7752 | E16: =DCF!$E$14-DCF!$E$15 -> -1566.78 | F16: =DCF!$F$14-DCF!$F$15 -> 1025.7602 | G16: =DCF!$G$14-DCF!$G$15 -> 3065.439 | H16: =DCF!$H$14-DCF!$H$15 -> 4457.8065 | I16: =DCF!$I$14-DCF!$I$15 -> 5113.6611 | J16: =DCF!$J$14-DCF!$J$15 -> 5791.9323
A17: Скорр. операционная маржа | B17: % | C17: =DCF!$C$16/DCF!$C$9 -> 0.084171322 | D17: =DCF!$D$16/DCF!$D$9 -> 0.045761943 | E17: =DCF!$E$16/DCF!$E$9 -> -0.02473951 | F17: =DCF!$F$16/DCF!$F$9 -> 0.015930286 | G17: =DCF!$G$16/DCF!$G$9 -> 0.044826937 | H17: =DCF!$H$16/DCF!$H$9 -> 0.060687993 | I17: =DCF!$I$16/DCF!$I$9 -> 0.06562671 | J17: =DCF!$J$16/DCF!$J$9 -> 0.070406454
A18: D&A | B18: $ млн | C18: =Hist!$I$26 -> 2939 | D18: =DCF!$D$9*Assumptions!$C$18 -> 3252.4233 | E18: =DCF!$E$9*Assumptions!$D$18 -> 3039.892 | F18: =DCF!$F$9*Assumptions!$E$18 -> 3090.7474 | G18: =DCF!$G$9*Assumptions!$F$18 -> 3282.4252 | H18: =DCF!$H$9*Assumptions!$G$18 -> 3525.8162 | I18: =DCF!$I$9*Assumptions!$H$18 -> 3740.1804 | J18: =DCF!$J$9*Assumptions!$I$18 -> 3948.6828
A19: EBITDAR = EBIT + D&A + фикс. аренда | B19: $ млн | C19: =Metrics!$I$31 -> 8970 | D19: =DCF!$D$16+DCF!$D$18+DCF!$D$9*Assumptions!$C$19 -> 7403.4602 | E19: =DCF!$E$16+DCF!$E$18+DCF!$E$9*Assumptions!$D$19 -> 2454.7439 | F19: =DCF!$F$16+DCF!$F$18+DCF!$F$9*Assumptions!$E$19 -> 5114.5615 | G19: =DCF!$G$16+DCF!$G$18+DCF!$G$9*Assumptions!$F$19 -> 7407.814 | H19: =DCF!$H$16+DCF!$H$18+DCF!$H$9*Assumptions!$G$19 -> 9122.1676 | I19: =DCF!$I$16+DCF!$I$18+DCF!$I$9*Assumptions!$H$19 -> 10061.608 | J19: =DCF!$J$16+DCF!$J$18+DCF!$J$9*Assumptions!$I$19 -> 11015.711
A20: Обязательства по опер. аренде | B20: $ млн | D20: =Hist!$K$51 -> 7204 | E20: =DCF!$D$20*(1+Assumptions!$D$28) -> 7059.92 | F20: =DCF!$E$20*(1+Assumptions!$E$28) -> 7201.1184 | G20: =DCF!$F$20*(1+Assumptions!$F$28) -> 7489.1631 | H20: =DCF!$G$20*(1+Assumptions!$G$28) -> 7788.7297 | I20: =DCF!$H$20*(1+Assumptions!$H$28) -> 8061.3352 | J20: =DCF!$I$20*(1+Assumptions!$I$28) -> 8303.1753
A21: Процентная часть аренды (возвращается в EBIT) | B21: $ млн | D21: =DCF!$D$20*Assumptions!$C$20 -> 468.26 | E21: =DCF!$E$20*Assumptions!$C$20 -> 458.8948 | F21: =DCF!$F$20*Assumptions!$C$20 -> 468.0727 | G21: =DCF!$G$20*Assumptions!$C$20 -> 486.7956 | H21: =DCF!$H$20*Assumptions!$C$20 -> 506.26743 | I21: =DCF!$I$20*Assumptions!$C$20 -> 523.98679 | J21: =DCF!$J$20*Assumptions!$C$20 -> 539.70639
A22: NOPAT (с поправкой на аренду) = (EBIT + % аренды) × (1 − t) | B22: $ млн | D22: =(DCF!$D$16+DCF!$D$21)*(1-Assumptions!$C$10) -> 2783.8474 | E22: =(DCF!$E$16+DCF!$E$21)*(1-Assumptions!$C$10) -> -864.15045 | F22: =(DCF!$F$16+DCF!$F$21)*(1-Assumptions!$C$10) -> 1165.1897 | G22: =(DCF!$G$16+DCF!$G$21)*(1-Assumptions!$C$10) -> 2770.743 | H22: =(DCF!$H$16+DCF!$H$21)*(1-Assumptions!$C$10) -> 3871.9777 | I22: =(DCF!$I$16+DCF!$I$21)*(1-Assumptions!$C$10) -> 4397.3653 | J22: =(DCF!$J$16+DCF!$J$21)*(1-Assumptions!$C$10) -> 4938.6782
A23: Скорр. капзатраты | B23: $ млн | D23: =Assumptions!$C$23 -> 7500 | E23: =DCF!$E$9*Assumptions!$D$33 -> 5066.4867 | F23: =DCF!$F$9*Assumptions!$E$33 -> 5151.2457 | G23: =DCF!$G$9*Assumptions!$F$33 -> 6154.5473 | H23: =DCF!$H$9*Assumptions!$G$33 -> 7345.4505 | I23: =DCF!$I$9*Assumptions!$H$33 -> 7792.0424 | J23: =DCF!$J$9*Assumptions!$I$33 -> 8226.4224
A24: Приток оборотного капитала | B24: $ млн | D24: =(DCF!$D$9-DCF!$C$9)*Assumptions!$C$21 -> 868.88192 | E24: =(DCF!$E$9-DCF!$D$9)*Assumptions!$D$21 -> -442.77351 | F24: =(DCF!$F$9-DCF!$E$9)*Assumptions!$E$21 -> 105.94876 | G24: =(DCF!$G$9-DCF!$F$9)*Assumptions!$F$21 -> 399.3287 | H24: =(DCF!$H$9-DCF!$G$9)*Assumptions!$G$21 -> 507.06459 | I24: =(DCF!$I$9-DCF!$H$9)*Assumptions!$H$21 -> 446.59198 | J24: =(DCF!$J$9-DCF!$I$9)*Assumptions!$I$21 -> 434.37995
A25: FCFF = NOPAT + D&A − капзатраты + Δоборотный капитал | B25: $ млн | D25: =DCF!$D$22+DCF!$D$18-DCF!$D$23+DCF!$D$24 -> -594.8473 | E25: =DCF!$E$22+DCF!$E$18-DCF!$E$23+DCF!$E$24 -> -3333.5186 | F25: =DCF!$F$22+DCF!$F$18-DCF!$F$23+DCF!$F$24 -> -789.35988 | G25: =DCF!$G$22+DCF!$G$18-DCF!$G$23+DCF!$G$24 -> 297.94958 | H25: =DCF!$H$22+DCF!$H$18-DCF!$H$23+DCF!$H$24 -> 559.40801 | I25: =DCF!$I$22+DCF!$I$18-DCF!$I$23+DCF!$I$24 -> 792.09523 | J25: =DCF!$J$22+DCF!$J$18-DCF!$J$23+DCF!$J$24 -> 1095.3185
A26: FCFF к дисконтированию (2026E — только 2П: минус факт 1П26) | B26: $ млн | D26: =DCF!$D$25-Assumptions!$C$12 -> -4032.7873 | E26: =DCF!$E$25 -> -3333.5186 | F26: =DCF!$F$25 -> -789.35988 | G26: =DCF!$G$25 -> 297.94958 | H26: =DCF!$H$25 -> 559.40801 | I26: =DCF!$I$25 -> 792.09523 | J26: =DCF!$J$25 -> 1095.3185
A27: Период дисконтирования (лет от 30.06.2026, середина периода) | B27: лет | D27: 0.25 | E27: 1 | F27: 2 | G27: 3 | H27: 4 | I27: 5 | J27: 6 | K27: [Д] середина периода; 2П26 = 0,25
A28: Коэффициент дисконтирования | B28: x | D28: =1/(1+WACC!$C$14)^DCF!$D$27 -> 0.97980256 | E28: =1/(1+WACC!$C$14)^DCF!$E$27 -> 0.92162505 | F28: =1/(1+WACC!$C$14)^DCF!$F$27 -> 0.84939274 | G28: =1/(1+WACC!$C$14)^DCF!$G$27 -> 0.78282163 | H28: =1/(1+WACC!$C$14)^DCF!$H$27 -> 0.72146802 | I28: =1/(1+WACC!$C$14)^DCF!$I$27 -> 0.664923 | J28: =1/(1+WACC!$C$14)^DCF!$J$27 -> 0.6128097
A29: PV FCFF | B29: $ млн | D29: =DCF!$D$26*DCF!$D$28 -> -3951.3353 | E29: =DCF!$E$26*DCF!$E$28 -> -3072.2543 | F29: =DCF!$F$26*DCF!$F$28 -> -670.47655 | G29: =DCF!$G$26*DCF!$G$28 -> 233.24138 | H29: =DCF!$H$26*DCF!$H$28 -> 403.59499 | I29: =DCF!$I$26*DCF!$I$28 -> 526.68234 | J29: =DCF!$J$26*DCF!$J$28 -> 671.2218
A30: EPS скорр. = (EBIT − чистые %) × (1 − t) / акции | B30: $ | D30: =(DCF!$D$16-Assumptions!$C$22)*(1-Assumptions!$C$10)/Assumptions!$C$6 -> 6.0918697 | E30: =(DCF!$E$16-Assumptions!$D$22)*(1-Assumptions!$C$10)/Assumptions!$C$6 -> -5.0553839 | F30: =(DCF!$F$16-Assumptions!$E$22)*(1-Assumptions!$C$10)/Assumptions!$C$6 -> 1.1362307 | G30: =(DCF!$G$16-Assumptions!$F$22)*(1-Assumptions!$C$10)/Assumptions!$C$6 -> 6.0074782 | H30: =(DCF!$H$16-Assumptions!$G$22)*(1-Assumptions!$C$10)/Assumptions!$C$6 -> 9.3327896 | I30: =(DCF!$I$16-Assumptions!$H$22)*(1-Assumptions!$C$10)/Assumptions!$C$6 -> 10.899129 | J30: =(DCF!$J$16-Assumptions!$I$22)*(1-Assumptions!$C$10)/Assumptions!$C$6 -> 12.519006
A31: Сумма PV FCFF 2П26–2032E | B31: $ млн | J31: =SUM(D29:J29) -> -5859.3256
A32: TV Гордон = NOPAT×(1+g)×(1−g/RONIC)/(WACC−g) | B32: $ млн | J32: =DCF!$J$22*(1+Assumptions!$C$24)*(1-Assumptions!$C$24/Assumptions!$C$25)/(WACC!$C$14-Assumptions!$C$24) -> 63234.712
A33: Выходной мультипликатор EV/EBITDAR | B33: x | J33: =Multiples!$C$51 -> 4.6083934 | K33: история UAL: мин / медиана / макс (лист Multiples)
A34: TV по мультипликатору = EV/EBITDAR × EBITDAR 2032E | B34: $ млн | J34: =DCF!$J$33*DCF!$J$19 -> 50764.727
A35: Дисконт TV (6,5 года) | B35: x | J35: =1/(1+WACC!$C$14)^6.5 -> 0.58830531
A36: EV (Гордон) | B36: $ млн | J36: =DCF!$J$31+DCF!$J$32*DCF!$J$35 -> 31341.991
A37: EV (мультипликатор) | B37: $ млн | J37: =DCF!$J$31+DCF!$J$34*DCF!$J$35 -> 24005.833
A38: Доля TV в EV (Гордон) | B38: % | J38: =DCF!$J$32*DCF!$J$35/DCF!$J$36 -> 1.1869481
A39: Стоимость акции (Гордон) = (EV − чистый скорр. долг + NOL) / акции | B39: $ | J39: =(DCF!$J$36-WACC!$C$15+Assumptions!$C$11)/Assumptions!$C$6 -> 46.653371
A40: Стоимость акции (мультипликатор) | B40: $ | J40: =(DCF!$J$37-WACC!$C$15+Assumptions!$C$11)/Assumptions!$C$6 -> 24.19116
A41: Стоимость акции DCF (взвешенная) | B41: $ | J41: =Assumptions!$C$13*DCF!$J$39+(1-Assumptions!$C$13)*DCF!$J$40 -> 35.422266
A42: Проверка: EV/EBITDAR, заложенный в TV Гордона | B42: x | J42: =DCF!$J$32/DCF!$J$19 -> 5.7404115
A44: Базовый | B44: Ед. | C44: 2025A | D44: 2026E | E44: 2027E | F44: 2028E | G44: 2029E | H44: 2030E | I44: 2031E | J44: 2032E | K44: Источник / тип
A45: ASM | B45: млн | C45: =Hist!$I$5 -> 330284 | D45: =DCF!$C$45*(1+Assumptions!$C$35) -> 338541.1 | E45: =DCF!$D$45*(1+Assumptions!$D$35) -> 352082.74 | F45: =DCF!$E$45*(1+Assumptions!$E$35) -> 369686.88 | G45: =DCF!$F$45*(1+Assumptions!$F$35) -> 388171.23 | H45: =DCF!$G$45*(1+Assumptions!$G$35) -> 405638.93 | I45: =DCF!$H$45*(1+Assumptions!$H$35) -> 421864.49 | J45: =DCF!$I$45*(1+Assumptions!$I$35) -> 436629.74
A46: Галлонов на 1000 ASM | B46: галл. | C46: =Metrics!$I$13 -> 14.118153 | D46: =DCF!$C$46*(1+Assumptions!$C$15) -> 13.976971 | E46: =DCF!$D$46*(1+Assumptions!$D$15) -> 13.837202 | F46: =DCF!$E$46*(1+Assumptions!$E$15) -> 13.69883 | G46: =DCF!$F$46*(1+Assumptions!$F$15) -> 13.561841 | H46: =DCF!$G$46*(1+Assumptions!$G$15) -> 13.426223 | I46: =DCF!$H$46*(1+Assumptions!$H$15) -> 13.291961 | J46: =DCF!$I$46*(1+Assumptions!$I$15) -> 13.159041
A47: Цена топлива | B47: $/галл. | C47: =Hist!$I$9 -> 2.44 | D47: =Assumptions!$C$39 -> 3.97 | E47: =Assumptions!$D$39 -> 3.3 | F47: =Assumptions!$E$39 -> 3 | G47: =Assumptions!$F$39 -> 2.9 | H47: =Assumptions!$G$39 -> 2.9 | I47: =Assumptions!$H$39 -> 2.95 | J47: =Assumptions!$I$39 -> 3
A48: Топливо на ASM | B48: центы | C48: =DCF!$C$46*DCF!$C$47/10 -> 3.4448293 | D48: =DCF!$D$46*DCF!$D$47/10 -> 5.5488576 | E48: =DCF!$E$46*DCF!$E$47/10 -> 4.5662765 | F48: =DCF!$F$46*DCF!$F$47/10 -> 4.1096489 | G48: =DCF!$G$46*DCF!$G$47/10 -> 3.932934 | H48: =DCF!$H$46*DCF!$H$47/10 -> 3.8936046 | I48: =DCF!$I$46*DCF!$I$47/10 -> 3.9211284 | J48: =DCF!$J$46*DCF!$J$47/10 -> 3.9477123
A49: TRASM = TRASM(t−1)×(1+базовый рост) + перенос×Δтопливо/ASM | B49: центы | C49: =Metrics!$I$8 -> 17.884608 | D49: =DCF!$C$49*(1+Assumptions!$C$36)+Assumptions!$C$37*(DCF!$D$48-DCF!$C$48) -> 20.014946 | E49: =DCF!$D$49*(1+Assumptions!$D$36)+Assumptions!$D$37*(DCF!$E$48-DCF!$D$48) -> 19.678309 | F49: =DCF!$E$49*(1+Assumptions!$E$36)+Assumptions!$E$37*(DCF!$F$48-DCF!$E$48) -> 19.713639 | G49: =DCF!$F$49*(1+Assumptions!$F$36)+Assumptions!$F$37*(DCF!$G$48-DCF!$F$48) -> 20.029766 | H49: =DCF!$G$49*(1+Assumptions!$G$36)+Assumptions!$G$37*(DCF!$H$48-DCF!$G$48) -> 20.49118 | I49: =DCF!$H$49*(1+Assumptions!$H$36)+Assumptions!$H$37*(DCF!$I$48-DCF!$H$48) -> 21.030984 | J49: =DCF!$I$49*(1+Assumptions!$I$36)+Assumptions!$I$37*(DCF!$J$48-DCF!$I$48) -> 21.583342
A50: Выручка | B50: $ млн | C50: =Hist!$I$19 -> 59070 | D50: =DCF!$D$45*DCF!$D$49/100 -> 67758.819 | E50: =DCF!$E$45*DCF!$E$49/100 -> 69283.932 | F50: =DCF!$F$45*DCF!$F$49/100 -> 72878.739 | G50: =DCF!$G$45*DCF!$G$49/100 -> 77749.786 | H50: =DCF!$H$45*DCF!$H$49/100 -> 83120.205 | I50: =DCF!$I$45*DCF!$I$49/100 -> 88722.251 | J50: =DCF!$J$45*DCF!$J$49/100 -> 94239.292
A51: CASM-ex | B51: центы | C51: =Metrics!$I$10 -> 12.64 | D51: =DCF!$C$51*(1+Assumptions!$C$38) -> 13.3352 | E51: =DCF!$D$51*(1+Assumptions!$D$38) -> 13.66858 | F51: =DCF!$E$51*(1+Assumptions!$E$38) -> 13.941952 | G51: =DCF!$F$51*(1+Assumptions!$F$38) -> 14.262616 | H51: =DCF!$G$51*(1+Assumptions!$G$38) -> 14.647707 | I51: =DCF!$H$51*(1+Assumptions!$H$38) -> 15.043195 | J51: =DCF!$I$51*(1+Assumptions!$I$38) -> 15.449361
A52: Нетопливные расходы (CASM-ex × ASM) | B52: $ млн | D52: =DCF!$D$45*DCF!$D$51/100 -> 45145.133 | E52: =DCF!$E$45*DCF!$E$51/100 -> 48124.712 | F52: =DCF!$F$45*DCF!$F$51/100 -> 51541.566 | G52: =DCF!$G$45*DCF!$G$51/100 -> 55363.373 | H52: =DCF!$H$45*DCF!$H$51/100 -> 59416.803 | I52: =DCF!$I$45*DCF!$I$51/100 -> 63461.898 | J52: =DCF!$J$45*DCF!$J$51/100 -> 67456.508
A53: Топливо | B53: $ млн | D53: =DCF!$D$45*DCF!$D$48/100 -> 18785.164 | E53: =DCF!$E$45*DCF!$E$48/100 -> 16077.072 | F53: =DCF!$F$45*DCF!$F$48/100 -> 15192.833 | G53: =DCF!$G$45*DCF!$G$48/100 -> 15266.518 | H53: =DCF!$H$45*DCF!$H$48/100 -> 15793.976 | I53: =DCF!$I$45*DCF!$I$48/100 -> 16541.848 | J53: =DCF!$J$45*DCF!$J$48/100 -> 17236.886
A54: Сторонние услуги | B54: $ млн | D54: =DCF!$D$50*Assumptions!$C$16 -> 304.91469 | E54: =DCF!$E$50*Assumptions!$D$16 -> 311.77769 | F54: =DCF!$F$50*Assumptions!$E$16 -> 327.95432 | G54: =DCF!$G$50*Assumptions!$F$16 -> 349.87404 | H54: =DCF!$H$50*Assumptions!$G$16 -> 374.04092 | I54: =DCF!$I$50*Assumptions!$H$16 -> 399.25013 | J54: =DCF!$J$50*Assumptions!$I$16 -> 424.07681
A55: EBIT до участия в прибыли | B55: $ млн | D55: =DCF!$D$50-DCF!$D$52-DCF!$D$53-DCF!$D$54 -> 3523.6082 | E55: =DCF!$E$50-DCF!$E$52-DCF!$E$53-DCF!$E$54 -> 4770.3707 | F55: =DCF!$F$50-DCF!$F$52-DCF!$F$53-DCF!$F$54 -> 5816.3857 | G55: =DCF!$G$50-DCF!$G$52-DCF!$G$53-DCF!$G$54 -> 6770.0211 | H55: =DCF!$H$50-DCF!$H$52-DCF!$H$53-DCF!$H$54 -> 7535.3851 | I55: =DCF!$I$50-DCF!$I$52-DCF!$I$53-DCF!$I$54 -> 8319.2544 | J55: =DCF!$J$50-DCF!$J$52-DCF!$J$53-DCF!$J$54 -> 9121.8209
A56: Участие в прибыли | B56: $ млн | D56: =MAX(0,DCF!$D$55)*Assumptions!$C$17 -> 422.83298 | E56: =MAX(0,DCF!$E$55)*Assumptions!$D$17 -> 572.44448 | F56: =MAX(0,DCF!$F$55)*Assumptions!$E$17 -> 697.96629 | G56: =MAX(0,DCF!$G$55)*Assumptions!$F$17 -> 812.40253 | H56: =MAX(0,DCF!$H$55)*Assumptions!$G$17 -> 904.24621 | I56: =MAX(0,DCF!$I$55)*Assumptions!$H$17 -> 998.31053 | J56: =MAX(0,DCF!$J$55)*Assumptions!$I$17 -> 1094.6185
A57: Скорр. EBIT | B57: $ млн | C57: =Hist!$I$31 -> 4972 | D57: =DCF!$D$55-DCF!$D$56 -> 3100.7752 | E57: =DCF!$E$55-DCF!$E$56 -> 4197.9262 | F57: =DCF!$F$55-DCF!$F$56 -> 5118.4194 | G57: =DCF!$G$55-DCF!$G$56 -> 5957.6186 | H57: =DCF!$H$55-DCF!$H$56 -> 6631.1389 | I57: =DCF!$I$55-DCF!$I$56 -> 7320.9439 | J57: =DCF!$J$55-DCF!$J$56 -> 8027.2024
A58: Скорр. операционная маржа | B58: % | C58: =DCF!$C$57/DCF!$C$50 -> 0.084171322 | D58: =DCF!$D$57/DCF!$D$50 -> 0.045761943 | E58: =DCF!$E$57/DCF!$E$50 -> 0.060590184 | F58: =DCF!$F$57/DCF!$F$50 -> 0.070231998 | G58: =DCF!$G$57/DCF!$G$50 -> 0.07662553 | H58: =DCF!$H$57/DCF!$H$50 -> 0.079777701 | I58: =DCF!$I$57/DCF!$I$50 -> 0.082515308 | J58: =DCF!$J$57/DCF!$J$50 -> 0.085178934
A59: D&A | B59: $ млн | C59: =Hist!$I$26 -> 2939 | D59: =DCF!$D$50*Assumptions!$C$18 -> 3252.4233 | E59: =DCF!$E$50*Assumptions!$D$18 -> 3325.6287 | F59: =DCF!$F$50*Assumptions!$E$18 -> 3498.1795 | G59: =DCF!$G$50*Assumptions!$F$18 -> 3731.9897 | H59: =DCF!$H$50*Assumptions!$G$18 -> 3989.7698 | I59: =DCF!$I$50*Assumptions!$H$18 -> 4258.6681 | J59: =DCF!$J$50*Assumptions!$I$18 -> 4523.486
A60: EBITDAR = EBIT + D&A + фикс. аренда | B60: $ млн | C60: =Metrics!$I$31 -> 8970 | D60: =DCF!$D$57+DCF!$D$59+DCF!$D$50*Assumptions!$C$19 -> 7403.4602 | E60: =DCF!$E$57+DCF!$E$59+DCF!$E$50*Assumptions!$D$19 -> 8597.4559 | F60: =DCF!$F$57+DCF!$F$59+DCF!$F$50*Assumptions!$E$19 -> 9746.2194 | G60: =DCF!$G$57+DCF!$G$59+DCF!$G$50*Assumptions!$F$19 -> 10894.73 | H60: =DCF!$H$57+DCF!$H$59+DCF!$H$50*Assumptions!$G$19 -> 11909.272 | I60: =DCF!$I$57+DCF!$I$59+DCF!$I$50*Assumptions!$H$19 -> 12954.807 | J60: =DCF!$J$57+DCF!$J$59+DCF!$J$50*Assumptions!$I$19 -> 14011.397
A61: Обязательства по опер. аренде | B61: $ млн | D61: =Hist!$K$51 -> 7204 | E61: =DCF!$D$61*(1+Assumptions!$D$35) -> 7492.16 | F61: =DCF!$E$61*(1+Assumptions!$E$35) -> 7866.768 | G61: =DCF!$F$61*(1+Assumptions!$F$35) -> 8260.1064 | H61: =DCF!$G$61*(1+Assumptions!$G$35) -> 8631.8112 | I61: =DCF!$H$61*(1+Assumptions!$H$35) -> 8977.0836 | J61: =DCF!$I$61*(1+Assumptions!$I$35) -> 9291.2816
A62: Процентная часть аренды (возвращается в EBIT) | B62: $ млн | D62: =DCF!$D$61*Assumptions!$C$20 -> 468.26 | E62: =DCF!$E$61*Assumptions!$C$20 -> 486.9904 | F62: =DCF!$F$61*Assumptions!$C$20 -> 511.33992 | G62: =DCF!$G$61*Assumptions!$C$20 -> 536.90692 | H62: =DCF!$H$61*Assumptions!$C$20 -> 561.06773 | I62: =DCF!$I$61*Assumptions!$C$20 -> 583.51044 | J62: =DCF!$J$61*Assumptions!$C$20 -> 603.9333
A63: NOPAT (с поправкой на аренду) = (EBIT + % аренды) × (1 − t) | B63: $ млн | D63: =(DCF!$D$57+DCF!$D$62)*(1-Assumptions!$C$10) -> 2783.8474 | E63: =(DCF!$E$57+DCF!$E$62)*(1-Assumptions!$C$10) -> 3654.2349 | F63: =(DCF!$F$57+DCF!$F$62)*(1-Assumptions!$C$10) -> 4391.2123 | G63: =(DCF!$G$57+DCF!$G$62)*(1-Assumptions!$C$10) -> 5065.7299 | H63: =(DCF!$H$57+DCF!$H$62)*(1-Assumptions!$C$10) -> 5609.9211 | I63: =(DCF!$I$57+DCF!$I$62)*(1-Assumptions!$C$10) -> 6165.4744 | J63: =(DCF!$J$57+DCF!$J$62)*(1-Assumptions!$C$10) -> 6732.2858
A64: Скорр. капзатраты | B64: $ млн | D64: =Assumptions!$C$23 -> 7500 | E64: =DCF!$E$50*Assumptions!$D$40 -> 7967.6521 | F64: =DCF!$F$50*Assumptions!$E$40 -> 8745.4487 | G64: =DCF!$G$50*Assumptions!$F$40 -> 9329.9744 | H64: =DCF!$H$50*Assumptions!$G$40 -> 9143.2225 | I64: =DCF!$I$50*Assumptions!$H$40 -> 9315.8364 | J64: =DCF!$J$50*Assumptions!$I$40 -> 9423.9292
A65: Приток оборотного капитала | B65: $ млн | D65: =(DCF!$D$50-DCF!$C$50)*Assumptions!$C$21 -> 868.88192 | E65: =(DCF!$E$50-DCF!$D$50)*Assumptions!$D$21 -> 152.51124 | F65: =(DCF!$F$50-DCF!$E$50)*Assumptions!$E$21 -> 359.48073 | G65: =(DCF!$G$50-DCF!$F$50)*Assumptions!$F$21 -> 487.10474 | H65: =(DCF!$H$50-DCF!$G$50)*Assumptions!$G$21 -> 537.04184 | I65: =(DCF!$I$50-DCF!$H$50)*Assumptions!$H$21 -> 560.20465 | J65: =(DCF!$J$50-DCF!$I$50)*Assumptions!$I$21 -> 551.70404
A66: FCFF = NOPAT + D&A − капзатраты + Δоборотный капитал | B66: $ млн | D66: =DCF!$D$63+DCF!$D$59-DCF!$D$64+DCF!$D$65 -> -594.8473 | E66: =DCF!$E$63+DCF!$E$59-DCF!$E$64+DCF!$E$65 -> -835.27723 | F66: =DCF!$F$63+DCF!$F$59-DCF!$F$64+DCF!$F$65 -> -496.57617 | G66: =DCF!$G$63+DCF!$G$59-DCF!$G$64+DCF!$G$65 -> -45.149998 | H66: =DCF!$H$63+DCF!$H$59-DCF!$H$64+DCF!$H$65 -> 993.5103 | I66: =DCF!$I$63+DCF!$I$59-DCF!$I$64+DCF!$I$65 -> 1668.5107 | J66: =DCF!$J$63+DCF!$J$59-DCF!$J$64+DCF!$J$65 -> 2383.5467
A67: FCFF к дисконтированию (2026E — только 2П: минус факт 1П26) | B67: $ млн | D67: =DCF!$D$66-Assumptions!$C$12 -> -4032.7873 | E67: =DCF!$E$66 -> -835.27723 | F67: =DCF!$F$66 -> -496.57617 | G67: =DCF!$G$66 -> -45.149998 | H67: =DCF!$H$66 -> 993.5103 | I67: =DCF!$I$66 -> 1668.5107 | J67: =DCF!$J$66 -> 2383.5467
A68: Период дисконтирования (лет от 30.06.2026, середина периода) | B68: лет | D68: 0.25 | E68: 1 | F68: 2 | G68: 3 | H68: 4 | I68: 5 | J68: 6 | K68: [Д] середина периода; 2П26 = 0,25
A69: Коэффициент дисконтирования | B69: x | D69: =1/(1+WACC!$C$14)^DCF!$D$68 -> 0.97980256 | E69: =1/(1+WACC!$C$14)^DCF!$E$68 -> 0.92162505 | F69: =1/(1+WACC!$C$14)^DCF!$F$68 -> 0.84939274 | G69: =1/(1+WACC!$C$14)^DCF!$G$68 -> 0.78282163 | H69: =1/(1+WACC!$C$14)^DCF!$H$68 -> 0.72146802 | I69: =1/(1+WACC!$C$14)^DCF!$I$68 -> 0.664923 | J69: =1/(1+WACC!$C$14)^DCF!$J$68 -> 0.6128097
A70: PV FCFF | B70: $ млн | D70: =DCF!$D$67*DCF!$D$69 -> -3951.3353 | E70: =DCF!$E$67*DCF!$E$69 -> -769.81243 | F70: =DCF!$F$67*DCF!$F$69 -> -421.78819 | G70: =DCF!$G$67*DCF!$G$69 -> -35.344395 | H70: =DCF!$H$67*DCF!$H$69 -> 716.78591 | I70: =DCF!$I$67*DCF!$I$69 -> 1109.4312 | J70: =DCF!$J$67*DCF!$J$69 -> 1460.6605
A71: EPS скорр. = (EBIT − чистые %) × (1 − t) / акции | B71: $ | D71: =(DCF!$D$57-Assumptions!$C$22)*(1-Assumptions!$C$10)/Assumptions!$C$6 -> 6.0918697 | E71: =(DCF!$E$57-Assumptions!$D$22)*(1-Assumptions!$C$10)/Assumptions!$C$6 -> 8.7121324 | F71: =(DCF!$F$57-Assumptions!$E$22)*(1-Assumptions!$C$10)/Assumptions!$C$6 -> 10.910493 | G71: =(DCF!$G$57-Assumptions!$F$22)*(1-Assumptions!$C$10)/Assumptions!$C$6 -> 12.914704 | H71: =(DCF!$H$57-Assumptions!$G$22)*(1-Assumptions!$C$10)/Assumptions!$C$6 -> 14.523234 | I71: =(DCF!$I$57-Assumptions!$H$22)*(1-Assumptions!$C$10)/Assumptions!$C$6 -> 16.170656 | J71: =(DCF!$J$57-Assumptions!$I$22)*(1-Assumptions!$C$10)/Assumptions!$C$6 -> 17.857373
A72: Сумма PV FCFF 2П26–2032E | B72: $ млн | J72: =SUM(D70:J70) -> -1891.4027
A73: TV Гордон = NOPAT×(1+g)×(1−g/RONIC)/(WACC−g) | B73: $ млн | J73: =DCF!$J$63*(1+Assumptions!$C$24)*(1-Assumptions!$C$24/Assumptions!$C$25)/(WACC!$C$14-Assumptions!$C$24) -> 86200.019
A74: Выходной мультипликатор EV/EBITDAR | B74: x | J74: =Multiples!$C$52 -> 6.2149084 | K74: история UAL: мин / медиана / макс (лист Multiples)
A75: TV по мультипликатору = EV/EBITDAR × EBITDAR 2032E | B75: $ млн | J75: =DCF!$J$74*DCF!$J$60 -> 87079.551
A76: Дисконт TV (6,5 года) | B76: x | J76: =1/(1+WACC!$C$14)^6.5 -> 0.58830531
A77: EV (Гордон) | B77: $ млн | J77: =DCF!$J$72+DCF!$J$73*DCF!$J$76 -> 48820.526
A78: EV (мультипликатор) | B78: $ млн | J78: =DCF!$J$72+DCF!$J$75*DCF!$J$76 -> 49337.959
A79: Доля TV в EV (Гордон) | B79: % | J79: =DCF!$J$73*DCF!$J$76/DCF!$J$77 -> 1.038742
A80: Стоимость акции (Гордон) = (EV − чистый скорр. долг + NOL) / акции | B80: $ | J80: =(DCF!$J$77-WACC!$C$15+Assumptions!$C$11)/Assumptions!$C$6 -> 100.17001
A81: Стоимость акции (мультипликатор) | B81: $ | J81: =(DCF!$J$78-WACC!$C$15+Assumptions!$C$11)/Assumptions!$C$6 -> 101.75432
A82: Стоимость акции DCF (взвешенная) | B82: $ | J82: =Assumptions!$C$13*DCF!$J$80+(1-Assumptions!$C$13)*DCF!$J$81 -> 100.96216
A83: Проверка: EV/EBITDAR, заложенный в TV Гордона | B83: x | J83: =DCF!$J$73/DCF!$J$60 -> 6.1521358
A85: Оптимистичный (премиальный спрос и маржа) | B85: Ед. | C85: 2025A | D85: 2026E | E85: 2027E | F85: 2028E | G85: 2029E | H85: 2030E | I85: 2031E | J85: 2032E | K85: Источник / тип
A86: ASM | B86: млн | C86: =Hist!$I$5 -> 330284 | D86: =DCF!$C$86*(1+Assumptions!$C$42) -> 338541.1 | E86: =DCF!$D$86*(1+Assumptions!$D$42) -> 355468.15 | F86: =DCF!$E$86*(1+Assumptions!$E$42) -> 376796.24 | G86: =DCF!$F$86*(1+Assumptions!$F$42) -> 399404.02 | H86: =DCF!$G$86*(1+Assumptions!$G$42) -> 419374.22 | I86: =DCF!$H$86*(1+Assumptions!$H$42) -> 438246.06 | J86: =DCF!$I$86*(1+Assumptions!$I$42) -> 455775.9
A87: Галлонов на 1000 ASM | B87: галл. | C87: =Metrics!$I$13 -> 14.118153 | D87: =DCF!$C$87*(1+Assumptions!$C$15) -> 13.976971 | E87: =DCF!$D$87*(1+Assumptions!$D$15) -> 13.837202 | F87: =DCF!$E$87*(1+Assumptions!$E$15) -> 13.69883 | G87: =DCF!$F$87*(1+Assumptions!$F$15) -> 13.561841 | H87: =DCF!$G$87*(1+Assumptions!$G$15) -> 13.426223 | I87: =DCF!$H$87*(1+Assumptions!$H$15) -> 13.291961 | J87: =DCF!$I$87*(1+Assumptions!$I$15) -> 13.159041
A88: Цена топлива | B88: $/галл. | C88: =Hist!$I$9 -> 2.44 | D88: =Assumptions!$C$46 -> 3.97 | E88: =Assumptions!$D$46 -> 2.9 | F88: =Assumptions!$E$46 -> 2.75 | G88: =Assumptions!$F$46 -> 2.7 | H88: =Assumptions!$G$46 -> 2.75 | I88: =Assumptions!$H$46 -> 2.8 | J88: =Assumptions!$I$46 -> 2.85
A89: Топливо на ASM | B89: центы | C89: =DCF!$C$87*DCF!$C$88/10 -> 3.4448293 | D89: =DCF!$D$87*DCF!$D$88/10 -> 5.5488576 | E89: =DCF!$E$87*DCF!$E$88/10 -> 4.0127885 | F89: =DCF!$F$87*DCF!$F$88/10 -> 3.7671781 | G89: =DCF!$G$87*DCF!$G$88/10 -> 3.6616972 | H89: =DCF!$H$87*DCF!$H$88/10 -> 3.6922113 | I89: =DCF!$I$87*DCF!$I$88/10 -> 3.721749 | J89: =DCF!$J$87*DCF!$J$88/10 -> 3.7503267
A90: TRASM = TRASM(t−1)×(1+базовый рост) + перенос×Δтопливо/ASM | B90: центы | C90: =Metrics!$I$8 -> 17.884608 | D90: =DCF!$C$90*(1+Assumptions!$C$43)+Assumptions!$C$44*(DCF!$D$89-DCF!$C$89) -> 20.014946 | E90: =DCF!$D$90*(1+Assumptions!$D$43)+Assumptions!$D$44*(DCF!$E$89-DCF!$D$89) -> 19.793828 | F90: =DCF!$E$90*(1+Assumptions!$E$43)+Assumptions!$E$44*(DCF!$F$89-DCF!$E$89) -> 20.142032 | G90: =DCF!$F$90*(1+Assumptions!$F$43)+Assumptions!$F$44*(DCF!$G$89-DCF!$F$89) -> 20.540102 | H90: =DCF!$G$90*(1+Assumptions!$G$43)+Assumptions!$G$44*(DCF!$H$89-DCF!$G$89) -> 21.084119 | I90: =DCF!$H$90*(1+Assumptions!$H$43)+Assumptions!$H$44*(DCF!$I$89-DCF!$H$89) -> 21.64076 | J90: =DCF!$I$90*(1+Assumptions!$I$43)+Assumptions!$I$44*(DCF!$J$89-DCF!$I$89) -> 22.210356
A91: Выручка | B91: $ млн | C91: =Hist!$I$19 -> 59070 | D91: =DCF!$D$86*DCF!$D$90/100 -> 67758.819 | E91: =DCF!$E$86*DCF!$E$90/100 -> 70360.755 | F91: =DCF!$F$86*DCF!$F$90/100 -> 75894.422 | G91: =DCF!$G$86*DCF!$G$90/100 -> 82037.994 | H91: =DCF!$H$86*DCF!$H$90/100 -> 88421.359 | I91: =DCF!$I$86*DCF!$I$90/100 -> 94839.776 | J91: =DCF!$J$86*DCF!$J$90/100 -> 101229.45
A92: CASM-ex | B92: центы | C92: =Metrics!$I$10 -> 12.64 | D92: =DCF!$C$92*(1+Assumptions!$C$45) -> 13.3352 | E92: =DCF!$D$92*(1+Assumptions!$D$45) -> 13.601904 | F92: =DCF!$E$92*(1+Assumptions!$E$45) -> 13.873942 | G92: =DCF!$F$92*(1+Assumptions!$F$45) -> 14.220791 | H92: =DCF!$G$92*(1+Assumptions!$G$45) -> 14.604752 | I92: =DCF!$H$92*(1+Assumptions!$H$45) -> 14.99908 | J92: =DCF!$I$92*(1+Assumptions!$I$45) -> 15.404055
A93: Нетопливные расходы (CASM-ex × ASM) | B93: $ млн | D93: =DCF!$D$86*DCF!$D$92/100 -> 45145.133 | E93: =DCF!$E$86*DCF!$E$92/100 -> 48350.437 | F93: =DCF!$F$86*DCF!$F$92/100 -> 52276.493 | G93: =DCF!$G$86*DCF!$G$92/100 -> 56798.409 | H93: =DCF!$H$86*DCF!$H$92/100 -> 61248.565 | I93: =DCF!$I$86*DCF!$I$92/100 -> 65732.878 | J93: =DCF!$J$86*DCF!$J$92/100 -> 70207.973
A94: Топливо | B94: $ млн | D94: =DCF!$D$86*DCF!$D$89/100 -> 18785.164 | E94: =DCF!$E$86*DCF!$E$89/100 -> 14264.185 | F94: =DCF!$F$86*DCF!$F$89/100 -> 14194.586 | G94: =DCF!$G$86*DCF!$G$89/100 -> 14624.966 | H94: =DCF!$H$86*DCF!$H$89/100 -> 15484.182 | I94: =DCF!$I$86*DCF!$I$89/100 -> 16310.418 | J94: =DCF!$J$86*DCF!$J$89/100 -> 17093.085
A95: Сторонние услуги | B95: $ млн | D95: =DCF!$D$91*Assumptions!$C$16 -> 304.91469 | E95: =DCF!$E$91*Assumptions!$D$16 -> 316.6234 | F95: =DCF!$F$91*Assumptions!$E$16 -> 341.5249 | G95: =DCF!$G$91*Assumptions!$F$16 -> 369.17097 | H95: =DCF!$H$91*Assumptions!$G$16 -> 397.89612 | I95: =DCF!$I$91*Assumptions!$H$16 -> 426.77899 | J95: =DCF!$J$91*Assumptions!$I$16 -> 455.53253
A96: EBIT до участия в прибыли | B96: $ млн | D96: =DCF!$D$91-DCF!$D$93-DCF!$D$94-DCF!$D$95 -> 3523.6082 | E96: =DCF!$E$91-DCF!$E$93-DCF!$E$94-DCF!$E$95 -> 7429.5091 | F96: =DCF!$F$91-DCF!$F$93-DCF!$F$94-DCF!$F$95 -> 9081.8183 | G96: =DCF!$G$91-DCF!$G$93-DCF!$G$94-DCF!$G$95 -> 10245.448 | H96: =DCF!$H$91-DCF!$H$93-DCF!$H$94-DCF!$H$95 -> 11290.716 | I96: =DCF!$I$91-DCF!$I$93-DCF!$I$94-DCF!$I$95 -> 12369.701 | J96: =DCF!$J$91-DCF!$J$93-DCF!$J$94-DCF!$J$95 -> 13472.861
A97: Участие в прибыли | B97: $ млн | D97: =MAX(0,DCF!$D$96)*Assumptions!$C$17 -> 422.83298 | E97: =MAX(0,DCF!$E$96)*Assumptions!$D$17 -> 891.54109 | F97: =MAX(0,DCF!$F$96)*Assumptions!$E$17 -> 1089.8182 | G97: =MAX(0,DCF!$G$96)*Assumptions!$F$17 -> 1229.4537 | H97: =MAX(0,DCF!$H$96)*Assumptions!$G$17 -> 1354.8859 | I97: =MAX(0,DCF!$I$96)*Assumptions!$H$17 -> 1484.3641 | J97: =MAX(0,DCF!$J$96)*Assumptions!$I$17 -> 1616.7433
A98: Скорр. EBIT | B98: $ млн | C98: =Hist!$I$31 -> 4972 | D98: =DCF!$D$96-DCF!$D$97 -> 3100.7752 | E98: =DCF!$E$96-DCF!$E$97 -> 6537.968 | F98: =DCF!$F$96-DCF!$F$97 -> 7992.0001 | G98: =DCF!$G$96-DCF!$G$97 -> 9015.9942 | H98: =DCF!$H$96-DCF!$H$97 -> 9935.8302 | I98: =DCF!$I$96-DCF!$I$97 -> 10885.337 | J98: =DCF!$J$96-DCF!$J$97 -> 11856.118
A99: Скорр. операционная маржа | B99: % | C99: =DCF!$C$98/DCF!$C$91 -> 0.084171322 | D99: =DCF!$D$98/DCF!$D$91 -> 0.045761943 | E99: =DCF!$E$98/DCF!$E$91 -> 0.092920663 | F99: =DCF!$F$98/DCF!$F$91 -> 0.10530418 | G99: =DCF!$G$98/DCF!$G$91 -> 0.10990023 | H99: =DCF!$H$98/DCF!$H$91 -> 0.11236912 | I99: =DCF!$I$98/DCF!$I$91 -> 0.11477607 | J99: =DCF!$J$98/DCF!$J$91 -> 0.11712123
A100: D&A | B100: $ млн | C100: =Hist!$I$26 -> 2939 | D100: =DCF!$D$91*Assumptions!$C$18 -> 3252.4233 | E100: =DCF!$E$91*Assumptions!$D$18 -> 3377.3162 | F100: =DCF!$F$91*Assumptions!$E$18 -> 3642.9322 | G100: =DCF!$G$91*Assumptions!$F$18 -> 3937.8237 | H100: =DCF!$H$91*Assumptions!$G$18 -> 4244.2252 | I100: =DCF!$I$91*Assumptions!$H$18 -> 4552.3093 | J100: =DCF!$J$91*Assumptions!$I$18 -> 4859.0137
A101: EBITDAR = EBIT + D&A + фикс. аренда | B101: $ млн | C101: =Metrics!$I$31 -> 8970 | D101: =DCF!$D$98+DCF!$D$100+DCF!$D$91*Assumptions!$C$19 -> 7403.4602 | E101: =DCF!$E$98+DCF!$E$100+DCF!$E$91*Assumptions!$D$19 -> 11005.876 | F101: =DCF!$F$98+DCF!$F$100+DCF!$F$91*Assumptions!$E$19 -> 12811.296 | G101: =DCF!$G$98+DCF!$G$100+DCF!$G$91*Assumptions!$F$19 -> 14225.407 | H101: =DCF!$H$98+DCF!$H$100+DCF!$H$91*Assumptions!$G$19 -> 15550.587 | I101: =DCF!$I$98+DCF!$I$100+DCF!$I$91*Assumptions!$H$19 -> 16907.662 | J101: =DCF!$J$98+DCF!$J$100+DCF!$J$91*Assumptions!$I$19 -> 18284.188
A102: Обязательства по опер. аренде | B102: $ млн | D102: =Hist!$K$51 -> 7204 | E102: =DCF!$D$102*(1+Assumptions!$D$42) -> 7564.2 | F102: =DCF!$E$102*(1+Assumptions!$E$42) -> 8018.052 | G102: =DCF!$F$102*(1+Assumptions!$F$42) -> 8499.1351 | H102: =DCF!$G$102*(1+Assumptions!$G$42) -> 8924.0919 | I102: =DCF!$H$102*(1+Assumptions!$H$42) -> 9325.676 | J102: =DCF!$I$102*(1+Assumptions!$I$42) -> 9698.7031
A103: Процентная часть аренды (возвращается в EBIT) | B103: $ млн | D103: =DCF!$D$102*Assumptions!$C$20 -> 468.26 | E103: =DCF!$E$102*Assumptions!$C$20 -> 491.673 | F103: =DCF!$F$102*Assumptions!$C$20 -> 521.17338 | G103: =DCF!$G$102*Assumptions!$C$20 -> 552.44378 | H103: =DCF!$H$102*Assumptions!$C$20 -> 580.06597 | I103: =DCF!$I$102*Assumptions!$C$20 -> 606.16894 | J103: =DCF!$J$102*Assumptions!$C$20 -> 630.4157
...

Sheet ReverseDCF
A1: Reverse DCF: какой рост RASM и какой WACC заложены в цену $103,23
A3: Поправка к базовому росту TRASM в 2027–2032 (п.п. в год) | C3: 2025A | D3: 2026E | E3: 2027E | F3: 2028E | G3: 2029E | H3: 2030E | I3: 2031E | J3: 2032E
A4: Поправки | B4: п.п. | D4: -0.01 | E4: -0.005 | F4: 0 | G4: 0.005 | H4: 0.01 | K4: [Д] сетка
A5: Базовый — reverse DCF | B5: Ед. | C5: 2025A | D5: 2026E | E5: 2027E | F5: 2028E | G5: 2029E | H5: 2030E | I5: 2031E | J5: 2032E | K5: Источник / тип
A6: ASM | B6: млн | C6: =Hist!$I$5 -> 330284 | D6: =ReverseDCF!$C$6*(1+Assumptions!$C$35) -> 338541.1 | E6: =ReverseDCF!$D$6*(1+Assumptions!$D$35) -> 352082.74 | F6: =ReverseDCF!$E$6*(1+Assumptions!$E$35) -> 369686.88 | G6: =ReverseDCF!$F$6*(1+Assumptions!$F$35) -> 388171.23 | H6: =ReverseDCF!$G$6*(1+Assumptions!$G$35) -> 405638.93 | I6: =ReverseDCF!$H$6*(1+Assumptions!$H$35) -> 421864.49 | J6: =ReverseDCF!$I$6*(1+Assumptions!$I$35) -> 436629.74
A7: Галлонов на 1000 ASM | B7: галл. | C7: =Metrics!$I$13 -> 14.118153 | D7: =ReverseDCF!$C$7*(1+Assumptions!$C$15) -> 13.976971 | E7: =ReverseDCF!$D$7*(1+Assumptions!$D$15) -> 13.837202 | F7: =ReverseDCF!$E$7*(1+Assumptions!$E$15) -> 13.69883 | G7: =ReverseDCF!$F$7*(1+Assumptions!$F$15) -> 13.561841 | H7: =ReverseDCF!$G$7*(1+Assumptions!$G$15) -> 13.426223 | I7: =ReverseDCF!$H$7*(1+Assumptions!$H$15) -> 13.291961 | J7: =ReverseDCF!$I$7*(1+Assumptions!$I$15) -> 13.159041
A8: Цена топлива | B8: $/галл. | C8: =Hist!$I$9 -> 2.44 | D8: =Assumptions!$C$39 -> 3.97 | E8: =Assumptions!$D$39 -> 3.3 | F8: =Assumptions!$E$39 -> 3 | G8: =Assumptions!$F$39 -> 2.9 | H8: =Assumptions!$G$39 -> 2.9 | I8: =Assumptions!$H$39 -> 2.95 | J8: =Assumptions!$I$39 -> 3
A9: Топливо на ASM | B9: центы | C9: =ReverseDCF!$C$7*ReverseDCF!$C$8/10 -> 3.4448293 | D9: =ReverseDCF!$D$7*ReverseDCF!$D$8/10 -> 5.5488576 | E9: =ReverseDCF!$E$7*ReverseDCF!$E$8/10 -> 4.5662765 | F9: =ReverseDCF!$F$7*ReverseDCF!$F$8/10 -> 4.1096489 | G9: =ReverseDCF!$G$7*ReverseDCF!$G$8/10 -> 3.932934 | H9: =ReverseDCF!$H$7*ReverseDCF!$H$8/10 -> 3.8936046 | I9: =ReverseDCF!$I$7*ReverseDCF!$I$8/10 -> 3.9211284 | J9: =ReverseDCF!$J$7*ReverseDCF!$J$8/10 -> 3.9477123
A10: TRASM = TRASM(t−1)×(1+базовый рост) + перенос×Δтопливо/ASM | B10: центы | C10: =Metrics!$I$8 -> 17.884608 | D10: =ReverseDCF!$C$10*(1+Assumptions!$C$36)+Assumptions!$C$37*(ReverseDCF!$D$9-ReverseDCF!$C$9) -> 20.014946 | E10: =ReverseDCF!$D$10*(1+Assumptions!$D$36+ReverseDCF!$D$4)+Assumptions!$D$37*(ReverseDCF!$E$9-ReverseDCF!$D$9) -> 19.47816 | F10: =ReverseDCF!$E$10*(1+Assumptions!$E$36+ReverseDCF!$D$4)+Assumptions!$E$37*(ReverseDCF!$F$9-ReverseDCF!$E$9) -> 19.313705 | G10: =ReverseDCF!$F$10*(1+Assumptions!$F$36+ReverseDCF!$D$4)+Assumptions!$F$37*(ReverseDCF!$G$9-ReverseDCF!$F$9) -> 19.426695 | H10: =ReverseDCF!$G$10*(1+Assumptions!$G$36+ReverseDCF!$D$4)+Assumptions!$G$37*(ReverseDCF!$H$9-ReverseDCF!$G$9) -> 19.678766 | I10: =ReverseDCF!$H$10*(1+Assumptions!$H$36+ReverseDCF!$D$4)+Assumptions!$H$37*(ReverseDCF!$I$9-ReverseDCF!$H$9) -> 20.001472 | J10: =ReverseDCF!$I$10*(1+Assumptions!$I$36+ReverseDCF!$D$4)+Assumptions!$I$37*(ReverseDCF!$J$9-ReverseDCF!$I$9) -> 20.328078
A11: Выручка | B11: $ млн | C11: =Hist!$I$19 -> 59070 | D11: =ReverseDCF!$D$6*ReverseDCF!$D$10/100 -> 67758.819 | E11: =ReverseDCF!$E$6*ReverseDCF!$E$10/100 -> 68579.24 | F11: =ReverseDCF!$F$6*ReverseDCF!$F$10/100 -> 71400.232 | G11: =ReverseDCF!$G$6*ReverseDCF!$G$10/100 -> 75408.841 | H11: =ReverseDCF!$H$6*ReverseDCF!$H$10/100 -> 79824.738 | I11: =ReverseDCF!$I$6*ReverseDCF!$I$10/100 -> 84379.106 | J11: =ReverseDCF!$J$6*ReverseDCF!$J$10/100 -> 88758.434
A12: CASM-ex | B12: центы | C12: =Metrics!$I$10 -> 12.64 | D12: =ReverseDCF!$C$12*(1+Assumptions!$C$38) -> 13.3352 | E12: =ReverseDCF!$D$12*(1+Assumptions!$D$38) -> 13.66858 | F12: =ReverseDCF!$E$12*(1+Assumptions!$E$38) -> 13.941952 | G12: =ReverseDCF!$F$12*(1+Assumptions!$F$38) -> 14.262616 | H12: =ReverseDCF!$G$12*(1+Assumptions!$G$38) -> 14.647707 | I12: =ReverseDCF!$H$12*(1+Assumptions!$H$38) -> 15.043195 | J12: =ReverseDCF!$I$12*(1+Assumptions!$I$38) -> 15.449361
A13: Нетопливные расходы (CASM-ex × ASM) | B13: $ млн | D13: =ReverseDCF!$D$6*ReverseDCF!$D$12/100 -> 45145.133 | E13: =ReverseDCF!$E$6*ReverseDCF!$E$12/100 -> 48124.712 | F13: =ReverseDCF!$F$6*ReverseDCF!$F$12/100 -> 51541.566 | G13: =ReverseDCF!$G$6*ReverseDCF!$G$12/100 -> 55363.373 | H13: =ReverseDCF!$H$6*ReverseDCF!$H$12/100 -> 59416.803 | I13: =ReverseDCF!$I$6*ReverseDCF!$I$12/100 -> 63461.898 | J13: =ReverseDCF!$J$6*ReverseDCF!$J$12/100 -> 67456.508
A14: Топливо | B14: $ млн | D14: =ReverseDCF!$D$6*ReverseDCF!$D$9/100 -> 18785.164 | E14: =ReverseDCF!$E$6*ReverseDCF!$E$9/100 -> 16077.072 | F14: =ReverseDCF!$F$6*ReverseDCF!$F$9/100 -> 15192.833 | G14: =ReverseDCF!$G$6*ReverseDCF!$G$9/100 -> 15266.518 | H14: =ReverseDCF!$H$6*ReverseDCF!$H$9/100 -> 15793.976 | I14: =ReverseDCF!$I$6*ReverseDCF!$I$9/100 -> 16541.848 | J14: =ReverseDCF!$J$6*ReverseDCF!$J$9/100 -> 17236.886
A15: Сторонние услуги | B15: $ млн | D15: =ReverseDCF!$D$11*Assumptions!$C$16 -> 304.91469 | E15: =ReverseDCF!$E$11*Assumptions!$D$16 -> 308.60658 | F15: =ReverseDCF!$F$11*Assumptions!$E$16 -> 321.30105 | G15: =ReverseDCF!$G$11*Assumptions!$F$16 -> 339.33979 | H15: =ReverseDCF!$H$11*Assumptions!$G$16 -> 359.21132 | I15: =ReverseDCF!$I$11*Assumptions!$H$16 -> 379.70598 | J15: =ReverseDCF!$J$11*Assumptions!$I$16 -> 399.41295
A16: EBIT до участия в прибыли | B16: $ млн | D16: =ReverseDCF!$D$11-ReverseDCF!$D$13-ReverseDCF!$D$14-ReverseDCF!$D$15 -> 3523.6082 | E16: =ReverseDCF!$E$11-ReverseDCF!$E$13-ReverseDCF!$E$14-ReverseDCF!$E$15 -> 4068.8501 | F16: =ReverseDCF!$F$11-ReverseDCF!$F$13-ReverseDCF!$F$14-ReverseDCF!$F$15 -> 4344.5325 | G16: =ReverseDCF!$G$11-ReverseDCF!$G$13-ReverseDCF!$G$14-ReverseDCF!$G$15 -> 4439.6103 | H16: =ReverseDCF!$H$11-ReverseDCF!$H$13-ReverseDCF!$H$14-ReverseDCF!$H$15 -> 4254.7475 | I16: =ReverseDCF!$I$11-ReverseDCF!$I$13-ReverseDCF!$I$14-ReverseDCF!$I$15 -> 3995.6533 | J16: =ReverseDCF!$J$11-ReverseDCF!$J$13-ReverseDCF!$J$14-ReverseDCF!$J$15 -> 3665.6268
A17: Участие в прибыли | B17: $ млн | D17: =MAX(0,ReverseDCF!$D$16)*Assumptions!$C$17 -> 422.83298 | E17: =MAX(0,ReverseDCF!$E$16)*Assumptions!$D$17 -> 488.26201 | F17: =MAX(0,ReverseDCF!$F$16)*Assumptions!$E$17 -> 521.3439 | G17: =MAX(0,ReverseDCF!$G$16)*Assumptions!$F$17 -> 532.75324 | H17: =MAX(0,ReverseDCF!$H$16)*Assumptions!$G$17 -> 510.5697 | I17: =MAX(0,ReverseDCF!$I$16)*Assumptions!$H$17 -> 479.4784 | J17: =MAX(0,ReverseDCF!$J$16)*Assumptions!$I$17 -> 439.87522
A18: Скорр. EBIT | B18: $ млн | C18: =Hist!$I$31 -> 4972 | D18: =ReverseDCF!$D$16-ReverseDCF!$D$17 -> 3100.7752 | E18: =ReverseDCF!$E$16-ReverseDCF!$E$17 -> 3580.5881 | F18: =ReverseDCF!$F$16-ReverseDCF!$F$17 -> 3823.1886 | G18: =ReverseDCF!$G$16-ReverseDCF!$G$17 -> 3906.8571 | H18: =ReverseDCF!$H$16-ReverseDCF!$H$17 -> 3744.1778 | I18: =ReverseDCF!$I$16-ReverseDCF!$I$17 -> 3516.1749 | J18: =ReverseDCF!$J$16-ReverseDCF!$J$17 -> 3225.7516
A19: Скорр. операционная маржа | B19: % | C19: =ReverseDCF!$C$18/ReverseDCF!$C$11 -> 0.084171322 | D19: =ReverseDCF!$D$18/ReverseDCF!$D$11 -> 0.045761943 | E19: =ReverseDCF!$E$18/ReverseDCF!$E$11 -> 0.052210962 | F19: =ReverseDCF!$F$18/ReverseDCF!$F$11 -> 0.053545885 | G19: =ReverseDCF!$G$18/ReverseDCF!$G$11 -> 0.051809005 | H19: =ReverseDCF!$H$18/ReverseDCF!$H$11 -> 0.046904981 | I19: =ReverseDCF!$I$18/ReverseDCF!$I$11 -> 0.041671156 | J19: =ReverseDCF!$J$18/ReverseDCF!$J$11 -> 0.036343043
A20: D&A | B20: $ млн | C20: =Hist!$I$26 -> 2939 | D20: =ReverseDCF!$D$11*Assumptions!$C$18 -> 3252.4233 | E20: =ReverseDCF!$E$11*Assumptions!$D$18 -> 3291.8035 | F20: =ReverseDCF!$F$11*Assumptions!$E$18 -> 3427.2112 | G20: =ReverseDCF!$G$11*Assumptions!$F$18 -> 3619.6244 | H20: =ReverseDCF!$H$11*Assumptions!$G$18 -> 3831.5874 | I20: =ReverseDCF!$I$11*Assumptions!$H$18 -> 4050.1971 | J20: =ReverseDCF!$J$11*Assumptions!$I$18 -> 4260.4048
A21: EBITDAR = EBIT + D&A + фикс. аренда | B21: $ млн | C21: =Metrics!$I$31 -> 8970 | D21: =ReverseDCF!$D$18+ReverseDCF!$D$20+ReverseDCF!$D$11*Assumptions!$C$19 -> 7403.4602 | E21: =ReverseDCF!$E$18+ReverseDCF!$E$20+ReverseDCF!$E$11*Assumptions!$D$19 -> 7935.3698 | F21: =ReverseDCF!$F$18+ReverseDCF!$F$20+ReverseDCF!$F$11*Assumptions!$E$19 -> 8357.1034 | G21: =ReverseDCF!$G$18+ReverseDCF!$G$20+ReverseDCF!$G$11*Assumptions!$F$19 -> 8695.3185 | H21: =ReverseDCF!$H$18+ReverseDCF!$H$20+ReverseDCF!$H$11*Assumptions!$G$19 -> 8813.0487 | I21: =ReverseDCF!$I$18+ReverseDCF!$I$20+ReverseDCF!$I$11*Assumptions!$H$19 -> 8874.2482 | J21: =ReverseDCF!$J$18+ReverseDCF!$J$20+ReverseDCF!$J$11*Assumptions!$I$19 -> 8861.9121
A22: Обязательства по опер. аренде | B22: $ млн | D22: =Hist!$K$51 -> 7204 | E22: =ReverseDCF!$D$22*(1+Assumptions!$D$35) -> 7492.16 | F22: =ReverseDCF!$E$22*(1+Assumptions!$E$35) -> 7866.768 | G22: =ReverseDCF!$F$22*(1+Assumptions!$F$35) -> 8260.1064 | H22: =ReverseDCF!$G$22*(1+Assumptions!$G$35) -> 8631.8112 | I22: =ReverseDCF!$H$22*(1+Assumptions!$H$35) -> 8977.0836 | J22: =ReverseDCF!$I$22*(1+Assumptions!$I$35) -> 9291.2816
A23: Процентная часть аренды (возвращается в EBIT) | B23: $ млн | D23: =ReverseDCF!$D$22*Assumptions!$C$20 -> 468.26 | E23: =ReverseDCF!$E$22*Assumptions!$C$20 -> 486.9904 | F23: =ReverseDCF!$F$22*Assumptions!$C$20 -> 511.33992 | G23: =ReverseDCF!$G$22*Assumptions!$C$20 -> 536.90692 | H23: =ReverseDCF!$H$22*Assumptions!$C$20 -> 561.06773 | I23: =ReverseDCF!$I$22*Assumptions!$C$20 -> 583.51044 | J23: =ReverseDCF!$J$22*Assumptions!$C$20 -> 603.9333
A24: NOPAT (с поправкой на аренду) = (EBIT + % аренды) × (1 − t) | B24: $ млн | D24: =(ReverseDCF!$D$18+ReverseDCF!$D$23)*(1-Assumptions!$C$10) -> 2783.8474 | E24: =(ReverseDCF!$E$18+ReverseDCF!$E$23)*(1-Assumptions!$C$10) -> 3172.7112 | F24: =(ReverseDCF!$F$18+ReverseDCF!$F$23)*(1-Assumptions!$C$10) -> 3380.9323 | G24: =(ReverseDCF!$G$18+ReverseDCF!$G$23)*(1-Assumptions!$C$10) -> 3466.1359 | H24: =(ReverseDCF!$H$18+ReverseDCF!$H$23)*(1-Assumptions!$C$10) -> 3358.0915 | I24: =(ReverseDCF!$I$18+ReverseDCF!$I$23)*(1-Assumptions!$C$10) -> 3197.7546 | J24: =(ReverseDCF!$J$18+ReverseDCF!$J$23)*(1-Assumptions!$C$10) -> 2987.1542
A25: Скорр. капзатраты | B25: $ млн | D25: =Assumptions!$C$23 -> 7500 | E25: =ReverseDCF!$E$11*Assumptions!$D$40 -> 7886.6126 | F25: =ReverseDCF!$F$11*Assumptions!$E$40 -> 8568.0279 | G25: =ReverseDCF!$G$11*Assumptions!$F$40 -> 9049.061 | H25: =ReverseDCF!$H$11*Assumptions!$G$40 -> 8780.7211 | I25: =ReverseDCF!$I$11*Assumptions!$H$40 -> 8859.8061 | J25: =ReverseDCF!$J$11*Assumptions!$I$40 -> 8875.8434
A26: Приток оборотного капитала | B26: $ млн | D26: =(ReverseDCF!$D$11-ReverseDCF!$C$11)*Assumptions!$C$21 -> 868.88192 | E26: =(ReverseDCF!$E$11-ReverseDCF!$D$11)*Assumptions!$D$21 -> 82.042066 | F26: =(ReverseDCF!$F$11-ReverseDCF!$E$11)*Assumptions!$E$21 -> 282.09925 | G26: =(ReverseDCF!$G$11-ReverseDCF!$F$11)*Assumptions!$F$21 -> 400.86089 | H26: =(ReverseDCF!$H$11-ReverseDCF!$G$11)*Assumptions!$G$21 -> 441.58963 | I26: =(ReverseDCF!$I$11-ReverseDCF!$H$11)*Assumptions!$H$21 -> 455.43684 | J26: =(ReverseDCF!$J$11-ReverseDCF!$I$11)*Assumptions!$I$21 -> 437.93276
A27: FCFF = NOPAT + D&A − капзатраты + Δоборотный капитал | B27: $ млн | D27: =ReverseDCF!$D$24+ReverseDCF!$D$20-ReverseDCF!$D$25+ReverseDCF!$D$26 -> -594.8473 | E27: =ReverseDCF!$E$24+ReverseDCF!$E$20-ReverseDCF!$E$25+ReverseDCF!$E$26 -> -1340.0558 | F27: =ReverseDCF!$F$24+ReverseDCF!$F$20-ReverseDCF!$F$25+ReverseDCF!$F$26 -> -1477.7852 | G27: =ReverseDCF!$G$24+ReverseDCF!$G$20-ReverseDCF!$G$25+ReverseDCF!$G$26 -> -1562.4398 | H27: =ReverseDCF!$H$24+ReverseDCF!$H$20-ReverseDCF!$H$25+ReverseDCF!$H$26 -> -1149.4526 | I27: =ReverseDCF!$I$24+ReverseDCF!$I$20-ReverseDCF!$I$25+ReverseDCF!$I$26 -> -1156.4176 | J27: =ReverseDCF!$J$24+ReverseDCF!$J$20-ReverseDCF!$J$25+ReverseDCF!$J$26 -> -1190.3516
A28: FCFF к дисконтированию (2026E — только 2П: минус факт 1П26) | B28: $ млн | D28: =ReverseDCF!$D$27-Assumptions!$C$12 -> -4032.7873 | E28: =ReverseDCF!$E$27 -> -1340.0558 | F28: =ReverseDCF!$F$27 -> -1477.7852 | G28: =ReverseDCF!$G$27 -> -1562.4398 | H28: =ReverseDCF!$H$27 -> -1149.4526 | I28: =ReverseDCF!$I$27 -> -1156.4176 | J28: =ReverseDCF!$J$27 -> -1190.3516
A29: Период дисконтирования (лет от 30.06.2026, середина периода) | B29: лет | D29: 0.25 | E29: 1 | F29: 2 | G29: 3 | H29: 4 | I29: 5 | J29: 6 | K29: [Д] середина периода; 2П26 = 0,25
A30: Коэффициент дисконтирования | B30: x | D30: =1/(1+WACC!$C$14)^ReverseDCF!$D$29 -> 0.97980256 | E30: =1/(1+WACC!$C$14)^ReverseDCF!$E$29 -> 0.92162505 | F30: =1/(1+WACC!$C$14)^ReverseDCF!$F$29 -> 0.84939274 | G30: =1/(1+WACC!$C$14)^ReverseDCF!$G$29 -> 0.78282163 | H30: =1/(1+WACC!$C$14)^ReverseDCF!$H$29 -> 0.72146802 | I30: =1/(1+WACC!$C$14)^ReverseDCF!$I$29 -> 0.664923 | J30: =1/(1+WACC!$C$14)^ReverseDCF!$J$29 -> 0.6128097
A31: PV FCFF | B31: $ млн | D31: =ReverseDCF!$D$28*ReverseDCF!$D$30 -> -3951.3353 | E31: =ReverseDCF!$E$28*ReverseDCF!$E$30 -> -1235.029 | F31: =ReverseDCF!$F$28*ReverseDCF!$F$30 -> -1255.22 | G31: =ReverseDCF!$G$28*ReverseDCF!$G$30 -> -1223.1116 | H31: =ReverseDCF!$H$28*ReverseDCF!$H$30 -> -829.29327 | I31: =ReverseDCF!$I$28*ReverseDCF!$I$30 -> -768.92868 | J31: =ReverseDCF!$J$28*ReverseDCF!$J$30 -> -729.45899
A32: EPS скорр. = (EBIT − чистые %) × (1 − t) / акции | B32: $ | D32: =(ReverseDCF!$D$18-Assumptions!$C$22)*(1-Assumptions!$C$10)/Assumptions!$C$6 -> 6.0918697 | E32: =(ReverseDCF!$E$18-Assumptions!$D$22)*(1-Assumptions!$C$10)/Assumptions!$C$6 -> 7.2377792 | F32: =(ReverseDCF!$F$18-Assumptions!$E$22)*(1-Assumptions!$C$10)/Assumptions!$C$6 -> 7.8171682 | G32: =(ReverseDCF!$G$18-Assumptions!$F$22)*(1-Assumptions!$C$10)/Assumptions!$C$6 -> 8.0169887 | H32: =(ReverseDCF!$H$18-Assumptions!$G$22)*(1-Assumptions!$C$10)/Assumptions!$C$6 -> 7.6284712 | I32: =(ReverseDCF!$I$18-Assumptions!$H$22)*(1-Assumptions!$C$10)/Assumptions!$C$6 -> 7.083945 | J32: =(ReverseDCF!$J$18-Assumptions!$I$22)*(1-Assumptions!$C$10)/Assumptions!$C$6 -> 6.3903436
A33: Сумма PV FCFF 2П26–2032E | B33: $ млн | J33: =SUM(D31:J31) -> -9992.3769
A34: TV Гордон = NOPAT×(1+g)×(1−g/RONIC)/(WACC−g) | B34: $ млн | J34: =ReverseDCF!$J$24*(1+Assumptions!$C$24)*(1-Assumptions!$C$24/Assumptions!$C$25)/(WACC!$C$14-Assumptions!$C$24) -> 38247.448
A35: Выходной мультипликатор EV/EBITDAR | B35: x | J35: =Multiples!$C$52 -> 6.2149084 | K35: история UAL: мин / медиана / макс (лист Multiples)
A36: TV по мультипликатору = EV/EBITDAR × EBITDAR 2032E | B36: $ млн | J36: =ReverseDCF!$J$35*ReverseDCF!$J$21 -> 55075.972
A37: Дисконт TV (6,5 года) | B37: x | J37: =1/(1+WACC!$C$14)^6.5 -> 0.58830531
A38: EV (Гордон) | B38: $ млн | J38: =ReverseDCF!$J$33+ReverseDCF!$J$34*ReverseDCF!$J$37 -> 12508.799
A39: EV (мультипликатор) | B39: $ млн | J39: =ReverseDCF!$J$33+ReverseDCF!$J$36*ReverseDCF!$J$37 -> 22409.11
A40: Доля TV в EV (Гордон) | B40: % | J40: =ReverseDCF!$J$34*ReverseDCF!$J$37/ReverseDCF!$J$38 -> 1.7988278
A41: Стоимость акции (Гордон) = (EV − чистый скорр. долг + NOL) / акции | B41: $ | J41: =(ReverseDCF!$J$38-WACC!$C$15+Assumptions!$C$11)/Assumptions!$C$6 -> -11.011024
A42: Стоимость акции (мультипликатор) | B42: $ | J42: =(ReverseDCF!$J$39-WACC!$C$15+Assumptions!$C$11)/Assumptions!$C$6 -> 19.302234
A43: Стоимость акции DCF (взвешенная) | B43: $ | J43: =Assumptions!$C$13*ReverseDCF!$J$41+(1-Assumptions!$C$13)*ReverseDCF!$J$42 -> 4.1456049
A44: Проверка: EV/EBITDAR, заложенный в TV Гордона | B44: x | J44: =ReverseDCF!$J$34/ReverseDCF!$J$21 -> 4.3159362
A46: Базовый — reverse DCF | B46: Ед. | C46: 2025A | D46: 2026E | E46: 2027E | F46: 2028E | G46: 2029E | H46: 2030E | I46: 2031E | J46: 2032E | K46: Источник / тип
A47: ASM | B47: млн | C47: =Hist!$I$5 -> 330284 | D47: =ReverseDCF!$C$47*(1+Assumptions!$C$35) -> 338541.1 | E47: =ReverseDCF!$D$47*(1+Assumptions!$D$35) -> 352082.74 | F47: =ReverseDCF!$E$47*(1+Assumptions!$E$35) -> 369686.88 | G47: =ReverseDCF!$F$47*(1+Assumptions!$F$35) -> 388171.23 | H47: =ReverseDCF!$G$47*(1+Assumptions!$G$35) -> 405638.93 | I47: =ReverseDCF!$H$47*(1+Assumptions!$H$35) -> 421864.49 | J47: =ReverseDCF!$I$47*(1+Assumptions!$I$35) -> 436629.74
A48: Галлонов на 1000 ASM | B48: галл. | C48: =Metrics!$I$13 -> 14.118153 | D48: =ReverseDCF!$C$48*(1+Assumptions!$C$15) -> 13.976971 | E48: =ReverseDCF!$D$48*(1+Assumptions!$D$15) -> 13.837202 | F48: =ReverseDCF!$E$48*(1+Assumptions!$E$15) -> 13.69883 | G48: =ReverseDCF!$F$48*(1+Assumptions!$F$15) -> 13.561841 | H48: =ReverseDCF!$G$48*(1+Assumptions!$G$15) -> 13.426223 | I48: =ReverseDCF!$H$48*(1+Assumptions!$H$15) -> 13.291961 | J48: =ReverseDCF!$I$48*(1+Assumptions!$I$15) -> 13.159041
A49: Цена топлива | B49: $/галл. | C49: =Hist!$I$9 -> 2.44 | D49: =Assumptions!$C$39 -> 3.97 | E49: =Assumptions!$D$39 -> 3.3 | F49: =Assumptions!$E$39 -> 3 | G49: =Assumptions!$F$39 -> 2.9 | H49: =Assumptions!$G$39 -> 2.9 | I49: =Assumptions!$H$39 -> 2.95 | J49: =Assumptions!$I$39 -> 3
A50: Топливо на ASM | B50: центы | C50: =ReverseDCF!$C$48*ReverseDCF!$C$49/10 -> 3.4448293 | D50: =ReverseDCF!$D$48*ReverseDCF!$D$49/10 -> 5.5488576 | E50: =ReverseDCF!$E$48*ReverseDCF!$E$49/10 -> 4.5662765 | F50: =ReverseDCF!$F$48*ReverseDCF!$F$49/10 -> 4.1096489 | G50: =ReverseDCF!$G$48*ReverseDCF!$G$49/10 -> 3.932934 | H50: =ReverseDCF!$H$48*ReverseDCF!$H$49/10 -> 3.8936046 | I50: =ReverseDCF!$I$48*ReverseDCF!$I$49/10 -> 3.9211284 | J50: =ReverseDCF!$J$48*ReverseDCF!$J$49/10 -> 3.9477123
A51: TRASM = TRASM(t−1)×(1+базовый рост) + перенос×Δтопливо/ASM | B51: центы | C51: =Metrics!$I$8 -> 17.884608 | D51: =ReverseDCF!$C$51*(1+Assumptions!$C$36)+Assumptions!$C$37*(ReverseDCF!$D$50-ReverseDCF!$C$50) -> 20.014946 | E51: =ReverseDCF!$D$51*(1+Assumptions!$D$36+ReverseDCF!$E$4)+Assumptions!$D$37*(ReverseDCF!$E$50-ReverseDCF!$D$50) -> 19.578235 | F51: =ReverseDCF!$E$51*(1+Assumptions!$E$36+ReverseDCF!$E$4)+Assumptions!$E$37*(ReverseDCF!$F$50-ReverseDCF!$E$50) -> 19.513172 | G51: =ReverseDCF!$F$51*(1+Assumptions!$F$36+ReverseDCF!$E$4)+Assumptions!$F$37*(ReverseDCF!$G$50-ReverseDCF!$F$50) -> 19.72672 | H51: =ReverseDCF!$G$51*(1+Assumptions!$G$36+ReverseDCF!$E$4)+Assumptions!$G$37*(ReverseDCF!$H$50-ReverseDCF!$G$50) -> 20.081925 | I51: =ReverseDCF!$H$51*(1+Assumptions!$H$36+ReverseDCF!$E$4)+Assumptions!$H$37*(ReverseDCF!$I$50-ReverseDCF!$H$50) -> 20.511088 | J51: =ReverseDCF!$I$51*(1+Assumptions!$I$36+ReverseDCF!$E$4)+Assumptions!$I$37*(ReverseDCF!$J$50-ReverseDCF!$I$50) -> 20.947893
A52: Выручка | B52: $ млн | C52: =Hist!$I$19 -> 59070 | D52: =ReverseDCF!$D$47*ReverseDCF!$D$51/100 -> 67758.819 | E52: =ReverseDCF!$E$47*ReverseDCF!$E$51/100 -> 68931.586 | F52: =ReverseDCF!$F$47*ReverseDCF!$F$51/100 -> 72137.636 | G52: =ReverseDCF!$G$47*ReverseDCF!$G$51/100 -> 76573.452 | H52: =ReverseDCF!$H$47*ReverseDCF!$H$51/100 -> 81460.107 | I52: =ReverseDCF!$I$47*ReverseDCF!$I$51/100 -> 86528.994 | J52: =ReverseDCF!$J$47*ReverseDCF!$J$51/100 -> 91464.733
A53: CASM-ex | B53: центы | C53: =Metrics!$I$10 -> 12.64 | D53: =ReverseDCF!$C$53*(1+Assumptions!$C$38) -> 13.3352 | E53: =ReverseDCF!$D$53*(1+Assumptions!$D$38) -> 13.66858 | F53: =ReverseDCF!$E$53*(1+Assumptions!$E$38) -> 13.941952 | G53: =ReverseDCF!$F$53*(1+Assumptions!$F$38) -> 14.262616 | H53: =ReverseDCF!$G$53*(1+Assumptions!$G$38) -> 14.647707 | I53: =ReverseDCF!$H$53*(1+Assumptions!$H$38) -> 15.043195 | J53: =ReverseDCF!$I$53*(1+Assumptions!$I$38) -> 15.449361
A54: Нетопливные расходы (CASM-ex × ASM) | B54: $ млн | D54: =ReverseDCF!$D$47*ReverseDCF!$D$53/100 -> 45145.133 | E54: =ReverseDCF!$E$47*ReverseDCF!$E$53/100 -> 48124.712 | F54: =ReverseDCF!$F$47*ReverseDCF!$F$53/100 -> 51541.566 | G54: =ReverseDCF!$G$47*ReverseDCF!$G$53/100 -> 55363.373 | H54: =ReverseDCF!$H$47*ReverseDCF!$H$53/100 -> 59416.803 | I54: =ReverseDCF!$I$47*ReverseDCF!$I$53/100 -> 63461.898 | J54: =ReverseDCF!$J$47*ReverseDCF!$J$53/100 -> 67456.508
A55: Топливо | B55: $ млн | D55: =ReverseDCF!$D$47*ReverseDCF!$D$50/100 -> 18785.164 | E55: =ReverseDCF!$E$47*ReverseDCF!$E$50/100 -> 16077.072 | F55: =ReverseDCF!$F$47*ReverseDCF!$F$50/100 -> 15192.833 | G55: =ReverseDCF!$G$47*ReverseDCF!$G$50/100 -> 15266.518 | H55: =ReverseDCF!$H$47*ReverseDCF!$H$50/100 -> 15793.976 | I55: =ReverseDCF!$I$47*ReverseDCF!$I$50/100 -> 16541.848 | J55: =ReverseDCF!$J$47*ReverseDCF!$J$50/100 -> 17236.886
A56: Сторонние услуги | B56: $ млн | D56: =ReverseDCF!$D$52*Assumptions!$C$16 -> 304.91469 | E56: =ReverseDCF!$E$52*Assumptions!$D$16 -> 310.19214 | F56: =ReverseDCF!$F$52*Assumptions!$E$16 -> 324.61936 | G56: =ReverseDCF!$G$52*Assumptions!$F$16 -> 344.58053 | H56: =ReverseDCF!$H$52*Assumptions!$G$16 -> 366.57048 | I56: =ReverseDCF!$I$52*Assumptions!$H$16 -> 389.38047 | J56: =ReverseDCF!$J$52*Assumptions!$I$16 -> 411.5913
A57: EBIT до участия в прибыли | B57: $ млн | D57: =ReverseDCF!$D$52-ReverseDCF!$D$54-ReverseDCF!$D$55-ReverseDCF!$D$56 -> 3523.6082 | E57: =ReverseDCF!$E$52-ReverseDCF!$E$54-ReverseDCF!$E$55-ReverseDCF!$E$56 -> 4419.6104 | F57: =ReverseDCF!$F$52-ReverseDCF!$F$54-ReverseDCF!$F$55-ReverseDCF!$F$56 -> 5078.6176 | G57: =ReverseDCF!$G$52-ReverseDCF!$G$54-ReverseDCF!$G$55-ReverseDCF!$G$56 -> 5598.9798 | H57: =ReverseDCF!$H$52-ReverseDCF!$H$54-ReverseDCF!$H$55-ReverseDCF!$H$56 -> 5882.7577 | I57: =ReverseDCF!$I$52-ReverseDCF!$I$54-ReverseDCF!$I$55-ReverseDCF!$I$56 -> 6135.8672 | J57: =ReverseDCF!$J$52-ReverseDCF!$J$54-ReverseDCF!$J$55-ReverseDCF!$J$56 -> 6359.7475
A58: Участие в прибыли | B58: $ млн | D58: =MAX(0,ReverseDCF!$D$57)*Assumptions!$C$17 -> 422.83298 | E58: =MAX(0,ReverseDCF!$E$57)*Assumptions!$D$17 -> 530.35325 | F58: =MAX(0,ReverseDCF!$F$57)*Assumptions!$E$17 -> 609.43412 | G58: =MAX(0,ReverseDCF!$G$57)*Assumptions!$F$17 -> 671.87758 | H58: =MAX(0,ReverseDCF!$H$57)*Assumptions!$G$17 -> 705.93092 | I58: =MAX(0,ReverseDCF!$I$57)*Assumptions!$H$17 -> 736.30407 | J58: =MAX(0,ReverseDCF!$J$57)*Assumptions!$I$17 -> 763.1697
A59: Скорр. EBIT | B59: $ млн | C59: =Hist!$I$31 -> 4972 | D59: =ReverseDCF!$D$57-ReverseDCF!$D$58 -> 3100.7752 | E59: =ReverseDCF!$E$57-ReverseDCF!$E$58 -> 3889.2571 | F59: =ReverseDCF!$F$57-ReverseDCF!$F$58 -> 4469.1835 | G59: =ReverseDCF!$G$57-ReverseDCF!$G$58 -> 4927.1023 | H59: =ReverseDCF!$H$57-ReverseDCF!$H$58 -> 5176.8268 | I59: =ReverseDCF!$I$57-ReverseDCF!$I$58 -> 5399.5632 | J59: =ReverseDCF!$J$57-ReverseDCF!$J$58 -> 5596.5778
A60: Скорр. операционная маржа | B60: % | C60: =ReverseDCF!$C$59/ReverseDCF!$C$52 -> 0.084171322 | D60: =ReverseDCF!$D$59/ReverseDCF!$D$52 -> 0.045761943 | E60: =ReverseDCF!$E$59/ReverseDCF!$E$52 -> 0.056421988 | F60: =ReverseDCF!$F$59/ReverseDCF!$F$52 -> 0.061953562 | G60: =ReverseDCF!$G$59/ReverseDCF!$G$52 -> 0.064344785 | H60: =ReverseDCF!$H$59/ReverseDCF!$H$52 -> 0.063550454 | I60: =ReverseDCF!$I$59/ReverseDCF!$I$52 -> 0.062401779 | J60: =ReverseDCF!$J$59/ReverseDCF!$J$52 -> 0.061188369
A61: D&A | B61: $ млн | C61: =Hist!$I$26 -> 2939 | D61: =ReverseDCF!$D$52*Assumptions!$C$18 -> 3252.4233 | E61: =ReverseDCF!$E$52*Assumptions!$D$18 -> 3308.7161 | F61: =ReverseDCF!$F$52*Assumptions!$E$18 -> 3462.6065 | G61: =ReverseDCF!$G$52*Assumptions!$F$18 -> 3675.5257 | H61: =ReverseDCF!$H$52*Assumptions!$G$18 -> 3910.0851 | I61: =ReverseDCF!$I$52*Assumptions!$H$18 -> 4153.3917 | J61: =ReverseDCF!$J$52*Assumptions!$I$18 -> 4390.3072
A62: EBITDAR = EBIT + D&A + фикс. аренда | B62: $ млн | C62: =Metrics!$I$31 -> 8970 | D62: =ReverseDCF!$D$59+ReverseDCF!$D$61+ReverseDCF!$D$52*Assumptions!$C$19 -> 7403.4602 | E62: =ReverseDCF!$E$59+ReverseDCF!$E$61+ReverseDCF!$E$52*Assumptions!$D$19 -> 8266.4128 | F62: =ReverseDCF!$F$59+ReverseDCF!$F$61+ReverseDCF!$F$52*Assumptions!$E$19 -> 9049.9234 | G62: =ReverseDCF!$G$59+ReverseDCF!$G$61+ReverseDCF!$G$52*Assumptions!$F$19 -> 9789.5164 | H62: =ReverseDCF!$H$59+ReverseDCF!$H$61+ReverseDCF!$H$52*Assumptions!$G$19 -> 10349.544 | I62: =ReverseDCF!$I$59+ReverseDCF!$I$61+ReverseDCF!$I$52*Assumptions!$H$19 -> 10894.154 | J62: =ReverseDCF!$J$59+ReverseDCF!$J$61+ReverseDCF!$J$52*Assumptions!$I$19 -> 11404.588
A63: Обязательства по опер. аренде | B63: $ млн | D63: =Hist!$K$51 -> 7204 | E63: =ReverseDCF!$D$63*(1+Assumptions!$D$35) -> 7492.16 | F63: =ReverseDCF!$E$63*(1+Assumptions!$E$35) -> 7866.768 | G63: =ReverseDCF!$F$63*(1+Assumptions!$F$35) -> 8260.1064 | H63: =ReverseDCF!$G$63*(1+Assumptions!$G$35) -> 8631.8112 | I63: =ReverseDCF!$H$63*(1+Assumptions!$H$35) -> 8977.0836 | J63: =ReverseDCF!$I$63*(1+Assumptions!$I$35) -> 9291.2816
A64: Процентная часть аренды (возвращается в EBIT) | B64: $ млн | D64: =ReverseDCF!$D$63*Assumptions!$C$20 -> 468.26 | E64: =ReverseDCF!$E$63*Assumptions!$C$20 -> 486.9904 | F64: =ReverseDCF!$F$63*Assumptions!$C$20 -> 511.33992 | G64: =ReverseDCF!$G$63*Assumptions!$C$20 -> 536.90692 | H64: =ReverseDCF!$H$63*Assumptions!$C$20 -> 561.06773 | I64: =ReverseDCF!$I$63*Assumptions!$C$20 -> 583.51044 | J64: =ReverseDCF!$J$63*Assumptions!$C$20 -> 603.9333
A65: NOPAT (с поправкой на аренду) = (EBIT + % аренды) × (1 − t) | B65: $ млн | D65: =(ReverseDCF!$D$59+ReverseDCF!$D$64)*(1-Assumptions!$C$10) -> 2783.8474 | E65: =(ReverseDCF!$E$59+ReverseDCF!$E$64)*(1-Assumptions!$C$10) -> 3413.4731 | F65: =(ReverseDCF!$F$59+ReverseDCF!$F$64)*(1-Assumptions!$C$10) -> 3884.8083 | G65: =(ReverseDCF!$G$59+ReverseDCF!$G$64)*(1-Assumptions!$C$10) -> 4261.9272 | H65: =(ReverseDCF!$H$59+ReverseDCF!$H$64)*(1-Assumptions!$C$10) -> 4475.5577 | I65: =(ReverseDCF!$I$59+ReverseDCF!$I$64)*(1-Assumptions!$C$10) -> 4666.7974 | J65: =(ReverseDCF!$J$59+ReverseDCF!$J$64)*(1-Assumptions!$C$10) -> 4836.3987
A66: Скорр. капзатраты | B66: $ млн | D66: =Assumptions!$C$23 -> 7500 | E66: =ReverseDCF!$E$52*Assumptions!$D$40 -> 7927.1324 | F66: =ReverseDCF!$F$52*Assumptions!$E$40 -> 8656.5163 | G66: =ReverseDCF!$G$52*Assumptions!$F$40 -> 9188.8142 | H66: =ReverseDCF!$H$52*Assumptions!$G$40 -> 8960.6118 | I66: =ReverseDCF!$I$52*Assumptions!$H$40 -> 9085.5444 | J66: =ReverseDCF!$J$52*Assumptions!$I$40 -> 9146.4733
A67: Приток оборотного капитала | B67: $ млн | D67: =(ReverseDCF!$D$52-ReverseDCF!$C$52)*Assumptions!$C$21 -> 868.88192 | E67: =(ReverseDCF!$E$52-ReverseDCF!$D$52)*Assumptions!$D$21 -> 117.27665 | F67: =(ReverseDCF!$F$52-ReverseDCF!$E$52)*Assumptions!$E$21 -> 320.60501 | G67: =(ReverseDCF!$G$52-ReverseDCF!$F$52)*Assumptions!$F$21 -> 443.58157 | H67: =(ReverseDCF!$H$52-ReverseDCF!$G$52)*Assumptions!$G$21 -> 488.66553 | I67: =(ReverseDCF!$I$52-ReverseDCF!$H$52)*Assumptions!$H$21 -> 506.88875 | J67: =(ReverseDCF!$J$52-ReverseDCF!$I$52)*Assumptions!$I$21 -> 493.57383
A68: FCFF = NOPAT + D&A − капзатраты + Δоборотный капитал | B68: $ млн | D68: =ReverseDCF!$D$65+ReverseDCF!$D$61-ReverseDCF!$D$66+ReverseDCF!$D$67 -> -594.8473 | E68: =ReverseDCF!$E$65+ReverseDCF!$E$61-ReverseDCF!$E$66+ReverseDCF!$E$67 -> -1087.6665 | F68: =ReverseDCF!$F$65+ReverseDCF!$F$61-ReverseDCF!$F$66+ReverseDCF!$F$67 -> -988.49649 | G68: =ReverseDCF!$G$65+ReverseDCF!$G$61-ReverseDCF!$G$66+ReverseDCF!$G$67 -> -807.77978 | H68: =ReverseDCF!$H$65+ReverseDCF!$H$61-ReverseDCF!$H$66+ReverseDCF!$H$67 -> -86.303396 | I68: =ReverseDCF!$I$65+ReverseDCF!$I$61-ReverseDCF!$I$66+ReverseDCF!$I$67 -> 241.53347 | J68: =ReverseDCF!$J$65+ReverseDCF!$J$61-ReverseDCF!$J$66+ReverseDCF!$J$67 -> 573.80639
A69: FCFF к дисконтированию (2026E — только 2П: минус факт 1П26) | B69: $ млн | D69: =ReverseDCF!$D$68-Assumptions!$C$12 -> -4032.7873 | E69: =ReverseDCF!$E$68 -> -1087.6665 | F69: =ReverseDCF!$F$68 -> -988.49649 | G69: =ReverseDCF!$G$68 -> -807.77978 | H69: =ReverseDCF!$H$68 -> -86.303396 | I69: =ReverseDCF!$I$68 -> 241.53347 | J69: =ReverseDCF!$J$68 -> 573.80639
A70: Период дисконтирования (лет от 30.06.2026, середина периода) | B70: лет | D70: 0.25 | E70: 1 | F70: 2 | G70: 3 | H70: 4 | I70: 5 | J70: 6 | K70: [Д] середина периода; 2П26 = 0,25
A71: Коэффициент дисконтирования | B71: x | D71: =1/(1+WACC!$C$14)^ReverseDCF!$D$70 -> 0.97980256 | E71: =1/(1+WACC!$C$14)^ReverseDCF!$E$70 -> 0.92162505 | F71: =1/(1+WACC!$C$14)^ReverseDCF!$F$70 -> 0.84939274 | G71: =1/(1+WACC!$C$14)^ReverseDCF!$G$70 -> 0.78282163 | H71: =1/(1+WACC!$C$14)^ReverseDCF!$H$70 -> 0.72146802 | I71: =1/(1+WACC!$C$14)^ReverseDCF!$I$70 -> 0.664923 | J71: =1/(1+WACC!$C$14)^ReverseDCF!$J$70 -> 0.6128097
A72: PV FCFF | B72: $ млн | D72: =ReverseDCF!$D$69*ReverseDCF!$D$71 -> -3951.3353 | E72: =ReverseDCF!$E$69*ReverseDCF!$E$71 -> -1002.4207 | F72: =ReverseDCF!$F$69*ReverseDCF!$F$71 -> -839.62174 | G72: =ReverseDCF!$G$69*ReverseDCF!$G$71 -> -632.34748 | H72: =ReverseDCF!$H$69*ReverseDCF!$H$71 -> -62.265141 | I72: =ReverseDCF!$I$69*ReverseDCF!$I$71 -> 160.60116 | J72: =ReverseDCF!$J$69*ReverseDCF!$J$71 -> 351.63412
A73: EPS скорр. = (EBIT − чистые %) × (1 − t) / акции | B73: $ | D73: =(ReverseDCF!$D$59-Assumptions!$C$22)*(1-Assumptions!$C$10)/Assumptions!$C$6 -> 6.0918697 | E73: =(ReverseDCF!$E$59-Assumptions!$D$22)*(1-Assumptions!$C$10)/Assumptions!$C$6 -> 7.9749558 | F73: =(ReverseDCF!$F$59-Assumptions!$E$22)*(1-Assumptions!$C$10)/Assumptions!$C$6 -> 9.3599606 | G73: =(ReverseDCF!$G$59-Assumptions!$F$22)*(1-Assumptions!$C$10)/Assumptions!$C$6 -> 10.453582 | H73: =(ReverseDCF!$H$59-Assumptions!$G$22)*(1-Assumptions!$C$10)/Assumptions!$C$6 -> 11.049984 | I73: =(ReverseDCF!$I$59-Assumptions!$H$22)*(1-Assumptions!$C$10)/Assumptions!$C$6 -> 11.581933 | J73: =(ReverseDCF!$J$59-Assumptions!$I$22)*(1-Assumptions!$C$10)/Assumptions!$C$6 -> 12.052452
A74: Сумма PV FCFF 2П26–2032E | B74: $ млн | J74: =SUM(D72:J72) -> -5975.7551
A75: TV Гордон = NOPAT×(1+g)×(1−g/RONIC)/(WACC−g) | B75: $ млн | J75: =ReverseDCF!$J$65*(1+Assumptions!$C$24)*(1-Assumptions!$C$24/Assumptions!$C$25)/(WACC!$C$14-Assumptions!$C$24) -> 61925.127
A76: Выходной мультипликатор EV/EBITDAR | B76: x | J76: =Multiples!$C$52 -> 6.2149084 | K76: история UAL: мин / медиана / макс (лист Multiples)
A77: TV по мультипликатору = EV/EBITDAR × EBITDAR 2032E | B77: $ млн | J77: =ReverseDCF!$J$76*ReverseDCF!$J$62 -> 70878.471
A78: Дисконт TV (6,5 года) | B78: x | J78: =1/(1+WACC!$C$14)^6.5 -> 0.58830531
A79: EV (Гордон) | B79: $ млн | J79: =ReverseDCF!$J$74+ReverseDCF!$J$75*ReverseDCF!$J$78 -> 30455.126
A80: EV (мультипликатор) | B80: $ млн | J80: =ReverseDCF!$J$74+ReverseDCF!$J$77*ReverseDCF!$J$78 -> 35722.426
A81: Доля TV в EV (Гордон) | B81: % | J81: =ReverseDCF!$J$75*ReverseDCF!$J$78/ReverseDCF!$J$79 -> 1.1962151
A82: Стоимость акции (Гордон) = (EV − чистый скорр. долг + NOL) / акции | B82: $ | J82: =(ReverseDCF!$J$79-WACC!$C$15+Assumptions!$C$11)/Assumptions!$C$6 -> 43.937924
A83: Стоимость акции (мультипликатор) | B83: $ | J83: =(ReverseDCF!$J$80-WACC!$C$15+Assumptions!$C$11)/Assumptions!$C$6 -> 60.065603
A84: Стоимость акции DCF (взвешенная) | B84: $ | J84: =Assumptions!$C$13*ReverseDCF!$J$82+(1-Assumptions!$C$13)*ReverseDCF!$J$83 -> 52.001763
A85: Проверка: EV/EBITDAR, заложенный в TV Гордона | B85: x | J85: =ReverseDCF!$J$75/ReverseDCF!$J$62 -> 5.4298433
A87: Базовый — reverse DCF | B87: Ед. | C87: 2025A | D87: 2026E | E87: 2027E | F87: 2028E | G87: 2029E | H87: 2030E | I87: 2031E | J87: 2032E | K87: Источник / тип
A88: ASM | B88: млн | C88: =Hist!$I$5 -> 330284 | D88: =ReverseDCF!$C$88*(1+Assumptions!$C$35) -> 338541.1 | E88: =ReverseDCF!$D$88*(1+Assumptions!$D$35) -> 352082.74 | F88: =ReverseDCF!$E$88*(1+Assumptions!$E$35) -> 369686.88 | G88: =ReverseDCF!$F$88*(1+Assumptions!$F$35) -> 388171.23 | H88: =ReverseDCF!$G$88*(1+Assumptions!$G$35) -> 405638.93 | I88: =ReverseDCF!$H$88*(1+Assumptions!$H$35) -> 421864.49 | J88: =ReverseDCF!$I$88*(1+Assumptions!$I$35) -> 436629.74
A89: Галлонов на 1000 ASM | B89: галл. | C89: =Metrics!$I$13 -> 14.118153 | D89: =ReverseDCF!$C$89*(1+Assumptions!$C$15) -> 13.976971 | E89: =ReverseDCF!$D$89*(1+Assumptions!$D$15) -> 13.837202 | F89: =ReverseDCF!$E$89*(1+Assumptions!$E$15) -> 13.69883 | G89: =ReverseDCF!$F$89*(1+Assumptions!$F$15) -> 13.561841 | H89: =ReverseDCF!$G$89*(1+Assumptions!$G$15) -> 13.426223 | I89: =ReverseDCF!$H$89*(1+Assumptions!$H$15) -> 13.291961 | J89: =ReverseDCF!$I$89*(1+Assumptions!$I$15) -> 13.159041
A90: Цена топлива | B90: $/галл. | C90: =Hist!$I$9 -> 2.44 | D90: =Assumptions!$C$39 -> 3.97 | E90: =Assumptions!$D$39 -> 3.3 | F90: =Assumptions!$E$39 -> 3 | G90: =Assumptions!$F$39 -> 2.9 | H90: =Assumptions!$G$39 -> 2.9 | I90: =Assumptions!$H$39 -> 2.95 | J90: =Assumptions!$I$39 -> 3
A91: Топливо на ASM | B91: центы | C91: =ReverseDCF!$C$89*ReverseDCF!$C$90/10 -> 3.4448293 | D91: =ReverseDCF!$D$89*ReverseDCF!$D$90/10 -> 5.5488576 | E91: =ReverseDCF!$E$89*ReverseDCF!$E$90/10 -> 4.5662765 | F91: =ReverseDCF!$F$89*ReverseDCF!$F$90/10 -> 4.1096489 | G91: =ReverseDCF!$G$89*ReverseDCF!$G$90/10 -> 3.932934 | H91: =ReverseDCF!$H$89*ReverseDCF!$H$90/10 -> 3.8936046 | I91: =ReverseDCF!$I$89*ReverseDCF!$I$90/10 -> 3.9211284 | J91: =ReverseDCF!$J$89*ReverseDCF!$J$90/10 -> 3.9477123
A92: TRASM = TRASM(t−1)×(1+базовый рост) + перенос×Δтопливо/ASM | B92: центы | C92: =Metrics!$I$8 -> 17.884608 | D92: =ReverseDCF!$C$92*(1+Assumptions!$C$36)+Assumptions!$C$37*(ReverseDCF!$D$91-ReverseDCF!$C$91) -> 20.014946 | E92: =ReverseDCF!$D$92*(1+Assumptions!$D$36+ReverseDCF!$F$4)+Assumptions!$D$37*(ReverseDCF!$E$91-ReverseDCF!$D$91) -> 19.678309 | F92: =ReverseDCF!$E$92*(1+Assumptions!$E$36+ReverseDCF!$F$4)+Assumptions!$E$37*(ReverseDCF!$F$91-ReverseDCF!$E$91) -> 19.713639 | G92: =ReverseDCF!$F$92*(1+Assumptions!$F$36+ReverseDCF!$F$4)+Assumptions!$F$37*(ReverseDCF!$G$91-ReverseDCF!$F$91) -> 20.029766 | H92: =ReverseDCF!$G$92*(1+Assumptions!$G$36+ReverseDCF!$F$4)+Assumptions!$G$37*(ReverseDCF!$H$91-ReverseDCF!$G$91) -> 20.49118 | I92: =ReverseDCF!$H$92*(1+Assumptions!$H$36+ReverseDCF!$F$4)+Assumptions!$H$37*(ReverseDCF!$I$91-ReverseDCF!$H$91) -> 21.030984 | J92: =ReverseDCF!$I$92*(1+Assumptions!$I$36+ReverseDCF!$F$4)+Assumptions!$I$37*(ReverseDCF!$J$91-ReverseDCF!$I$91) -> 21.583342
A93: Выручка | B93: $ млн | C93: =Hist!$I$19 -> 59070 | D93: =ReverseDCF!$D$88*ReverseDCF!$D$92/100 -> 67758.819 | E93: =ReverseDCF!$E$88*ReverseDCF!$E$92/100 -> 69283.932 | F93: =ReverseDCF!$F$88*ReverseDCF!$F$92/100 -> 72878.739 | G93: =ReverseDCF!$G$88*ReverseDCF!$G$92/100 -> 77749.786 | H93: =ReverseDCF!$H$88*ReverseDCF!$H$92/100 -> 83120.205 | I93: =ReverseDCF!$I$88*ReverseDCF!$I$92/100 -> 88722.251 | J93: =ReverseDCF!$J$88*ReverseDCF!$J$92/100 -> 94239.292
A94: CASM-ex | B94: центы | C94: =Metrics!$I$10 -> 12.64 | D94: =ReverseDCF!$C$94*(1+Assumptions!$C$38) -> 13.3352 | E94: =ReverseDCF!$D$94*(1+Assumptions!$D$38) -> 13.66858 | F94: =ReverseDCF!$E$94*(1+Assumptions!$E$38) -> 13.941952 | G94: =ReverseDCF!$F$94*(1+Assumptions!$F$38) -> 14.262616 | H94: =ReverseDCF!$G$94*(1+Assumptions!$G$38) -> 14.647707 | I94: =ReverseDCF!$H$94*(1+Assumptions!$H$38) -> 15.043195 | J94: =ReverseDCF!$I$94*(1+Assumptions!$I$38) -> 15.449361
A95: Нетопливные расходы (CASM-ex × ASM) | B95: $ млн | D95: =ReverseDCF!$D$88*ReverseDCF!$D$94/100 -> 45145.133 | E95: =ReverseDCF!$E$88*ReverseDCF!$E$94/100 -> 48124.712 | F95: =ReverseDCF!$F$88*ReverseDCF!$F$94/100 -> 51541.566 | G95: =ReverseDCF!$G$88*ReverseDCF!$G$94/100 -> 55363.373 | H95: =ReverseDCF!$H$88*ReverseDCF!$H$94/100 -> 59416.803 | I95: =ReverseDCF!$I$88*ReverseDCF!$I$94/100 -> 63461.898 | J95: =ReverseDCF!$J$88*ReverseDCF!$J$94/100 -> 67456.508
A96: Топливо | B96: $ млн | D96: =ReverseDCF!$D$88*ReverseDCF!$D$91/100 -> 18785.164 | E96: =ReverseDCF!$E$88*ReverseDCF!$E$91/100 -> 16077.072 | F96: =ReverseDCF!$F$88*ReverseDCF!$F$91/100 -> 15192.833 | G96: =ReverseDCF!$G$88*ReverseDCF!$G$91/100 -> 15266.518 | H96: =ReverseDCF!$H$88*ReverseDCF!$H$91/100 -> 15793.976 | I96: =ReverseDCF!$I$88*ReverseDCF!$I$91/100 -> 16541.848 | J96: =ReverseDCF!$J$88*ReverseDCF!$J$91/100 -> 17236.886
A97: Сторонние услуги | B97: $ млн | D97: =ReverseDCF!$D$93*Assumptions!$C$16 -> 304.91469 | E97: =ReverseDCF!$E$93*Assumptions!$D$16 -> 311.77769 | F97: =ReverseDCF!$F$93*Assumptions!$E$16 -> 327.95432 | G97: =ReverseDCF!$G$93*Assumptions!$F$16 -> 349.87404 | H97: =ReverseDCF!$H$93*Assumptions!$G$16 -> 374.04092 | I97: =ReverseDCF!$I$93*Assumptions!$H$16 -> 399.25013 | J97: =ReverseDCF!$J$93*Assumptions!$I$16 -> 424.07681
A98: EBIT до участия в прибыли | B98: $ млн | D98: =ReverseDCF!$D$93-ReverseDCF!$D$95-ReverseDCF!$D$96-ReverseDCF!$D$97 -> 3523.6082 | E98: =ReverseDCF!$E$93-ReverseDCF!$E$95-ReverseDCF!$E$96-ReverseDCF!$E$97 -> 4770.3707 | F98: =ReverseDCF!$F$93-ReverseDCF!$F$95-ReverseDCF!$F$96-ReverseDCF!$F$97 -> 5816.3857 | G98: =ReverseDCF!$G$93-ReverseDCF!$G$95-ReverseDCF!$G$96-ReverseDCF!$G$97 -> 6770.0211 | H98: =ReverseDCF!$H$93-ReverseDCF!$H$95-ReverseDCF!$H$96-ReverseDCF!$H$97 -> 7535.3851 | I98: =ReverseDCF!$I$93-ReverseDCF!$I$95-ReverseDCF!$I$96-ReverseDCF!$I$97 -> 8319.2544 | J98: =ReverseDCF!$J$93-ReverseDCF!$J$95-ReverseDCF!$J$96-ReverseDCF!$J$97 -> 9121.8209
A99: Участие в прибыли | B99: $ млн | D99: =MAX(0,ReverseDCF!$D$98)*Assumptions!$C$17 -> 422.83298 | E99: =MAX(0,ReverseDCF!$E$98)*Assumptions!$D$17 -> 572.44448 | F99: =MAX(0,ReverseDCF!$F$98)*Assumptions!$E$17 -> 697.96629 | G99: =MAX(0,ReverseDCF!$G$98)*Assumptions!$F$17 -> 812.40253 | H99: =MAX(0,ReverseDCF!$H$98)*Assumptions!$G$17 -> 904.24621 | I99: =MAX(0,ReverseDCF!$I$98)*Assumptions!$H$17 -> 998.31053 | J99: =MAX(0,ReverseDCF!$J$98)*Assumptions!$I$17 -> 1094.6185
A100: Скорр. EBIT | B100: $ млн | C100: =Hist!$I$31 -> 4972 | D100: =ReverseDCF!$D$98-ReverseDCF!$D$99 -> 3100.7752 | E100: =ReverseDCF!$E$98-ReverseDCF!$E$99 -> 4197.9262 | F100: =ReverseDCF!$F$98-ReverseDCF!$F$99 -> 5118.4194 | G100: =ReverseDCF!$G$98-ReverseDCF!$G$99 -> 5957.6186 | H100: =ReverseDCF!$H$98-ReverseDCF!$H$99 -> 6631.1389 | I100: =ReverseDCF!$I$98-ReverseDCF!$I$99 -> 7320.9439 | J100: =ReverseDCF!$J$98-ReverseDCF!$J$99 -> 8027.2024
A101: Скорр. операционная маржа | B101: % | C101: =ReverseDCF!$C$100/ReverseDCF!$C$93 -> 0.084171322 | D101: =ReverseDCF!$D$100/ReverseDCF!$D$93 -> 0.045761943 | E101: =ReverseDCF!$E$100/ReverseDCF!$E$93 -> 0.060590184 | F101: =ReverseDCF!$F$100/ReverseDCF!$F$93 -> 0.070231998 | G101: =ReverseDCF!$G$100/ReverseDCF!$G$93 -> 0.07662553 | H101: =ReverseDCF!$H$100/ReverseDCF!$H$93 -> 0.079777701 | I101: =ReverseDCF!$I$100/ReverseDCF!$I$93 -> 0.082515308 | J101: =ReverseDCF!$J$100/ReverseDCF!$J$93 -> 0.085178934
A102: D&A | B102: $ млн | C102: =Hist!$I$26 -> 2939 | D102: =ReverseDCF!$D$93*Assumptions!$C$18 -> 3252.4233 | E102: =ReverseDCF!$E$93*Assumptions!$D$18 -> 3325.6287 | F102: =ReverseDCF!$F$93*Assumptions!$E$18 -> 3498.1795 | G102: =ReverseDCF!$G$93*Assumptions!$F$18 -> 3731.9897 | H102: =ReverseDCF!$H$93*Assumptions!$G$18 -> 3989.7698 | I102: =ReverseDCF!$I$93*Assumptions!$H$18 -> 4258.6681 | J102: =ReverseDCF!$J$93*Assumptions!$I$18 -> 4523.486
A103: EBITDAR = EBIT + D&A + фикс. аренда | B103: $ млн | C103: =Metrics!$I$31 -> 8970 | D103: =ReverseDCF!$D$100+ReverseDCF!$D$102+ReverseDCF!$D$93*Assumptions!$C$19 -> 7403.4602 | E103: =ReverseDCF!$E$100+ReverseDCF!$E$102+ReverseDCF!$E$93*Assumptions!$D$19 -> 8597.4559 | F103: =ReverseDCF!$F$100+ReverseDCF!$F$102+ReverseDCF!$F$93*Assumptions!$E$19 -> 9746.2194 | G103: =ReverseDCF!$G$100+ReverseDCF!$G$102+ReverseDCF!$G$93*Assumptions!$F$19 -> 10894.73 | H103: =ReverseDCF!$H$100+ReverseDCF!$H$102+ReverseDCF!$H$93*Assumptions!$G$19 -> 11909.272 | I103: =ReverseDCF!$I$100+ReverseDCF!$I$102+ReverseDCF!$I$93*Assumptions!$H$19 -> 12954.807 | J103: =ReverseDCF!$J$100+ReverseDCF!$J$102+ReverseDCF!$J$93*Assumptions!$I$19 -> 14011.397
...

Sheet Multiples
A1: Сравнительная оценка: пиры (TTM на 30.06.2026, цены на 13.10.2026)
A3: Показатель | B3: Ед. | C3: UAL | D3: DAL | E3: AAL | F3: LUV | G3: ALK | H3: JBLU | I3: Медиана пиров | J3: Источник / тип
A4: Вводные (XBRL companyfacts SEC, 10-K 2025 + 10-Q 2К26)
A5: Цена акции 13.10.2026 | B5: $ | C5: 103.23 | D5: 79.57 | E5: 12.5 | F5: 40.65 | G5: 37.81 | H5: 3.35 | J5: [Ф] Yahoo Finance chart API, закрытие 13.10.2026
A6: Акций | B6: млн | C6: 326.6 | D6: 657.912 | E6: 661.97 | F6: 489.208 | G6: 111.603 | H6: 377.312 | J6: [Ф] обложки 10-Q (DAL — 10-Q 3К26); UAL — разводнённые 2К26 для согласования с DCF
A7: Выручка TTM | B7: $ млн | C7: 62902 | D7: 68287 | E7: 58337 | F7: 30073 | G7: 14763 | H7: 9503 | J7: [Ф] XBRL Revenues/RevenueFromContract…: FY2025 + 1П26 − 1П25
A8: Операционная прибыль TTM (GAAP) | B8: $ млн | C8: 4874 | D8: 5516 | E8: 1008 | F8: 1041 | G8: -224 | H8: -565 | J8: [Ф] XBRL OperatingIncomeLoss (включая спецстатьи: у ALK/AAL/JBLU — расходы на интеграцию/реструктуризацию; у UAL — доход $615 млн от sale-leaseback)
A9: D&A TTM | B9: $ млн | C9: 2996 | D9: 2525 | E9: 1899 | F9: 1565 | G9: 813 | H9: 711 | J9: [Ф] XBRL
A10: Аренда самолётов TTM | B10: $ млн | C10: 329 | D10: 579 | E10: 1237 | F10: 0 | G10: 249 | H10: 65 | J10: [Ф] XBRL AircraftRental; LUV — отдельно не раскрывается (0, флот в собственности)
A11: Чистая прибыль TTM | B11: $ млн | C11: 3496 | D11: 3950 | E11: -326 | F11: 837 | G11: -175 | H11: -886 | J11: [Ф] XBRL NetIncomeLoss
A12: CFO TTM | B12: $ млн | C12: 8913 | D12: 8134 | E12: 4374 | F12: 2528 | G12: 1020 | H12: -128 | J12: [Ф] XBRL
A13: Капзатраты TTM | B13: $ млн | C13: 6369 | D13: 4724 | E13: 4089 | F13: 2934 | G13: 1154 | H13: 953 | J13: [Ф] XBRL; DAL = ProductiveAssets FY25 + (FlightEquipment+Other) 1П26 − 1П25; ALK = FlightEquipment + OtherPP&E
A14: Долг + фин. аренда (тек. + долгоср.) | B14: $ млн | C14: 26464 | D14: 13952 | E14: 28927 | F14: 5946 | G14: 6235 | H14: 8478 | J14: [Ф] XBRL LongTermDebtAndCapitalLeaseObligations (+Current), 30.06.2026
A15: Опер. аренда (обязательства) | B15: $ млн | C15: 7204 | D15: 6032 | E15: 6802 | F15: 943 | G15: 1381 | H15: 908 | J15: [Ф] XBRL OperatingLeaseLiability (Current+Noncurrent)
A16: Пенсии и пострабочие (долгоср.) | B16: $ млн | C16: 1074 | D16: 3066 | E16: 1160 | F16: 321 | G16: 349 | H16: 0 | J16: [Ф] XBRL; UAL — 8-K 15.07.2026; JBLU — не найдено (0)
... A18: Собственный капитал | B18: $ млн | C18: 16697 | D18: 21815 | E18: -3972 | F18: 7082 | G18: 3670 | H18: 1587 | J18: [Ф] XBRL StockholdersEquity
A19: Прогноз EPS FY2026 (консенсус/гайденс) | B19: $ | C19: 7.92 | D19: 5.35 | E19: 0 | J19: [Ф] UAL — консенсус Yahoo Finance (~13.10.2026, 23 аналитика); DAL — середина гайденса $5,10–5,60 (09.10.2026); AAL — середина (−0,65…0,65) (23.07.2026); LUV/ALK/JBLU — не найдено
A20: Расчёт (формулы)
A21: Капитализация | B21: $ млн | C21: =Multiples!$C$5*Multiples!$C$6 -> 33714.918 | D21: =Multiples!$D$5*Multiples!$D$6 -> 52350.058 | E21: =Multiples!$E$5*Multiples!$E$6 -> 8274.625 | F21: =Multiples!$F$5*Multiples!$F$6 -> 19886.305 | G21: =Multiples!$G$5*Multiples!$G$6 -> 4219.7094 | H21: =Multiples!$H$5*Multiples!$H$6 -> 1263.9952
A22: EV = капитализация + долг + опер. аренда + пенсии − ден. средства | B22: $ млн | C22: =Multiples!$C$21+Multiples!$C$14+Multiples!$C$15+Multiples!$C$16-Multiples!$C$17 -> 51819.918 | D22: =Multiples!$D$21+Multiples!$D$14+Multiples!$D$15+Multiples!$D$16-Multiples!$D$17 -> 70735.058 | E22: =Multiples!$E$21+Multiples!$E$14+Multiples!$E$15+Multiples!$E$16-Multiples!$E$17 -> 37393.625 | F22: =Multiples!$F$21+Multiples!$F$14+Multiples!$F$15+Multiples!$F$16-Multiples!$F$17 -> 23305.305 | G22: =Multiples!$G$21+Multiples!$G$14+Multiples!$G$15+Multiples!$G$16-Multiples!$G$17 -> 9522.7094 | H22: =Multiples!$H$21+Multiples!$H$14+Multiples!$H$15+Multiples!$H$16-Multiples!$H$17 -> 8629.9952
A23: EBITDAR (GAAP) = опер. прибыль + D&A + аренда самолётов | B23: $ млн | C23: =Multiples!$C$8+Multiples!$C$9+Multiples!$C$10 -> 8199 | D23: =Multiples!$D$8+Multiples!$D$9+Multiples!$D$10 -> 8620 | E23: =Multiples!$E$8+Multiples!$E$9+Multiples!$E$10 -> 4144 | F23: =Multiples!$F$8+Multiples!$F$9+Multiples!$F$10 -> 2606 | G23: =Multiples!$G$8+Multiples!$G$9+Multiples!$G$10 -> 838 | H23: =Multiples!$H$8+Multiples!$H$9+Multiples!$H$10 -> 211
A24: EV / EBITDAR | B24: x | C24: =IF(Multiples!$C$23>0,Multiples!$C$22/Multiples!$C$23,"н/п") -> 6.320273 | D24: =IF(Multiples!$D$23>0,Multiples!$D$22/Multiples!$D$23,"н/п") -> 8.2059232 | E24: =IF(Multiples!$E$23>0,Multiples!$E$22/Multiples!$E$23,"н/п") -> 9.0235582 | F24: =IF(Multiples!$F$23>0,Multiples!$F$22/Multiples!$F$23,"н/п") -> 8.9429414 | G24: =IF(Multiples!$G$23>0,Multiples!$G$22/Multiples!$G$23,"н/п") -> 11.363615 | H24: =IF(Multiples!$H$23>0,Multiples!$H$22/Multiples!$H$23,"н/п") -> 40.900451 | I24: =MEDIAN(D24:H24) -> 9.0235582 | J24: формула
A25: EV / выручка | B25: x | C25: =Multiples!$C$22/Multiples!$C$7 -> 0.82381988 | D25: =Multiples!$D$22/Multiples!$D$7 -> 1.0358495 | E25: =Multiples!$E$22/Multiples!$E$7 -> 0.64099328 | F25: =Multiples!$F$22/Multiples!$F$7 -> 0.77495778 | G25: =Multiples!$G$22/Multiples!$G$7 -> 0.64503891 | H25: =Multiples!$H$22/Multiples!$H$7 -> 0.90813377 | I25: =MEDIAN(D25:H25) -> 0.77495778 | J25: формула
A26: P/E TTM (GAAP) | B26: x | C26: =IF(Multiples!$C$11>0,Multiples!$C$21/Multiples!$C$11,"н/п") -> 9.6438553 | D26: =IF(Multiples!$D$11>0,Multiples!$D$21/Multiples!$D$11,"н/п") -> 13.253179 | E26: =IF(Multiples!$E$11>0,Multiples!$E$21/Multiples!$E$11,"н/п") -> н/п | F26: =IF(Multiples!$F$11>0,Multiples!$F$21/Multiples!$F$11,"н/п") -> 23.759027 | G26: =IF(Multiples!$G$11>0,Multiples!$G$21/Multiples!$G$11,"н/п") -> н/п | H26: =IF(Multiples!$H$11>0,Multiples!$H$21/Multiples!$H$11,"н/п") -> н/п | I26: =MEDIAN(D26:H26) -> 18.506103 | J26: формула
A27: P/E FY2026 (консенсус/гайденс) | B27: x | C27: =IF(Multiples!$C$19>0,Multiples!$C$5/Multiples!$C$19,"н/п") -> 13.034091 | D27: =IF(Multiples!$D$19>0,Multiples!$D$5/Multiples!$D$19,"н/п") -> 14.872897 | E27: =IF(Multiples!$E$19>0,Multiples!$E$5/Multiples!$E$19,"н/п") -> н/п | J27: AAL — н/п (прибыль около нуля)
A28: FCF yield = (CFO − капзатраты) / капитализация | B28: % | C28: =(Multiples!$C$12-Multiples!$C$13)/Multiples!$C$21 -> 0.075456212 | D28: =(Multiples!$D$12-Multiples!$D$13)/Multiples!$D$21 -> 0.065138419 | E28: =(Multiples!$E$12-Multiples!$E$13)/Multiples!$E$21 -> 0.034442648 | F28: =(Multiples!$F$12-Multiples!$F$13)/Multiples!$F$21 -> -0.02041606 | G28: =(Multiples!$G$12-Multiples!$G$13)/Multiples!$G$21 -> -0.031755741 | H28: =(Multiples!$H$12-Multiples!$H$13)/Multiples!$H$21 -> -0.85522477 | I28: =MEDIAN(D28:H28) -> -0.02041606 | J28: формула
A29: P/FCF | B29: x | C29: =IF(Multiples!$C$12-Multiples!$C$13>0,Multiples!$C$21/(Multiples!$C$12-Multiples!$C$13),"н/п") -> 13.252719 | D29: =IF(Multiples!$D$12-Multiples!$D$13>0,Multiples!$D$21/(Multiples!$D$12-Multiples!$D$13),"н/п") -> 15.351923 | E29: =IF(Multiples!$E$12-Multiples!$E$13>0,Multiples!$E$21/(Multiples!$E$12-Multiples!$E$13),"н/п") -> 29.033772 | F29: =IF(Multiples!$F$12-Multiples!$F$13>0,Multiples!$F$21/(Multiples!$F$12-Multiples!$F$13),"н/п") -> н/п | G29: =IF(Multiples!$G$12-Multiples!$G$13>0,Multiples!$G$21/(Multiples!$G$12-Multiples!$G$13),"н/п") -> н/п | H29: =IF(Multiples!$H$12-Multiples!$H$13>0,Multiples!$H$21/(Multiples!$H$12-Multiples!$H$13),"н/п") -> н/п | I29: =MEDIAN(D29:H29) -> 22.192848 | J29: формула
A30: P/B | B30: x | C30: =IF(Multiples!$C$18>0,Multiples!$C$21/Multiples!$C$18,"н/п") -> 2.0192201 | D30: =IF(Multiples!$D$18>0,Multiples!$D$21/Multiples!$D$18,"н/п") -> 2.3997276 | E30: =IF(Multiples!$E$18>0,Multiples!$E$21/Multiples!$E$18,"н/п") -> н/п | F30: =IF(Multiples!$F$18>0,Multiples!$F$21/Multiples!$F$18,"н/п") -> 2.8080069 | G30: =IF(Multiples!$G$18>0,Multiples!$G$21/Multiples!$G$18,"н/п") -> 1.1497846 | H30: =IF(Multiples!$H$18>0,Multiples!$H$21/Multiples!$H$18,"н/п") -> 0.7964683 | I30: =MEDIAN(D30:H30) -> 1.7747561 | J30: формула
A31: Операционная маржа TTM (GAAP) | B31: % | C31: =Multiples!$C$8/Multiples!$C$7 -> 0.077485613 | D31: =Multiples!$D$8/Multiples!$D$7 -> 0.080776722 | E31: =Multiples!$E$8/Multiples!$E$7 -> 0.017278914 | F31: =Multiples!$F$8/Multiples!$F$7 -> 0.034615768 | G31: =Multiples!$G$8/Multiples!$G$7 -> -0.015173068 | H31: =Multiples!$H$8/Multiples!$H$7 -> -0.059454909 | I31: =MEDIAN(D31:H31) -> 0.017278914 | J31: формула
A32: Чистый скорр. долг / EBITDAR | B32: x | C32: =IF(Multiples!$C$23>0,(Multiples!$C$22-Multiples!$C$21)/Multiples!$C$23,"н/п") -> 2.2081961 | D32: =IF(Multiples!$D$23>0,(Multiples!$D$22-Multiples!$D$21)/Multiples!$D$23,"н/п") -> 2.1328306 | E32: =IF(Multiples!$E$23>0,(Multiples!$E$22-Multiples!$E$21)/Multiples!$E$23,"н/п") -> 7.0267857 | F32: =IF(Multiples!$F$23>0,(Multiples!$F$22-Multiples!$F$21)/Multiples!$F$23,"н/п") -> 1.3119724 | G32: =IF(Multiples!$G$23>0,(Multiples!$G$22-Multiples!$G$21)/Multiples!$G$23,"н/п") -> 6.3281623 | H32: =IF(Multiples!$H$23>0,(Multiples!$H$22-Multiples!$H$21)/Multiples!$H$23,"н/п") -> 34.909953 | I32: =MEDIAN(D32:H32) -> 6.3281623 | J32: формула
A33: Медиана пиров рассчитана по DAL, AAL, LUV, ALK, JBLU (без UAL); MEDIAN игнорирует «н/п».
A34: Некорректность сравнения: LUV — point-to-point лоукостер (короткие рейсы, без премиум-кабин до 2026); JBLU и ALK — убыточны (интеграция Hawaiian у ALK), их EV/EBITDAR завышен;
A35: AAL — отрицательный капитал (P/B н/п) и прибыль около нуля; DAL — собственный НПЗ (снижает цену топлива ~$0,3–0,4/галл.) и выручка НПЗ в TRASM; у UAL TTM-прибыль включает $615 млн разовых доходов.
A37: История мультипликаторов UAL (на конец года; 2020–21 не показательны — убытки) | B37: Ед. | C37: 2019 | D37: 2022 | E37: 2023 | F37: 2024 | G37: 2025 | H37: Текущий | J37: Источник / тип
A38: Цена акции | B38: $ | C38: =Hist!$C$61 -> 88.09 | D38: =Hist!$F$61 -> 37.7 | E38: =Hist!$G$61 -> 41.26 | F38: =Hist!$H$61 -> 97.1 | G38: =Hist!$I$61 -> 111.82 | H38: =Assumptions!$C$5 -> 103.23
A39: Акций | B39: млн | C39: =Hist!$C$60 -> 251.2 | D39: =Hist!$F$60 -> 326.9 | E39: =Hist!$G$60 -> 328 | F39: =Hist!$H$60 -> 327.9 | G39: =Hist!$I$60 -> 323.5 | H39: =Assumptions!$C$6 -> 326.6
A40: Капитализация | B40: $ млн | C40: =Multiples!$C$38*Multiples!$C$39 -> 22128.208 | D40: =Multiples!$D$38*Multiples!$D$39 -> 12324.13 | E40: =Multiples!$E$38*Multiples!$E$39 -> 13533.28 | F40: =Multiples!$F$38*Multiples!$F$39 -> 31839.09 | G40: =Multiples!$G$38*Multiples!$G$39 -> 36173.77 | H40: =Multiples!$H$38*Multiples!$H$39 -> 33714.918
A41: Чистый скорр. долг | B41: $ млн | C41: =Metrics!$C$45 -> 16952 | D41: =Metrics!$F$45 -> 22304 | E41: =Metrics!$G$45 -> 23956 | F41: =Metrics!$H$45 -> 20391 | G41: =Metrics!$I$45 -> 19854 | H41: =Metrics!$L$45 -> 18105 | J41: 2019 — [О] на основе XBRL (определение пенсий уже)
A42: EV | B42: $ млн | C42: =Multiples!$C$40+Multiples!$C$41 -> 39080.208 | D42: =Multiples!$D$40+Multiples!$D$41 -> 34628.13 | E42: =Multiples!$E$40+Multiples!$E$41 -> 37489.28 | F42: =Multiples!$F$40+Multiples!$F$41 -> 52230.09 | G42: =Multiples!$G$40+Multiples!$G$41 -> 56027.77 | H42: =Multiples!$H$40+Multiples!$H$41 -> 51819.918
A43: EBITDAR (скорр. EBITDA + аренда самолётов) | B43: $ млн | C43: =Metrics!$C$30 -> 7096 | D43: =Metrics!$F$30 -> 5200 | E43: =Metrics!$G$30 -> 8135 | F43: =Metrics!$H$30 -> 8404 | G43: =Metrics!$I$30 -> 8328 | H43: =Metrics!$L$30 -> 7729
A44: EV / EBITDAR | B44: x | C44: =Multiples!$C$42/Multiples!$C$43 -> 5.5073574 | D44: =Multiples!$D$42/Multiples!$D$43 -> 6.6592558 | E44: =Multiples!$E$42/Multiples!$E$43 -> 4.6083934 | F44: =Multiples!$F$42/Multiples!$F$43 -> 6.2149084 | G44: =Multiples!$G$42/Multiples!$G$43 -> 6.7276381 | H44: =Multiples!$H$42/Multiples!$H$43 -> 6.7046084
A45: Скорр. EPS (текущий — TTM) | B45: $ | C45: =Hist!$C$37 -> 12.05 | D45: =Hist!$F$37 -> 2.52 | E45: =Hist!$G$37 -> 10.05 | F45: =Hist!$H$37 -> 10.61 | G45: =Hist!$I$37 -> 10.62 | H45: =Hist!$L$37 -> 9.05
A46: P/E (скорр.) | B46: x | C46: =Multiples!$C$38/Multiples!$C$45 -> 7.3103734 | D46: =Multiples!$D$38/Multiples!$D$45 -> 14.960317 | E46: =Multiples!$E$38/Multiples!$E$45 -> 4.1054726 | F46: =Multiples!$F$38/Multiples!$F$45 -> 9.1517436 | G46: =Multiples!$G$38/Multiples!$G$45 -> 10.52919 | H46: =Multiples!$H$38/Multiples!$H$45 -> 11.40663
A47: P/B | B47: x | C47: =Multiples!$C$40/Hist!$C$58 -> 1.919019 | D47: =Multiples!$D$40/Hist!$F$58 -> 1.7871418 | E47: =Multiples!$E$40/Hist!$G$58 -> 1.4514457 | F47: =Multiples!$F$40/Hist!$H$58 -> 2.5119598 | G47: =Multiples!$G$40/Hist!$I$58 -> 2.3670835 | H47: =Multiples!$H$40/Hist!$L$58 -> 2.0192201
A48: FCF yield (CFO − капзатраты GAAP) | B48: % | C48: =Metrics!$C$34/Multiples!$C$40 -> 0.10760022 | D48: =Metrics!$F$34/Multiples!$D$40 -> 0.10118361 | E48: =Metrics!$G$34/Multiples!$E$40 -> -0.019211898 | F48: =Metrics!$H$34/Multiples!$F$40 -> 0.12029238 | G48: =Metrics!$I$34/Multiples!$G$40 -> 0.070686578 | H48: =Metrics!$L$34/Multiples!$H$40 -> 0.075456212
A49: EV / выручка | B49: x | C49: =Multiples!$C$42/Hist!$C$19 -> 0.90340063 | D49: =Multiples!$D$42/Hist!$F$19 -> 0.77028428 | E49: =Multiples!$E$42/Hist!$G$19 -> 0.69790346 | F49: =Multiples!$F$42/Hist!$H$19 -> 0.91530571 | G49: =Multiples!$G$42/Hist!$I$19 -> 0.94849788 | H49: =Multiples!$H$42/Hist!$L$19 -> 0.82381988
A50: Статистика истории UAL (2019, 2022–2025) | C50: EV/EBITDAR | D50: P/E | E50: P/B | J50: Источник / тип
A51: Минимум | B51: x | C51: =MIN(Multiples!$C$44,Multiples!$D$44,Multiples!$E$44,Multiples!$F$44,Multiples!$G$44) -> 4.6083934 | D51: =MIN(Multiples!$C$46,Multiples!$D$46,Multiples!$E$46,Multiples!$F$46,Multiples!$G$46) -> 4.1054726 | E51: =MIN(Multiples!$C$47,Multiples!$D$47,Multiples!$E$47,Multiples!$F$47,Multiples!$G$47) -> 1.4514457
A52: Медиана | B52: x | C52: =MEDIAN(Multiples!$C$44,Multiples!$D$44,Multiples!$E$44,Multiples!$F$44,Multiples!$G$44) -> 6.2149084 | D52: =MEDIAN(Multiples!$C$46,Multiples!$D$46,Multiples!$E$46,Multiples!$F$46,Multiples!$G$46) -> 9.1517436 | E52: =MEDIAN(Multiples!$C$47,Multiples!$D$47,Multiples!$E$47,Multiples!$F$47,Multiples!$G$47) -> 1.919019
A53: Максимум | B53: x | C53: =MAX(Multiples!$C$44,Multiples!$D$44,Multiples!$E$44,Multiples!$F$44,Multiples!$G$44) -> 6.7276381 | D53: =MAX(Multiples!$C$46,Multiples!$D$46,Multiples!$E$46,Multiples!$F$46,Multiples!$G$46) -> 14.960317 | E53: =MAX(Multiples!$C$47,Multiples!$D$47,Multiples!$E$47,Multiples!$F$47,Multiples!$G$47) -> 2.5119598
A55: Оценка UAL по мультипликаторам | C55: Значение | J55: Источник / тип
A56: EV/EBITDAR медиана пиров × EBITDAR TTM UAL (GAAP) | B56: $/акция | C56: =(Multiples!$I$24*Multiples!$C$23-WACC!$C$15)/Assumptions!$C$6 -> 171.09355 | J56: пиры убыточны/искажены — справочно
A57: EV/EBITDAR медиана истории UAL × EBITDAR 2027E (база) | B57: $/акция | C57: =(Multiples!$C$52*DCF!$E$60-WACC!$C$15+Assumptions!$C$11)/Assumptions!$C$6 -> 114.29088 | J57: EBITDAR 2027E — лист DCF, базовый сценарий
A58: Нормализованная EPS = mid-cycle маржа × выручка 2027E (база) | B58: $ | C58: =(Metrics!$I$54*DCF!$E$50-Assumptions!$D$22)*(1-Assumptions!$C$10)/Assumptions!$C$6 -> 12.973153 | J58: [О]
A59: P/E на нормализованной EPS (текущая цена) | B59: x | C59: =Assumptions!$C$5/Multiples!$C$58 -> 7.9572022
A60: Нормализованная EPS × медианный P/E истории | B60: $/акция | C60: =Multiples!$C$58*Multiples!$D$52 -> 118.72697
A62: Международные пиры (только контекст; мультипликаторы не рассчитаны)
A63: Air France-KLM (AF.PA) €10,48; IAG (IAG.L) 412,45 пенса; Lufthansa (LHA.DE) €7,10 — котировки Yahoo Finance 14.10.2026 (внутри дня).
A64: Причины не сравнивать напрямую: МСФО (IFRS 16 — вся аренда уже в EBITDA, EBITDAR ≈ EBITDA), другая валюта, госучастие (AF-KLM), структура хабов ЕС и регулирование слотов.
A65: Первичные отчёты за 1П26 в рамках работы не собраны — не найдено; на вывод не влияет, т.к. рекомендация опирается на DCF и собственную историю UAL.

Sheet Scenarios
A1: Сценарии и целевая цена (горизонт 12 месяцев)
A3: Показатель | B3: Ед. | C3: Bear | D3: Base | E3: Bull | F3: Взвешенно | G3: Источник / тип
A4: Вероятность | B4: % | C4: =Assumptions!$C$49 -> 0.25 | D4: =Assumptions!$C$50 -> 0.5 | E4: =Assumptions!$C$51 -> 0.25 | F4: =SUM(C4:E4) -> 1
A5: Стоимость акции DCF | B5: $ | C5: =DCF!$J$41 -> 35.422266 | D5: =DCF!$J$82 -> 100.96216 | E5: =DCF!$J$123 -> 199.86437 | F5: =C4*C5+D4*D5+E4*E5 -> 109.30274
A6: Потенциал к цене $103,23 | B6: % | C6: =Scenarios!$C$5/Assumptions!$C$5-1 -> -0.65686074 | D6: =Scenarios!$D$5/Assumptions!$C$5-1 -> -0.02196877 | E6: =Scenarios!$E$5/Assumptions!$C$5-1 -> 0.93610748 | F6: =Scenarios!$F$5/Assumptions!$C$5-1 -> 0.058827298
A7: EPS 2027E | B7: $ | C7: =DCF!$E$30 -> -5.0553839 | D7: =DCF!$E$71 -> 8.7121324 | E7: =DCF!$E$112 -> 14.30072
A8: Опер. маржа 2027E | B8: % | C8: =DCF!$E$17 -> -0.02473951 | D8: =DCF!$E$58 -> 0.060590184 | E8: =DCF!$E$99 -> 0.092920663
A9: Опер. маржа 2032E (терминал) | B9: % | C9: =DCF!$J$17 -> 0.070406454 | D9: =DCF!$J$58 -> 0.085178934 | E9: =DCF!$J$99 -> 0.11712123
A10: Топливо 2027E | B10: $/галл. | C10: =DCF!$E$6 -> 4.1 | D10: =DCF!$E$47 -> 3.3 | E10: =DCF!$E$88 -> 2.9
A11: DCF Гордон | B11: $ | C11: =DCF!$J$39 -> 46.653371 | D11: =DCF!$J$80 -> 100.17001 | E11: =DCF!$J$121 -> 201.39086
A12: DCF выходной мультипликатор | B12: $ | C12: =DCF!$J$40 -> 24.19116 | D12: =DCF!$J$81 -> 101.75432 | E12: =DCF!$J$122 -> 198.33789
A14: Итог | C14: Значение | G14: Источник / тип
A15: Целевая цена (взвешенная DCF, округл. до $1) | B15: $ | C15: =ROUND(Scenarios!$F$5,0) -> 109
A16: Нижняя граница диапазона = мин(DCF база, EV/EBITDAR ист., норм. P/E) | B16: $ | C16: =ROUND(MIN(DCF!$J$82,Multiples!$C$57,Multiples!$C$60),0) -> 101
A17: Верхняя граница = макс(взвешенная DCF, EV/EBITDAR ист., норм. P/E) | B17: $ | C17: =ROUND(MAX(Scenarios!$F$5,Multiples!$C$57,Multiples!$C$60),0) -> 119
A18: Потенциал к целевой цене | B18: % | C18: =Scenarios!$C$15/Assumptions!$C$5-1 -> 0.055894604
A19: Рекомендация (правило: Buy > +15%, Sell < −10%) | C19: =IF(Scenarios!$C$18>Assumptions!$C$53,"BUY",IF(Scenarios!$C$18<Assumptions!$C$54,"SELL","HOLD")) -> HOLD
A20: Справочно: взвешенная DCF через 12 мес. (× (1 + Ke)) | B20: $ | C20: =Scenarios!$F$5*(1+WACC!$C$7) -> 122.46564 | G20: не используется в целевой цене (консервативно); UAL не платит дивиденды

Sheet Sensitivity
A1: Чувствительность (базовый сценарий)
A3: 1) Стоимость акции DCF (метод Гордона), $: WACC × терминальный рост
A4: WACC \ g | B4: 0.015 | C4: 0.02 | D4: 0.025 | E4: 0.03 | F4: 0.035
A5: 0.075 | B5: =(DCF!$D$67/(1+$A5)^DCF!$D$68+DCF!$E$67/(1+$A5)^DCF!$E$68+DCF!$F$67/(1+$A5)^DCF!$F$68+DCF!$G$67/(1+$A5)^DCF!$G$68+DCF!$H$67/(1+$A5)^DCF!$H$68+DCF!$I$67/(1+$A5)^DCF!$I$68+DCF!$J$67/(1+$A5)^DCF!$J$68+DCF!$J$63*(1+B$4)*(1-B$4/Assumptions!$C$25)/($A5-B$4)/(1+$A5)^6.5-WACC!$C$15+Assumptions!$C$11)/Assumptions!$C$6 -> 130.55743 | C5: =(DCF!$D$67/(1+$A5)^DCF!$D$68+DCF!$E$67/(1+$A5)^DCF!$E$68+DCF!$F$67/(1+$A5)^DCF!$F$68+DCF!$G$67/(1+$A5)^DCF!$G$68+DCF!$H$67/(1+$A5)^DCF!$H$68+DCF!$I$67/(1+$A5)^DCF!$I$68+DCF!$J$67/(1+$A5)^DCF!$J$68+DCF!$J$63*(1+C$4)*(1-C$4/Assumptions!$C$25)/($A5-C$4)/(1+$A5)^6.5-WACC!$C$15+Assumptions!$C$11)/Assumptions!$C$6 -> 136.44715 | D5: =(DCF!$D$67/(1+$A5)^DCF!$D$68+DCF!$E$67/(1+$A5)^DCF!$E$68+DCF!$F$67/(1+$A5)^DCF!$F$68+DCF!$G$67/(1+$A5)^DCF!$G$68+DCF!$H$67/(1+$A5)^DCF!$H$68+DCF!$I$67/(1+$A5)^DCF!$I$68+DCF!$J$67/(1+$A5)^DCF!$J$68+DCF!$J$63*(1+D$4)*(1-D$4/Assumptions!$C$25)/($A5-D$4)/(1+$A5)^6.5-WACC!$C$15+Assumptions!$C$11)/Assumptions!$C$6 -> 143.38599 | E5: =(DCF!$D$67/(1+$A5)^DCF!$D$68+DCF!$E$67/(1+$A5)^DCF!$E$68+DCF!$F$67/(1+$A5)^DCF!$F$68+DCF!$G$67/(1+$A5)^DCF!$G$68+DCF!$H$67/(1+$A5)^DCF!$H$68+DCF!$I$67/(1+$A5)^DCF!$I$68+DCF!$J$67/(1+$A5)^DCF!$J$68+DCF!$J$63*(1+E$4)*(1-E$4/Assumptions!$C$25)/($A5-E$4)/(1+$A5)^6.5-WACC!$C$15+Assumptions!$C$11)/Assumptions!$C$6 -> 151.72366 | F5: =(DCF!$D$67/(1+$A5)^DCF!$D$68+DCF!$E$67/(1+$A5)^DCF!$E$68+DCF!$F$67/(1+$A5)^DCF!$F$68+DCF!$G$67/(1+$A5)^DCF!$G$68+DCF!$H$67/(1+$A5)^DCF!$H$68+DCF!$I$67/(1+$A5)^DCF!$I$68+DCF!$J$67/(1+$A5)^DCF!$J$68+DCF!$J$63*(1+F$4)*(1-F$4/Assumptions!$C$25)/($A5-F$4)/(1+$A5)^6.5-WACC!$C$15+Assumptions!$C$11)/Assumptions!$C$6 -> 161.98472
A6: 0.08 | B6: =(DCF!$D$67/(1+$A6)^DCF!$D$68+DCF!$E$67/(1+$A6)^DCF!$E$68+DCF!$F$67/(1+$A6)^DCF!$F$68+DCF!$G$67/(1+$A6)^DCF!$G$68+DCF!$H$67/(1+$A6)^DCF!$H$68+DCF!$I$67/(1+$A6)^DCF!$I$68+DCF!$J$67/(1+$A6)^DCF!$J$68+DCF!$J$63*(1+B$4)*(1-B$4/Assumptions!$C$25)/($A6-B$4)/(1+$A6)^6.5-WACC!$C$15+Assumptions!$C$11)/Assumptions!$C$6 -> 111.01355 | C6: =(DCF!$D$67/(1+$A6)^DCF!$D$68+DCF!$E$67/(1+$A6)^DCF!$E$68+DCF!$F$67/(1+$A6)^DCF!$F$68+DCF!$G$67/(1+$A6)^DCF!$G$68+DCF!$H$67/(1+$A6)^DCF!$H$68+DCF!$I$67/(1+$A6)^DCF!$I$68+DCF!$J$67/(1+$A6)^DCF!$J$68+DCF!$J$63*(1+C$4)*(1-C$4/Assumptions!$C$25)/($A6-C$4)/(1+$A6)^6.5-WACC!$C$15+Assumptions!$C$11)/Assumptions!$C$6 -> 115.09992 | D6: =(DCF!$D$67/(1+$A6)^DCF!$D$68+DCF!$E$67/(1+$A6)^DCF!$E$68+DCF!$F$67/(1+$A6)^DCF!$F$68+DCF!$G$67/(1+$A6)^DCF!$G$68+DCF!$H$67/(1+$A6)^DCF!$H$68+DCF!$I$67/(1+$A6)^DCF!$I$68+DCF!$J$67/(1+$A6)^DCF!$J$68+DCF!$J$63*(1+D$4)*(1-D$4/Assumptions!$C$25)/($A6-D$4)/(1+$A6)^6.5-WACC!$C$15+Assumptions!$C$11)/Assumptions!$C$6 -> 119.81563 | E6: =(DCF!$D$67/(1+$A6)^DCF!$D$68+DCF!$E$67/(1+$A6)^DCF!$E$68+DCF!$F$67/(1+$A6)^DCF!$F$68+DCF!$G$67/(1+$A6)^DCF!$G$68+DCF!$H$67/(1+$A6)^DCF!$H$68+DCF!$I$67/(1+$A6)^DCF!$I$68+DCF!$J$67/(1+$A6)^DCF!$J$68+DCF!$J$63*(1+E$4)*(1-E$4/Assumptions!$C$25)/($A6-E$4)/(1+$A6)^6.5-WACC!$C$15+Assumptions!$C$11)/Assumptions!$C$6 -> 125.34949 | F6: =(DCF!$D$67/(1+$A6)^DCF!$D$68+DCF!$E$67/(1+$A6)^DCF!$E$68+DCF!$F$67/(1+$A6)^DCF!$F$68+DCF!$G$67/(1+$A6)^DCF!$G$68+DCF!$H$67/(1+$A6)^DCF!$H$68+DCF!$I$67/(1+$A6)^DCF!$I$68+DCF!$J$67/(1+$A6)^DCF!$J$68+DCF!$J$63*(1+F$4)*(1-F$4/Assumptions!$C$25)/($A6-F$4)/(1+$A6)^6.5-WACC!$C$15+Assumptions!$C$11)/Assumptions!$C$6 -> 131.97422
A7: 0.085 | B7: =(DCF!$D$67/(1+$A7)^DCF!$D$68+DCF!$E$67/(1+$A7)^DCF!$E$68+DCF!$F$67/(1+$A7)^DCF!$F$68+DCF!$G$67/(1+$A7)^DCF!$G$68+DCF!$H$67/(1+$A7)^DCF!$H$68+DCF!$I$67/(1+$A7)^DCF!$I$68+DCF!$J$67/(1+$A7)^DCF!$J$68+DCF!$J$63*(1+B$4)*(1-B$4/Assumptions!$C$25)/($A7-B$4)/(1+$A7)^6.5-WACC!$C$15+Assumptions!$C$11)/Assumptions!$C$6 -> 94.398946 | C7: =(DCF!$D$67/(1+$A7)^DCF!$D$68+DCF!$E$67/(1+$A7)^DCF!$E$68+DCF!$F$67/(1+$A7)^DCF!$F$68+DCF!$G$67/(1+$A7)^DCF!$G$68+DCF!$H$67/(1+$A7)^DCF!$H$68+DCF!$I$67/(1+$A7)^DCF!$I$68+DCF!$J$67/(1+$A7)^DCF!$J$68+DCF!$J$63*(1+C$4)*(1-C$4/Assumptions!$C$25)/($A7-C$4)/(1+$A7)^6.5-WACC!$C$15+Assumptions!$C$11)/Assumptions!$C$6 -> 97.1748 | D7: =(DCF!$D$67/(1+$A7)^DCF!$D$68+DCF!$E$67/(1+$A7)^DCF!$E$68+DCF!$F$67/(1+$A7)^DCF!$F$68+DCF!$G$67/(1+$A7)^DCF!$G$68+DCF!$H$67/(1+$A7)^DCF!$H$68+DCF!$I$67/(1+$A7)^DCF!$I$68+DCF!$J$67/(1+$A7)^DCF!$J$68+DCF!$J$63*(1+D$4)*(1-D$4/Assumptions!$C$25)/($A7-D$4)/(1+$A7)^6.5-WACC!$C$15+Assumptions!$C$11)/Assumptions!$C$6 -> 100.31222 | E7: =(DCF!$D$67/(1+$A7)^DCF!$D$68+DCF!$E$67/(1+$A7)^DCF!$E$68+DCF!$F$67/(1+$A7)^DCF!$F$68+DCF!$G$67/(1+$A7)^DCF!$G$68+DCF!$H$67/(1+$A7)^DCF!$H$68+DCF!$I$67/(1+$A7)^DCF!$I$68+DCF!$J$67/(1+$A7)^DCF!$J$68+DCF!$J$63*(1+E$4)*(1-E$4/Assumptions!$C$25)/($A7-E$4)/(1+$A7)^6.5-WACC!$C$15+Assumptions!$C$11)/Assumptions!$C$6 -> 103.9098 | F7: =(DCF!$D$67/(1+$A7)^DCF!$D$68+DCF!$E$67/(1+$A7)^DCF!$E$68+DCF!$F$67/(1+$A7)^DCF!$F$68+DCF!$G$67/(1+$A7)^DCF!$G$68+DCF!$H$67/(1+$A7)^DCF!$H$68+DCF!$I$67/(1+$A7)^DCF!$I$68+DCF!$J$67/(1+$A7)^DCF!$J$68+DCF!$J$63*(1+F$4)*(1-F$4/Assumptions!$C$25)/($A7-F$4)/(1+$A7)^6.5-WACC!$C$15+Assumptions!$C$11)/Assumptions!$C$6 -> 108.1056
A8: 0.09 | B8: =(DCF!$D$67/(1+$A8)^DCF!$D$68+DCF!$E$67/(1+$A8)^DCF!$E$68+DCF!$F$67/(1+$A8)^DCF!$F$68+DCF!$G$67/(1+$A8)^DCF!$G$68+DCF!$H$67/(1+$A8)^DCF!$H$68+DCF!$I$67/(1+$A8)^DCF!$I$68+DCF!$J$67/(1+$A8)^DCF!$J$68+DCF!$J$63*(1+B$4)*(1-B$4/Assumptions!$C$25)/($A8-B$4)/(1+$A8)^6.5-WACC!$C$15+Assumptions!$C$11)/Assumptions!$C$6 -> 80.12313 | C8: =(DCF!$D$67/(1+$A8)^DCF!$D$68+DCF!$E$67/(1+$A8)^DCF!$E$68+DCF!$F$67/(1+$A8)^DCF!$F$68+DCF!$G$67/(1+$A8)^DCF!$G$68+DCF!$H$67/(1+$A8)^DCF!$H$68+DCF!$I$67/(1+$A8)^DCF!$I$68+DCF!$J$67/(1+$A8)^DCF!$J$68+DCF!$J$63*(1+C$4)*(1-C$4/Assumptions!$C$25)/($A8-C$4)/(1+$A8)^6.5-WACC!$C$15+Assumptions!$C$11)/Assumptions!$C$6 -> 81.933875 | D8: =(DCF!$D$67/(1+$A8)^DCF!$D$68+DCF!$E$67/(1+$A8)^DCF!$E$68+DCF!$F$67/(1+$A8)^DCF!$F$68+DCF!$G$67/(1+$A8)^DCF!$G$68+DCF!$H$67/(1+$A8)^DCF!$H$68+DCF!$I$67/(1+$A8)^DCF!$I$68+DCF!$J$67/(1+$A8)^DCF!$J$68+DCF!$J$63*(1+D$4)*(1-D$4/Assumptions!$C$25)/($A8-D$4)/(1+$A8)^6.5-WACC!$C$15+Assumptions!$C$11)/Assumptions!$C$6 -> 83.932638 | E8: =(DCF!$D$67/(1+$A8)^DCF!$D$68+DCF!$E$67/(1+$A8)^DCF!$E$68+DCF!$F$67/(1+$A8)^DCF!$F$68+DCF!$G$67/(1+$A8)^DCF!$G$68+DCF!$H$67/(1+$A8)^DCF!$H$68+DCF!$I$67/(1+$A8)^DCF!$I$68+DCF!$J$67/(1+$A8)^DCF!$J$68+DCF!$J$63*(1+E$4)*(1-E$4/Assumptions!$C$25)/($A8-E$4)/(1+$A8)^6.5-WACC!$C$15+Assumptions!$C$11)/Assumptions!$C$6 -> 86.166422 | F8: =(DCF!$D$67/(1+$A8)^DCF!$D$68+DCF!$E$67/(1+$A8)^DCF!$E$68+DCF!$F$67/(1+$A8)^DCF!$F$68+DCF!$G$67/(1+$A8)^DCF!$G$68+DCF!$H$67/(1+$A8)^DCF!$H$68+DCF!$I$67/(1+$A8)^DCF!$I$68+DCF!$J$67/(1+$A8)^DCF!$J$68+DCF!$J$63*(1+F$4)*(1-F$4/Assumptions!$C$25)/($A8-F$4)/(1+$A8)^6.5-WACC!$C$15+Assumptions!$C$11)/Assumptions!$C$6 -> 88.699325
A9: 0.095 | B9: =(DCF!$D$67/(1+$A9)^DCF!$D$68+DCF!$E$67/(1+$A9)^DCF!$E$68+DCF!$F$67/(1+$A9)^DCF!$F$68+DCF!$G$67/(1+$A9)^DCF!$G$68+DCF!$H$67/(1+$A9)^DCF!$H$68+DCF!$I$67/(1+$A9)^DCF!$I$68+DCF!$J$67/(1+$A9)^DCF!$J$68+DCF!$J$63*(1+B$4)*(1-B$4/Assumptions!$C$25)/($A9-B$4)/(1+$A9)^6.5-WACC!$C$15+Assumptions!$C$11)/Assumptions!$C$6 -> 67.743414 | C9: =(DCF!$D$67/(1+$A9)^DCF!$D$68+DCF!$E$67/(1+$A9)^DCF!$E$68+DCF!$F$67/(1+$A9)^DCF!$F$68+DCF!$G$67/(1+$A9)^DCF!$G$68+DCF!$H$67/(1+$A9)^DCF!$H$68+DCF!$I$67/(1+$A9)^DCF!$I$68+DCF!$J$67/(1+$A9)^DCF!$J$68+DCF!$J$63*(1+C$4)*(1-C$4/Assumptions!$C$25)/($A9-C$4)/(1+$A9)^6.5-WACC!$C$15+Assumptions!$C$11)/Assumptions!$C$6 -> 68.836177 | D9: =(DCF!$D$67/(1+$A9)^DCF!$D$68+DCF!$E$67/(1+$A9)^DCF!$E$68+DCF!$F$67/(1+$A9)^DCF!$F$68+DCF!$G$67/(1+$A9)^DCF!$G$68+DCF!$H$67/(1+$A9)^DCF!$H$68+DCF!$I$67/(1+$A9)^DCF!$I$68+DCF!$J$67/(1+$A9)^DCF!$J$68+DCF!$J$63*(1+D$4)*(1-D$4/Assumptions!$C$25)/($A9-D$4)/(1+$A9)^6.5-WACC!$C$15+Assumptions!$C$11)/Assumptions!$C$6 -> 70.003424 | E9: =(DCF!$D$67/(1+$A9)^DCF!$D$68+DCF!$E$67/(1+$A9)^DCF!$E$68+DCF!$F$67/(1+$A9)^DCF!$F$68+DCF!$G$67/(1+$A9)^DCF!$G$68+DCF!$H$67/(1+$A9)^DCF!$H$68+DCF!$I$67/(1+$A9)^DCF!$I$68+DCF!$J$67/(1+$A9)^DCF!$J$68+DCF!$J$63*(1+E$4)*(1-E$4/Assumptions!$C$25)/($A9-E$4)/(1+$A9)^6.5-WACC!$C$15+Assumptions!$C$11)/Assumptions!$C$6 -> 71.262342 | F9: =(DCF!$D$67/(1+$A9)^DCF!$D$68+DCF!$E$67/(1+$A9)^DCF!$E$68+DCF!$F$67/(1+$A9)^DCF!$F$68+DCF!$G$67/(1+$A9)^DCF!$G$68+DCF!$H$67/(1+$A9)^DCF!$H$68+DCF!$I$67/(1+$A9)^DCF!$I$68+DCF!$J$67/(1+$A9)^DCF!$J$68+DCF!$J$63*(1+F$4)*(1-F$4/Assumptions!$C$25)/($A9-F$4)/(1+$A9)^6.5-WACC!$C$15+Assumptions!$C$11)/Assumptions!$C$6 -> 72.635851
A11: Метод Гордона; FCFF не зависят от WACC и g. Центральная ячейка (8,5% / 2,5%) ≈ значению Гордона в DCF при WACC 8,5%.
A13: 2) Reverse DCF по WACC: стоимость акции (Гордон, g = 2,5%) по сетке WACC
A14: WACC | B14: 0.07 | C14: 0.075 | D14: 0.08 | E14: 0.085 | F14: 0.09 | G14: 0.095 | H14: 0.1 | I14: 0.105 | J14: 0.11
A15: Стоимость, $ | B15: =(DCF!$D$67/(1+B$14)^DCF!$D$68+DCF!$E$67/(1+B$14)^DCF!$E$68+DCF!$F$67/(1+B$14)^DCF!$F$68+DCF!$G$67/(1+B$14)^DCF!$G$68+DCF!$H$67/(1+B$14)^DCF!$H$68+DCF!$I$67/(1+B$14)^DCF!$I$68+DCF!$J$67/(1+B$14)^DCF!$J$68+DCF!$J$63*(1+Assumptions!$C$24)*(1-Assumptions!$C$24/Assumptions!$C$25)/(B$14-Assumptions!$C$24)/(1+B$14)^6.5-WACC!$C$15+Assumptions!$C$11)/Assumptions!$C$6 -> 172.38586 | C15: =(DCF!$D$67/(1+C$14)^DCF!$D$68+DCF!$E$67/(1+C$14)^DCF!$E$68+DCF!$F$67/(1+C$14)^DCF!$F$68+DCF!$G$67/(1+C$14)^DCF!$G$68+DCF!$H$67/(1+C$14)^DCF!$H$68+DCF!$I$67/(1+C$14)^DCF!$I$68+DCF!$J$67/(1+C$14)^DCF!$J$68+DCF!$J$63*(1+Assumptions!$C$24)*(1-Assumptions!$C$24/Assumptions!$C$25)/(C$14-Assumptions!$C$24)/(1+C$14)^6.5-WACC!$C$15+Assumptions!$C$11)/Assumptions!$C$6 -> 143.38599 | D15: =(DCF!$D$67/(1+D$14)^DCF!$D$68+DCF!$E$67/(1+D$14)^DCF!$E$68+DCF!$F$67/(1+D$14)^DCF!$F$68+DCF!$G$67/(1+D$14)^DCF!$G$68+DCF!$H$67/(1+D$14)^DCF!$H$68+DCF!$I$67/(1+D$14)^DCF!$I$68+DCF!$J$67/(1+D$14)^DCF!$J$68+DCF!$J$63*(1+Assumptions!$C$24)*(1-Assumptions!$C$24/Assumptions!$C$25)/(D$14-Assumptions!$C$24)/(1+D$14)^6.5-WACC!$C$15+Assumptions!$C$11)/Assumptions!$C$6 -> 119.81563 | E15: =(DCF!$D$67/(1+E$14)^DCF!$D$68+DCF!$E$67/(1+E$14)^DCF!$E$68+DCF!$F$67/(1+E$14)^DCF!$F$68+DCF!$G$67/(1+E$14)^DCF!$G$68+DCF!$H$67/(1+E$14)^DCF!$H$68+DCF!$I$67/(1+E$14)^DCF!$I$68+DCF!$J$67/(1+E$14)^DCF!$J$68+DCF!$J$63*(1+Assumptions!$C$24)*(1-Assumptions!$C$24/Assumptions!$C$25)/(E$14-Assumptions!$C$24)/(1+E$14)^6.5-WACC!$C$15+Assumptions!$C$11)/Assumptions!$C$6 -> 100.31222 | F15: =(DCF!$D$67/(1+F$14)^DCF!$D$68+DCF!$E$67/(1+F$14)^DCF!$E$68+DCF!$F$67/(1+F$14)^DCF!$F$68+DCF!$G$67/(1+F$14)^DCF!$G$68+DCF!$H$67/(1+F$14)^DCF!$H$68+DCF!$I$67/(1+F$14)^DCF!$I$68+DCF!$J$67/(1+F$14)^DCF!$J$68+DCF!$J$63*(1+Assumptions!$C$24)*(1-Assumptions!$C$24/Assumptions!$C$25)/(F$14-Assumptions!$C$24)/(1+F$14)^6.5-WACC!$C$15+Assumptions!$C$11)/Assumptions!$C$6 -> 83.932638 | G15: =(DCF!$D$67/(1+G$14)^DCF!$D$68+DCF!$E$67/(1+G$14)^DCF!$E$68+DCF!$F$67/(1+G$14)^DCF!$F$68+DCF!$G$67/(1+G$14)^DCF!$G$68+DCF!$H$67/(1+G$14)^DCF!$H$68+DCF!$I$67/(1+G$14)^DCF!$I$68+DCF!$J$67/(1+G$14)^DCF!$J$68+DCF!$J$63*(1+Assumptions!$C$24)*(1-Assumptions!$C$24/Assumptions!$C$25)/(G$14-Assumptions!$C$24)/(1+G$14)^6.5-WACC!$C$15+Assumptions!$C$11)/Assumptions!$C$6 -> 70.003424 | H15: =(DCF!$D$67/(1+H$14)^DCF!$D$68+DCF!$E$67/(1+H$14)^DCF!$E$68+DCF!$F$67/(1+H$14)^DCF!$F$68+DCF!$G$67/(1+H$14)^DCF!$G$68+DCF!$H$67/(1+H$14)^DCF!$H$68+DCF!$I$67/(1+H$14)^DCF!$I$68+DCF!$J$67/(1+H$14)^DCF!$J$68+DCF!$J$63*(1+Assumptions!$C$24)*(1-Assumptions!$C$24/Assumptions!$C$25)/(H$14-Assumptions!$C$24)/(1+H$14)^6.5-WACC!$C$15+Assumptions!$C$11)/Assumptions!$C$6 -> 58.03085 | I15: =(DCF!$D$67/(1+I$14)^DCF!$D$68+DCF!$E$67/(1+I$14)^DCF!$E$68+DCF!$F$67/(1+I$14)^DCF!$F$68+DCF!$G$67/(1+I$14)^DCF!$G$68+DCF!$H$67/(1+I$14)^DCF!$H$68+DCF!$I$67/(1+I$14)^DCF!$I$68+DCF!$J$67/(1+I$14)^DCF!$J$68+DCF!$J$63*(1+Assumptions!$C$24)*(1-Assumptions!$C$24/Assumptions!$C$25)/(I$14-Assumptions!$C$24)/(1+I$14)^6.5-WACC!$C$15+Assumptions!$C$11)/Assumptions!$C$6 -> 47.644766 | J15: =(DCF!$D$67/(1+J$14)^DCF!$D$68+DCF!$E$67/(1+J$14)^DCF!$E$68+DCF!$F$67/(1+J$14)^DCF!$F$68+DCF!$G$67/(1+J$14)^DCF!$G$68+DCF!$H$67/(1+J$14)^DCF!$H$68+DCF!$I$67/(1+J$14)^DCF!$I$68+DCF!$J$67/(1+J$14)^DCF!$J$68+DCF!$J$63*(1+Assumptions!$C$24)*(1-Assumptions!$C$24/Assumptions!$C$25)/(J$14-Assumptions!$C$24)/(1+J$14)^6.5-WACC!$C$15+Assumptions!$C$11)/Assumptions!$C$6 -> 38.562239
A16: WACC, заложенный в цену | B16: =IF(AND(Assumptions!$C$5<=B15,Assumptions!$C$5>=C15),B14+(B15-Assumptions!$C$5)/(B15-C15)*(C14-B14),IF(AND(Assumptions!$C$5<=C15,Assumptions!$C$5>=D15),C14+(C15-Assumptions!$C$5)/(C15-D15)*(D14-C14),IF(AND(Assumptions!$C$5<=D15,Assumptions!$C$5>=E15),D14+(D15-Assumptions!$C$5)/(D15-E15)*(E14-D14),IF(AND(Assumptions!$C$5<=E15,Assumptions!$C$5>=F15),E14+(E15-Assumptions!$C$5)/(E15-F15)*(F14-E14),IF(AND(Assumptions!$C$5<=F15,Assumptions!$C$5>=G15),F14+(F15-Assumptions!$C$5)/(F15-G15)*(G14-F14),IF(AND(Assumptions!$C$5<=G15,Assumptions!$C$5>=H15),G14+(G15-Assumptions!$C$5)/(G15-H15)*(H14-G14),IF(AND(Assumptions!$C$5<=H15,Assumptions!$C$5>=I15),H14+(H15-Assumptions!$C$5)/(H15-I15)*(I14-H14),IF(AND(Assumptions!$C$5<=I15,Assumptions!$C$5>=J15),I14+(I15-Assumptions!$C$5)/(I15-J15)*(J14-I14),"вне сетки")))))))) -> 0.084251981
A18: 3) EPS 2027E (база), $: цена топлива 2027E × отклонение TRASM 2027E от базы
A19: Топливо $/галл. \ ΔTRASM | B19: -0.04 | C19: -0.02 | D19: 0 | E19: 0.02 | F19: 0.04
A20: 2.7 | B20: =((DCF!$E$55+DCF!$E$45*DCF!$E$49/100*B$19*(1-Assumptions!$D$16)-DCF!$E$45*DCF!$E$46/1000*($A20-DCF!$E$47))-MAX(0,(DCF!$E$55+DCF!$E$45*DCF!$E$49/100*B$19*(1-Assumptions!$D$16)-DCF!$E$45*DCF!$E$46/1000*($A20-DCF!$E$47)))*Assumptions!$D$17-Assumptions!$D$22)*(1-Assumptions!$C$10)/Assumptions!$C$6 -> 9.0572613 | C20: =((DCF!$E$55+DCF!$E$45*DCF!$E$49/100*C$19*(1-Assumptions!$D$16)-DCF!$E$45*DCF!$E$46/1000*($A20-DCF!$E$47))-MAX(0,(DCF!$E$55+DCF!$E$45*DCF!$E$49/100*C$19*(1-Assumptions!$D$16)-DCF!$E$45*DCF!$E$46/1000*($A20-DCF!$E$47)))*Assumptions!$D$17-Assumptions!$D$22)*(1-Assumptions!$C$10)/Assumptions!$C$6 -> 11.956372 | D20: =((DCF!$E$55+DCF!$E$45*DCF!$E$49/100*D$19*(1-Assumptions!$D$16)-DCF!$E$45*DCF!$E$46/1000*($A20-DCF!$E$47))-MAX(0,(DCF!$E$55+DCF!$E$45*DCF!$E$49/100*D$19*(1-Assumptions!$D$16)-DCF!$E$45*DCF!$E$46/1000*($A20-DCF!$E$47)))*Assumptions!$D$17-Assumptions!$D$22)*(1-Assumptions!$C$10)/Assumptions!$C$6 -> 14.855484 | E20: =((DCF!$E$55+DCF!$E$45*DCF!$E$49/100*E$19*(1-Assumptions!$D$16)-DCF!$E$45*DCF!$E$46/1000*($A20-DCF!$E$47))-MAX(0,(DCF!$E$55+DCF!$E$45*DCF!$E$49/100*E$19*(1-Assumptions!$D$16)-DCF!$E$45*DCF!$E$46/1000*($A20-DCF!$E$47)))*Assumptions!$D$17-Assumptions!$D$22)*(1-Assumptions!$C$10)/Assumptions!$C$6 -> 17.754595 | F20: =((DCF!$E$55+DCF!$E$45*DCF!$E$49/100*F$19*(1-Assumptions!$D$16)-DCF!$E$45*DCF!$E$46/1000*($A20-DCF!$E$47))-MAX(0,(DCF!$E$55+DCF!$E$45*DCF!$E$49/100*F$19*(1-Assumptions!$D$16)-DCF!$E$45*DCF!$E$46/1000*($A20-DCF!$E$47)))*Assumptions!$D$17-Assumptions!$D$22)*(1-Assumptions!$C$10)/Assumptions!$C$6 -> 20.653706
A21: 3 | B21: =((DCF!$E$55+DCF!$E$45*DCF!$E$49/100*B$19*(1-Assumptions!$D$16)-DCF!$E$45*DCF!$E$46/1000*($A21-DCF!$E$47))-MAX(0,(DCF!$E$55+DCF!$E$45*DCF!$E$49/100*B$19*(1-Assumptions!$D$16)-DCF!$E$45*DCF!$E$46/1000*($A21-DCF!$E$47)))*Assumptions!$D$17-Assumptions!$D$22)*(1-Assumptions!$C$10)/Assumptions!$C$6 -> 5.9855856 | C21: =((DCF!$E$55+DCF!$E$45*DCF!$E$49/100*C$19*(1-Assumptions!$D$16)-DCF!$E$45*DCF!$E$46/1000*($A21-DCF!$E$47))-MAX(0,(DCF!$E$55+DCF!$E$45*DCF!$E$49/100*C$19*(1-Assumptions!$D$16)-DCF!$E$45*DCF!$E$46/1000*($A21-DCF!$E$47)))*Assumptions!$D$17-Assumptions!$D$22)*(1-Assumptions!$C$10)/Assumptions!$C$6 -> 8.8846968 | D21: =((DCF!$E$55+DCF!$E$45*DCF!$E$49/100*D$19*(1-Assumptions!$D$16)-DCF!$E$45*DCF!$E$46/1000*($A21-DCF!$E$47))-MAX(0,(DCF!$E$55+DCF!$E$45*DCF!$E$49/100*D$19*(1-Assumptions!$D$16)-DCF!$E$45*DCF!$E$46/1000*($A21-DCF!$E$47)))*Assumptions!$D$17-Assumptions!$D$22)*(1-Assumptions!$C$10)/Assumptions!$C$6 -> 11.783808 | E21: =((DCF!$E$55+DCF!$E$45*DCF!$E$49/100*E$19*(1-Assumptions!$D$16)-DCF!$E$45*DCF!$E$46/1000*($A21-DCF!$E$47))-MAX(0,(DCF!$E$55+DCF!$E$45*DCF!$E$49/100*E$19*(1-Assumptions!$D$16)-DCF!$E$45*DCF!$E$46/1000*($A21-DCF!$E$47)))*Assumptions!$D$17-Assumptions!$D$22)*(1-Assumptions!$C$10)/Assumptions!$C$6 -> 14.682919 | F21: =((DCF!$E$55+DCF!$E$45*DCF!$E$49/100*F$19*(1-Assumptions!$D$16)-DCF!$E$45*DCF!$E$46/1000*($A21-DCF!$E$47))-MAX(0,(DCF!$E$55+DCF!$E$45*DCF!$E$49/100*F$19*(1-Assumptions!$D$16)-DCF!$E$45*DCF!$E$46/1000*($A21-DCF!$E$47)))*Assumptions!$D$17-Assumptions!$D$22)*(1-Assumptions!$C$10)/Assumptions!$C$6 -> 17.582031
A22: 3.3 | B22: =((DCF!$E$55+DCF!$E$45*DCF!$E$49/100*B$19*(1-Assumptions!$D$16)-DCF!$E$45*DCF!$E$46/1000*($A22-DCF!$E$47))-MAX(0,(DCF!$E$55+DCF!$E$45*DCF!$E$49/100*B$19*(1-Assumptions!$D$16)-DCF!$E$45*DCF!$E$46/1000*($A22-DCF!$E$47)))*Assumptions!$D$17-Assumptions!$D$22)*(1-Assumptions!$C$10)/Assumptions!$C$6 -> 2.9139099 | C22: =((DCF!$E$55+DCF!$E$45*DCF!$E$49/100*C$19*(1-Assumptions!$D$16)-DCF!$E$45*DCF!$E$46/1000*($A22-DCF!$E$47))-MAX(0,(DCF!$E$55+DCF!$E$45*DCF!$E$49/100*C$19*(1-Assumptions!$D$16)-DCF!$E$45*DCF!$E$46/1000*($A22-DCF!$E$47)))*Assumptions!$D$17-Assumptions!$D$22)*(1-Assumptions!$C$10)/Assumptions!$C$6 -> 5.8130211 | D22: =((DCF!$E$55+DCF!$E$45*DCF!$E$49/100*D$19*(1-Assumptions!$D$16)-DCF!$E$45*DCF!$E$46/1000*($A22-DCF!$E$47))-MAX(0,(DCF!$E$55+DCF!$E$45*DCF!$E$49/100*D$19*(1-Assumptions!$D$16)-DCF!$E$45*DCF!$E$46/1000*($A22-DCF!$E$47)))*Assumptions!$D$17-Assumptions!$D$22)*(1-Assumptions!$C$10)/Assumptions!$C$6 -> 8.7121324 | E22: =((DCF!$E$55+DCF!$E$45*DCF!$E$49/100*E$19*(1-Assumptions!$D$16)-DCF!$E$45*DCF!$E$46/1000*($A22-DCF!$E$47))-MAX(0,(DCF!$E$55+DCF!$E$45*DCF!$E$49/100*E$19*(1-Assumptions!$D$16)-DCF!$E$45*DCF!$E$46/1000*($A22-DCF!$E$47)))*Assumptions!$D$17-Assumptions!$D$22)*(1-Assumptions!$C$10)/Assumptions!$C$6 -> 11.611244 | F22: =((DCF!$E$55+DCF!$E$45*DCF!$E$49/100*F$19*(1-Assumptions!$D$16)-DCF!$E$45*DCF!$E$46/1000*($A22-DCF!$E$47))-MAX(0,(DCF!$E$55+DCF!$E$45*DCF!$E$49/100*F$19*(1-Assumptions!$D$16)-DCF!$E$45*DCF!$E$46/1000*($A22-DCF!$E$47)))*Assumptions!$D$17-Assumptions!$D$22)*(1-Assumptions!$C$10)/Assumptions!$C$6 -> 14.510355
A23: 3.6 | B23: =((DCF!$E$55+DCF!$E$45*DCF!$E$49/100*B$19*(1-Assumptions!$D$16)-DCF!$E$45*DCF!$E$46/1000*($A23-DCF!$E$47))-MAX(0,(DCF!$E$55+DCF!$E$45*DCF!$E$49/100*B$19*(1-Assumptions!$D$16)-DCF!$E$45*DCF!$E$46/1000*($A23-DCF!$E$47)))*Assumptions!$D$17-Assumptions!$D$22)*(1-Assumptions!$C$10)/Assumptions!$C$6 -> -0.15776577 | C23: =((DCF!$E$55+DCF!$E$45*DCF!$E$49/100*C$19*(1-Assumptions!$D$16)-DCF!$E$45*DCF!$E$46/1000*($A23-DCF!$E$47))-MAX(0,(DCF!$E$55+DCF!$E$45*DCF!$E$49/100*C$19*(1-Assumptions!$D$16)-DCF!$E$45*DCF!$E$46/1000*($A23-DCF!$E$47)))*Assumptions!$D$17-Assumptions!$D$22)*(1-Assumptions!$C$10)/Assumptions!$C$6 -> 2.7413455 | D23: =((DCF!$E$55+DCF!$E$45*DCF!$E$49/100*D$19*(1-Assumptions!$D$16)-DCF!$E$45*DCF!$E$46/1000*($A23-DCF!$E$47))-MAX(0,(DCF!$E$55+DCF!$E$45*DCF!$E$49/100*D$19*(1-Assumptions!$D$16)-DCF!$E$45*DCF!$E$46/1000*($A23-DCF!$E$47)))*Assumptions!$D$17-Assumptions!$D$22)*(1-Assumptions!$C$10)/Assumptions!$C$6 -> 5.6404567 | E23: =((DCF!$E$55+DCF!$E$45*DCF!$E$49/100*E$19*(1-Assumptions!$D$16)-DCF!$E$45*DCF!$E$46/1000*($A23-DCF!$E$47))-MAX(0,(DCF!$E$55+DCF!$E$45*DCF!$E$49/100*E$19*(1-Assumptions!$D$16)-DCF!$E$45*DCF!$E$46/1000*($A23-DCF!$E$47)))*Assumptions!$D$17-Assumptions!$D$22)*(1-Assumptions!$C$10)/Assumptions!$C$6 -> 8.5395679 | F23: =((DCF!$E$55+DCF!$E$45*DCF!$E$49/100*F$19*(1-Assumptions!$D$16)-DCF!$E$45*DCF!$E$46/1000*($A23-DCF!$E$47))-MAX(0,(DCF!$E$55+DCF!$E$45*DCF!$E$49/100*F$19*(1-Assumptions!$D$16)-DCF!$E$45*DCF!$E$46/1000*($A23-DCF!$E$47)))*Assumptions!$D$17-Assumptions!$D$22)*(1-Assumptions!$C$10)/Assumptions!$C$6 -> 11.438679
A24: 3.9 | B24: =((DCF!$E$55+DCF!$E$45*DCF!$E$49/100*B$19*(1-Assumptions!$D$16)-DCF!$E$45*DCF!$E$46/1000*($A24-DCF!$E$47))-MAX(0,(DCF!$E$55+DCF!$E$45*DCF!$E$49/100*B$19*(1-Assumptions!$D$16)-DCF!$E$45*DCF!$E$46/1000*($A24-DCF!$E$47)))*Assumptions!$D$17-Assumptions!$D$22)*(1-Assumptions!$C$10)/Assumptions!$C$6 -> -3.4907016 | C24: =((DCF!$E$55+DCF!$E$45*DCF!$E$49/100*C$19*(1-Assumptions!$D$16)-DCF!$E$45*DCF!$E$46/1000*($A24-DCF!$E$47))-MAX(0,(DCF!$E$55+DCF!$E$45*DCF!$E$49/100*C$19*(1-Assumptions!$D$16)-DCF!$E$45*DCF!$E$46/1000*($A24-DCF!$E$47)))*Assumptions!$D$17-Assumptions!$D$22)*(1-Assumptions!$C$10)/Assumptions!$C$6 -> -0.33033021 | D24: =((DCF!$E$55+DCF!$E$45*DCF!$E$49/100*D$19*(1-Assumptions!$D$16)-DCF!$E$45*DCF!$E$46/1000*($A24-DCF!$E$47))-MAX(0,(DCF!$E$55+DCF!$E$45*DCF!$E$49/100*D$19*(1-Assumptions!$D$16)-DCF!$E$45*DCF!$E$46/1000*($A24-DCF!$E$47)))*Assumptions!$D$17-Assumptions!$D$22)*(1-Assumptions!$C$10)/Assumptions!$C$6 -> 2.568781 | E24: =((DCF!$E$55+DCF!$E$45*DCF!$E$49/100*E$19*(1-Assumptions!$D$16)-DCF!$E$45*DCF!$E$46/1000*($A24-DCF!$E$47))-MAX(0,(DCF!$E$55+DCF!$E$45*DCF!$E$49/100*E$19*(1-Assumptions!$D$16)-DCF!$E$45*DCF!$E$46/1000*($A24-DCF!$E$47)))*Assumptions!$D$17-Assumptions!$D$22)*(1-Assumptions!$C$10)/Assumptions!$C$6 -> 5.4678923 | F24: =((DCF!$E$55+DCF!$E$45*DCF!$E$49/100*F$19*(1-Assumptions!$D$16)-DCF!$E$45*DCF!$E$46/1000*($A24-DCF!$E$47))-MAX(0,(DCF!$E$55+DCF!$E$45*DCF!$E$49/100*F$19*(1-Assumptions!$D$16)-DCF!$E$45*DCF!$E$46/1000*($A24-DCF!$E$47)))*Assumptions!$D$17-Assumptions!$D$22)*(1-Assumptions!$C$10)/Assumptions!$C$6 -> 8.3670035
A25: 4.2 | B25: =((DCF!$E$55+DCF!$E$45*DCF!$E$49/100*B$19*(1-Assumptions!$D$16)-DCF!$E$45*DCF!$E$46/1000*($A25-DCF!$E$47))-MAX(0,(DCF!$E$55+DCF!$E$45*DCF!$E$49/100*B$19*(1-Assumptions!$D$16)-DCF!$E$45*DCF!$E$46/1000*($A25-DCF!$E$47)))*Assumptions!$D$17-Assumptions!$D$22)*(1-Assumptions!$C$10)/Assumptions!$C$6 -> -6.9812422 | C25: =((DCF!$E$55+DCF!$E$45*DCF!$E$49/100*C$19*(1-Assumptions!$D$16)-DCF!$E$45*DCF!$E$46/1000*($A25-DCF!$E$47))-MAX(0,(DCF!$E$55+DCF!$E$45*DCF!$E$49/100*C$19*(1-Assumptions!$D$16)-DCF!$E$45*DCF!$E$46/1000*($A25-DCF!$E$47)))*Assumptions!$D$17-Assumptions!$D$22)*(1-Assumptions!$C$10)/Assumptions!$C$6 -> -3.6867976 | D25: =((DCF!$E$55+DCF!$E$45*DCF!$E$49/100*D$19*(1-Assumptions!$D$16)-DCF!$E$45*DCF!$E$46/1000*($A25-DCF!$E$47))-MAX(0,(DCF!$E$55+DCF!$E$45*DCF!$E$49/100*D$19*(1-Assumptions!$D$16)-DCF!$E$45*DCF!$E$46/1000*($A25-DCF!$E$47)))*Assumptions!$D$17-Assumptions!$D$22)*(1-Assumptions!$C$10)/Assumptions!$C$6 -> -0.50289465 | E25: =((DCF!$E$55+DCF!$E$45*DCF!$E$49/100*E$19*(1-Assumptions!$D$16)-DCF!$E$45*DCF!$E$46/1000*($A25-DCF!$E$47))-MAX(0,(DCF!$E$55+DCF!$E$45*DCF!$E$49/100*E$19*(1-Assumptions!$D$16)-DCF!$E$45*DCF!$E$46/1000*($A25-DCF!$E$47)))*Assumptions!$D$17-Assumptions!$D$22)*(1-Assumptions!$C$10)/Assumptions!$C$6 -> 2.3962166 | F25: =((DCF!$E$55+DCF!$E$45*DCF!$E$49/100*F$19*(1-Assumptions!$D$16)-DCF!$E$45*DCF!$E$46/1000*($A25-DCF!$E$47))-MAX(0,(DCF!$E$55+DCF!$E$45*DCF!$E$49/100*F$19*(1-Assumptions!$D$16)-DCF!$E$45*DCF!$E$46/1000*($A25-DCF!$E$47)))*Assumptions!$D$17-Assumptions!$D$22)*(1-Assumptions!$C$10)/Assumptions!$C$6 -> 5.2953278
A26: Перенос топлива в тариф в этой таблице не моделируется (статический эффект); в DCF перенос учитывается.
A28: 4) Чувствительность операционной прибыли, $ млн (до участия в прибыли и без переноса в тариф)
B29: TTM 2К26 | C29: 2027E (база)
A30: Топливо +10% | B30: =-Hist!$L$24*0.1 -> -1407 | C30: =-DCF!$E$53*0.1 -> -1607.7072
A31: Топливо −10% | B31: =Hist!$L$24*0.1 -> 1407 | C31: =DCF!$E$53*0.1 -> 1607.7072
A32: RASM +1% | B32: =Hist!$L$19*0.01 -> 629.02 | C32: =DCF!$E$50*0.01 -> 692.83932
A33: RASM −1% | B33: =-Hist!$L$19*0.01 -> -629.02 | C33: =-DCF!$E$50*0.01 -> -692.83932
A34: Справочно: скорр. опер. прибыль | B34: =Hist!$L$31 -> 4259 | C34: =DCF!$E$57 -> 4197.9262
A35: Топливо ±10% в % от опер. прибыли | B35: =B30/B34 -> -0.33035924 | C35: =C30/C34 -> -0.38297652
A36: RASM ±1% в % от опер. прибыли | B36: =B32/B34 -> 0.14769195 | C36: =C32/C34 -> 0.16504323

Sheet Debt
A1: Долг, ликвидность, поставки самолётов
A3: График денежных обязательств на 31.12.2025, $ млрд | C3: 2026 | D3: 2027 | E3: 2028 | F3: 2029 | G3: 2030 | H3: После 2030 | I3: Итого | J3: Источник / тип
A4: Долг и проценты | B4: $ млрд | C4: 5 | D4: 2.8 | E4: 2.6 | F4: 3.6 | G4: 3 | H4: 9 | I4: =SUM(C4:H4) -> 26 | J4: [Ф] 10-K 2025, Liquidity — material cash requirements
A5: Финансовая аренда | B5: $ млрд | C5: 0.1 | D5: 0.2 | E5: 0.1 | F5: 0 | G5: 0 | H5: 0 | I5: =SUM(C5:H5) -> 0.4 | J5: [Ф] 10-K 2025, Liquidity — material cash requirements
A6: Операционная аренда | B6: $ млрд | C6: 0.9 | D6: 1.1 | E6: 0.9 | F6: 0.7 | G6: 0.8 | H6: 3.6 | I6: =SUM(C6:H6) -> 8 | J6: [Ф] 10-K 2025, Liquidity — material cash requirements
A7: Прочие фин. обязательства | B7: $ млрд | C7: 0.4 | D7: 0.6 | E7: 0.2 | F7: 0.2 | G7: 0.2 | H7: 2.7 | I7: =SUM(C7:H7) -> 4.3 | J7: [Ф] 10-K 2025, Liquidity — material cash requirements
A8: Капитальные закупки (самолёты и пр.) | B8: $ млрд | C8: 12.6 | D8: 5.6 | E8: 7.4 | F8: 9 | G8: 8.7 | H8: 13.8 | I8: =SUM(C8:H8) -> 57.1 | J8: [Ф] 10-K 2025, Liquidity — material cash requirements
A9: Итого долг + аренда | B9: $ млрд | C9: =SUM(C4:C7) -> 6.4 | D9: =SUM(D4:D7) -> 4.7 | E9: =SUM(E4:E7) -> 3.8 | F9: =SUM(F4:F7) -> 4.5 | G9: =SUM(G4:G7) -> 4 | H9: =SUM(H4:H7) -> 15.3 | I9: =SUM(I4:I7) -> 38.7
A10: После 31.12.2025: выпущены ноты $1 млрд 2029 (4,875%) и $1 млрд 2031 (5,375%); во 2К26 привлечено $3,7 млрд банковских кредитов, досрочно погашено ~$1 млрд дорогого долга (8-K 15.07.2026).
A12: Ликвидность и рейтинги на 30.06.2026 | C12: Значение | J12: Источник / тип
A13: Доступная ликвидность (вкл. невыбранные кредитные линии) | B13: $ млн | C13: 19600 | J13: [Ф] 8-K 15.07.2026
A14: Ликвидность / выручка TTM | B14: % | C14: =Debt!$C$13/Hist!$L$19 -> 0.31159582
A15: Револьверная линия (не выбрана на 31.12.2025) | B15: $ млн | C15: 3000 | J15: [Ф] 10-K 2025
A16: Ковенант: минимальная ликвидность | B16: $ млн | C16: 2000 | J16: [Ф] 10-K 2025
A17: Рейтинги S&P / Moody's / Fitch | C17: BB+ / Ba1 / BB+ | J17: [Ф] 10-Q 2К26: S&P BB+ (позитивный), Moody's Ba1 (стабильный), Fitch BB+ (стабильный); цель UAL — инвестиционный рейтинг в 2026
A18: Остаток программы выкупа акций | B18: $ млн | C18: 755 | J18: [Ф] 10-Q 2К26 (на 09.07.2026); во 2К26 выкупа не было
A20: Долговая нагрузка: через EBITDAR и через денежный поток | B20: x | C20: 2022 | D20: 2023 | E20: 2024 | F20: 2025 | G20: TTM 2К26 | J20: Источник / тип
A21: Чистый скорр. долг / EBITDAR | B21: x | C21: =Metrics!$F$46 -> 4.2892308 | D21: =Metrics!$G$46 -> 2.9448064 | E21: =Metrics!$H$46 -> 2.4263446 | F21: =Metrics!$I$46 -> 2.3840058 | G21: =Metrics!$L$46 -> 2.3424764
A22: Чистый скорр. долг / CFO | B22: x | C22: =Metrics!$F$48 -> 3.6768876 | D22: =Metrics!$G$48 -> 3.466358 | E22: =Metrics!$H$48 -> 2.1589201 | F22: =Metrics!$I$48 -> 2.3548808 | G22: =Metrics!$L$48 -> 2.0313026
A23: Чистый скорр. долг / CFO без прироста ATL и миль | B23: x | C23: =Metrics!$F$49 -> 4.9874776 | D23: =Metrics!$G$49 -> 3.2843433 | E23: =Metrics!$H$49 -> 2.4597105 | F23: =Metrics!$I$49 -> 2.6384053
A24: Покрытие фикс. платежей (EBITDAR / (% + аренда)) | B24: x | C24: =Metrics!$F$51 -> 2.5615764 | D24: =Metrics!$G$51 -> 3.7784487 | E24: =Metrics!$H$51 -> 4.6125137 | F24: =Metrics!$I$51 -> 5.1249231 | G24: =Metrics!$L$51 -> 4.6700906
A25: Вывод: CFO у авиакомпании завышен притоком авансов (ATL) и нулевыми денежными налогами (NOL), поэтому долг/CFO выглядит мягче; надёжнее EBITDAR с поправкой на аренду, оценённый через цикл.
A27: Поставки самолётов: контрактные vs ожидаемые (10-Q 2К26) | B27: шт. | C27: Контракт 2П26 | D27: Контракт 2027 | E27: Контракт после | F27: Ожид. 2П26 | G27: Ожид. 2027 | H27: Ожид. после | J27: Источник / тип
A28: Boeing 787 | B28: шт. | C28: 42 | D28: 11 | E28: 93 | F28: 12 | G28: 27 | H28: 107 | J28: [Ф] 10-Q 2К26, Firm Order and Option Aircraft
A29: Boeing 737 MAX 9 | B29: шт. | C29: 63 | D29: 0 | E29: 0 | F29: 40 | G29: 23 | H29: 0 | J29: [Ф] 10-Q 2К26, Firm Order and Option Aircraft
A30: Boeing 737 MAX 10 | B30: шт. | C30: 3 | D30: 44 | E30: 120 | F30: 0 | G30: 20 | H30: 147 | J30: [Ф] 10-Q 2К26, Firm Order and Option Aircraft
A31: Airbus A321neo | B31: шт. | C31: 8 | D31: 3 | E31: 100 | F31: 6 | G31: 5 | H31: 100 | J31: [Ф] 10-Q 2К26, Firm Order and Option Aircraft
A32: Airbus A321XLR | B32: шт. | C32: 5 | D32: 15 | E32: 29 | F32: 5 | G32: 15 | H32: 29 | J32: [Ф] 10-Q 2К26, Firm Order and Option Aircraft
A33: Итого | B33: шт. | C33: =SUM(C28:C32) -> 121 | D33: =SUM(D28:D32) -> 73 | E33: =SUM(E28:E32) -> 342 | F33: =SUM(F28:F32) -> 63 | G33: =SUM(G28:G32) -> 90 | H33: =SUM(H28:H32) -> 383
A34: Boeing: ожидаемо / контрактно (2П26 + 2027) | B34: % | F34: =SUM(F28:G30)/SUM(C28:D30) -> 0.74846626 | J34: формула: доля контрактных поставок Boeing, которую UAL реально ожидает
A35: A350: 45 твёрдых заказов без графика поставок (10-K 2025). MAX 10 не сертифицирован — поставки сдвинуты на 2027+.
